{"initSeeds": {"ZN0": {"ZN0_midPrice": 110.546875, "Volatility_ZN0": 0.08524911233684787, "ZN0_lastTS": "2023_12_13_03", "ZN0_symbol": "@TYH24", "CL0_midPrice": 68.04, "Volatility_CL0": 0.3158808981136695, "CL0_symbol": "QCLF24", "CL0_lastTS": "2023_12_13_03", "ICE-US_CT0_midPrice": 81.12, "Volatility_ICE-US_CT0": 0.29655814123386914, "ICE-US_CT0_symbol": "@CTH24", "ICE-US_CT0_lastTS": "2023_12_13_02", "AUD=_midPrice": 0.65435, "Volatility_AUD=": 0.0010445271474599138, "AUD=_symbol": "AUDUSD.COMP", "AUD=_lastTS": "2023_12_13_03", "CAD=_midPrice": 1.3601926032726235, "Volatility_CAD=": 0.001278853273811173, "CAD=_symbol": "CADUSD.COMP", "CAD=_lastTS": "2023_12_13_03", "PL0_midPrice": 933.8, "Volatility_PL0": 3.4823616004660325, "PL0_symbol": "QPLF24", "PL0_lastTS": "2023_12_13_03", "ZN0_CL0_Move_uniDR_9_smoothSeed": -0.08905037434870725, "ZN0_CL0_Move_uniDR_9_zSeed": -0.009698146656146682, "ZN0_CL0_Move_uniDR_9_volSeed": 0.01815625317791899, "ZN0_PL0_Move_uniDR_9_smoothSeed": 0.27051844655338764, "ZN0_PL0_Move_uniDR_9_zSeed": 0.17791521006629848, "ZN0_PL0_Move_uniDR_9_volSeed": 0.1788163079276366, "ZN0_AUD=_Move_uniDR_35_smoothSeed": -4.865455476336033e-05, "ZN0_AUD=_Move_uniDR_35_zSeed": 8.486820594914314e-07, "ZN0_AUD=_Move_uniDR_35_volSeed": 2.639912207231946e-05, "ZN0_CAD=_Move_uniDR_18_smoothSeed": 6.118201533789934e-05, "ZN0_CAD=_Move_uniDR_18_zSeed": -4.589310188822771e-06, "ZN0_CAD=_Move_uniDR_18_volSeed": 4.945825734893516e-05, "ZN0_ICE-US_CT0_Move_uniDR_68_smoothSeed": -0.00075497745992491, "ZN0_ICE-US_CT0_Move_uniDR_68_zSeed": 0.0007942236526845408, "ZN0_ICE-US_CT0_Move_uniDR_68_volSeed": 0.005411126517955703}, "ZF0": {"ZF0_midPrice": 107.0703125, "Volatility_ZF0": 0.05363124953781031, "ZF0_lastTS": "2023_12_13_03", "ZF0_symbol": "@FVH24", "CL0_midPrice": 68.04, "Volatility_CL0": 0.3181647422784506, "CL0_symbol": "QCLF24", "CL0_lastTS": "2023_12_13_03", "PL0_midPrice": 933.8, "Volatility_PL0": 3.4070448520722696, "PL0_symbol": "QPLF24", "PL0_lastTS": "2023_12_13_03", "HO0_midPrice": 2.496, "Volatility_HO0": 0.01070565178230582, "HO0_symbol": "QHOF24", "HO0_lastTS": "2023_12_13_03", "NZD=_midPrice": 0.60891, "Volatility_NZD=": 0.0009789126128239604, "NZD=_symbol": "NZDUSD.COMP", "NZD=_lastTS": "2023_12_13_03", "ZF0_HO0_Move_uniDR_68_smoothSeed": -0.0010438414527702508, "ZF0_HO0_Move_uniDR_68_zSeed": -1.975607446559775e-05, "ZF0_HO0_Move_uniDR_68_volSeed": 0.000283023522201623, "ZF0_NZD=_Move_uniDR_6_smoothSeed": -0.0002571373508458513, "ZF0_NZD=_Move_uniDR_6_zSeed": -1.580413023159432e-05, "ZF0_NZD=_Move_uniDR_6_volSeed": 6.39724446440672e-05, "ZF0_PL0_Move_uniDR_9_smoothSeed": 0.37405549930110227, "ZF0_PL0_Move_uniDR_9_zSeed": 0.17965898914980966, "ZF0_PL0_Move_uniDR_9_volSeed": 0.1764166967805836, "ZF0_CL0_Move_uniDR_6_smoothSeed": -0.1468276650400001, "ZF0_CL0_Move_uniDR_6_zSeed": -0.020339354206909806, "ZF0_CL0_Move_uniDR_6_volSeed": 0.022493054302068716}, "FBTP0": {"FBTP0_midPrice": 116.38, "Volatility_FBTP0": 0.2300000571729479, "FBTP0_lastTS": "2023_12_12_14", "FBTP0_symbol": "BTPH24", "CL0_midPrice": 68.04, "Volatility_CL0": 0.4433528922348416, "CL0_symbol": "QCLF24", "CL0_lastTS": "2023_12_13_03", "ICE-EU_BRN0_midPrice": 72.62, "Volatility_ICE-EU_BRN0": 0.437555170526843, "ICE-EU_BRN0_symbol": "QBZG24", "ICE-EU_BRN0_lastTS": "2023_12_13_03", "FTI0_midPrice": 788.55, "Volatility_FTI0": 1.7874125443743039, "FTI0_symbol": "AEXZ23", "FTI0_lastTS": "2023_12_12_16", "ICE-LL_R0_midPrice": 98.67, "Volatility_ICE-LL_R0": 0.16001972376573087, "ICE-LL_R0_symbol": "LGH24", "ICE-LL_R0_lastTS": "2023_12_12_13", "ICE-EU_G0_midPrice": 719.25, "Volatility_ICE-EU_G0": 5.100574621478686, "ICE-EU_G0_symbol": "GASF24", "ICE-EU_G0_lastTS": "2023_12_13_03", "EUR=_midPrice": 1.07812, "Volatility_EUR=": 0.0016374064623067488, "EUR=_symbol": "EURUSD.COMP", "EUR=_lastTS": "2023_12_13_03", "FBTP0_ICE-LL_R0_Move_uniDR_68_smoothSeed": 0.01050634093111372, "FBTP0_ICE-LL_R0_Move_uniDR_68_zSeed": 0.0001160865217980892, "FBTP0_ICE-LL_R0_Move_uniDR_68_volSeed": 0.003260360930481788, "FBTP0_FTI0_VSR_uniDR_68_smoothSeed": 0.07331641771586421, "FBTP0_FTI0_VSR_uniDR_68_zSeed": 0.0020881625561581917, "FBTP0_FTI0_VSR_uniDR_68_volSeed": 0.027426866552666917, "FBTP0_CL0_VSR_uniDR_68_smoothSeed": -0.07092353361334623, "FBTP0_CL0_VSR_uniDR_68_zSeed": 4.642261923790624e-05, "FBTP0_CL0_VSR_uniDR_68_volSeed": 0.046429810573740196, "FBTP0_ICE-EU_G0_VSR_uniDR_35_smoothSeed": -0.13629243923410853, "FBTP0_ICE-EU_G0_VSR_uniDR_35_zSeed": -0.0009403015372747314, "FBTP0_ICE-EU_G0_VSR_uniDR_35_volSeed": 0.06389920471301844, "FBTP0_ICE-EU_BRN0_VSR_uniDR_68_smoothSeed": -0.08048929501501273, "FBTP0_ICE-EU_BRN0_VSR_uniDR_68_zSeed": -0.0001755268550372797, "FBTP0_ICE-EU_BRN0_VSR_uniDR_68_volSeed": 0.050400578220846134}, "AP0": {"AP0_midPrice": 7271.0, "Volatility_AP0": 12.853662484398304, "AP0_lastTS": "2023_12_13_02", "AP0_symbol": "SPIZ23", "AUD=_midPrice": 0.65435, "Volatility_AUD=": 0.0012777988515944058, "AUD=_symbol": "AUDUSD.COMP", "AUD=_lastTS": "2023_12_13_03", "JPY=_midPrice": 145.9534408523681, "Volatility_JPY=": 0.18325481246510225, "JPY=_symbol": "JPYUSD.COMP", "JPY=_lastTS": "2023_12_13_03", "FGBL0_midPrice": 135.14, "Volatility_FGBL0": 0.15393012500804634, "FGBL0_symbol": "BDH24", "FGBL0_lastTS": "2023_12_13_03", "ICE-LL_R0_midPrice": 98.67, "Volatility_ICE-LL_R0": 0.1250871895198291, "ICE-LL_R0_symbol": "LGH24", "ICE-LL_R0_lastTS": "2023_12_12_13", "ICE-US_KC0_midPrice": 185.45, "Volatility_ICE-US_KC0": 0.7813976130345391, "ICE-US_KC0_symbol": "@KCH24", "ICE-US_KC0_lastTS": "2023_12_12_14", "NQ0_midPrice": 16593.75, "Volatility_NQ0": 28.38419345800123, "NQ0_symbol": "@NQH24", "NQ0_lastTS": "2023_12_13_03", "ZS0_midPrice": 1319.75, "Volatility_ZS0": 3.9367963154880496, "ZS0_symbol": "@SF24", "ZS0_lastTS": "2023_12_13_03", "ZS1_midPrice": 1338.25, "Volatility_ZS1": 3.836655444185604, "ZS1_symbol": "@SH24", "ZS1_lastTS": "2023_12_13_03", "FBTS0_midPrice": 105.75, "Volatility_FBTS0": 0.0525985155964213, "FBTS0_symbol": "BTSH24", "FBTS0_lastTS": "2023_12_12_13", "AP0_FGBL0_Basis_uniDR_6_smoothSeed": -7119.013937315208, "AP0_FGBL0_Basis_uniDR_6_zSeed": -4032.2006568484267, "AP0_FGBL0_Basis_uniDR_6_volSeed": 686.5721061932218, "AP0_ICE-LL_R0_Move_uniDR_6_smoothSeed": 0.011345744674762065, "AP0_ICE-LL_R0_Move_uniDR_6_zSeed": 0.009454488618871361, "AP0_ICE-LL_R0_Move_uniDR_6_volSeed": 0.008321764479415449, "AP0_JPY=_Move_uniDR_35_smoothSeed": 0.013241343356409127, "AP0_JPY=_Move_uniDR_35_zSeed": 0.0002914980939085757, "AP0_JPY=_Move_uniDR_35_volSeed": 0.005298946534200491, "AP0_ICE-US_KC0_Move_uniDR_17_smoothSeed": 0.07905089160177806, "AP0_ICE-US_KC0_Move_uniDR_17_zSeed": 0.015417912849191055, "AP0_ICE-US_KC0_Move_uniDR_17_volSeed": 0.03241453209277472, "AP0_ZS1_Basis_uniDR_35_smoothSeed": -4765.15615132906, "AP0_ZS1_Basis_uniDR_35_zSeed": -468.10460875558, "AP0_ZS1_Basis_uniDR_35_volSeed": 65.12135698734303, "AP0_NQ0_VSR_uniDR_35_smoothSeed": 0.08403464635516539, "AP0_NQ0_VSR_uniDR_35_zSeed": 0.010822297682169522, "AP0_NQ0_VSR_uniDR_35_volSeed": 0.02881155251599793, "AP0_FBTS0_Move_uniDR_6_smoothSeed": -0.001088956504816912, "AP0_FBTS0_Move_uniDR_6_zSeed": -0.002248021055455735, "AP0_FBTS0_Move_uniDR_6_volSeed": 0.0031047094785870903}, "ES0": {"ES0_midPrice": 4701.5, "Volatility_ES0": 6.796293018338725, "ES0_lastTS": "2023_12_13_03", "ES0_symbol": "@ESH24", "FDAX0_midPrice": 16792.0, "Volatility_FDAX0": 28.994679801046072, "FDAX0_symbol": "DXMZ23", "FDAX0_lastTS": "2023_12_13_03", "FESX0_midPrice": 4536.0, "Volatility_FESX0": 8.339556124839694, "FESX0_symbol": "EXZ23", "FESX0_lastTS": "2023_12_13_03", "FCE0_midPrice": 7564.0, "Volatility_FCE0": 12.84586113067964, "FCE0_symbol": "MTZ23", "FCE0_lastTS": "2023_12_12_16", "FTI0_midPrice": 788.55, "Volatility_FTI0": 1.2852355127088337, "FTI0_symbol": "AEXZ23", "FTI0_lastTS": "2023_12_12_16", "ICE-LL_R0_midPrice": 98.67, "Volatility_ICE-LL_R0": 0.1138833797883938, "ICE-LL_R0_symbol": "LGH24", "ICE-LL_R0_lastTS": "2023_12_12_13", "ES0_FTI0_VSR_uniDR_5_smoothSeed": -0.051479894881423946, "ES0_FTI0_VSR_uniDR_5_zSeed": -0.033234137354624646, "ES0_FTI0_VSR_uniDR_5_volSeed": 0.05036300916584359, "ES0_FCE0_VSR_uniDR_5_smoothSeed": -0.07895436591524783, "ES0_FCE0_VSR_uniDR_5_zSeed": -0.0353657303343542, "ES0_FCE0_VSR_uniDR_5_volSeed": 0.05407671050082656, "ES0_FDAX0_VSR_uniDR_5_smoothSeed": -0.15685189582859776, "ES0_FDAX0_VSR_uniDR_5_zSeed": -0.06673497267813862, "ES0_FDAX0_VSR_uniDR_5_volSeed": 0.05494571960499245, "ES0_ICE-LL_R0_Move_uniDR_68_smoothSeed": 0.009348863272846992, "ES0_ICE-LL_R0_Move_uniDR_68_zSeed": 0.00022924046348259691, "ES0_ICE-LL_R0_Move_uniDR_68_volSeed": 0.0022313932890408853, "ES0_FESX0_VSR_uniDR_5_smoothSeed": -0.2229816052363719, "ES0_FESX0_VSR_uniDR_5_zSeed": -0.05208004636507761, "ES0_FESX0_VSR_uniDR_5_volSeed": 0.051272795999402355}, "FSMI0": {"FSMI0_midPrice": 11147.0, "Volatility_FSMI0": 24.68601577977844, "FSMI0_lastTS": "2023_12_13_03", "FSMI0_symbol": "SWZ23", "FBTS0_midPrice": 105.75, "Volatility_FBTS0": 0.05014879869690271, "FBTS0_symbol": "BTSH24", "FBTS0_lastTS": "2023_12_12_13", "CHF=_midPrice": 0.8765820877855726, "Volatility_CHF=": 0.0014656224782073994, "CHF=_symbol": "CHFUSD.COMP", "CHF=_lastTS": "2023_12_13_03", "NG0_midPrice": 2.253, "Volatility_NG0": 0.03606521494304247, "NG0_symbol": "QNGF24", "NG0_lastTS": "2023_12_13_03", "FSMI0_FBTS0_Move_uniDR_6_smoothSeed": -0.003430657515620871, "FSMI0_FBTS0_Move_uniDR_6_zSeed": -0.00261510791028641, "FSMI0_FBTS0_Move_uniDR_6_volSeed": 0.0031865738817334036, "FSMI0_NG0_Move_uniDR_6_smoothSeed": -0.009194634346658143, "FSMI0_NG0_Move_uniDR_6_zSeed": -0.0011081645113593427, "FSMI0_NG0_Move_uniDR_6_volSeed": 0.002654029464701207}, "FTI0": {"FTI0_midPrice": 788.55, "Volatility_FTI0": 1.7347207894393104, "FTI0_lastTS": "2023_12_12_16", "FTI0_symbol": "AEXZ23", "HE0_midPrice": 68.225, "Volatility_HE0": 0.3279525290598751, "HE0_symbol": "@HEG24", "HE0_lastTS": "2023_12_12_15", "FBTS0_midPrice": 105.75, "Volatility_FBTS0": 0.05769030959922696, "FBTS0_symbol": "BTSH24", "FBTS0_lastTS": "2023_12_12_13", "HE1_midPrice": 75.425, "Volatility_HE1": 0.39791636708902334, "HE1_symbol": "@HEJ24", "HE1_lastTS": "2023_12_12_15", "NG0_midPrice": 2.253, "Volatility_NG0": 0.03776210860174186, "NG0_symbol": "QNGF24", "NG0_lastTS": "2023_12_13_03", "ICE-US_KC0_midPrice": 185.45, "Volatility_ICE-US_KC0": 0.864114989246753, "ICE-US_KC0_symbol": "@KCH24", "ICE-US_KC0_lastTS": "2023_12_12_14", "EUR=_midPrice": 1.07812, "Volatility_EUR=": 0.0015537363750464394, "EUR=_symbol": "EURUSD.COMP", "EUR=_lastTS": "2023_12_13_03", "FTI0_FBTS0_Move_uniDR_5_smoothSeed": -0.0034958157036750347, "FTI0_FBTS0_Move_uniDR_5_zSeed": -0.0030316397407602336, "FTI0_FBTS0_Move_uniDR_5_volSeed": 0.003663707829282105, "FTI0_ICE-US_KC0_Move_uniDR_9_smoothSeed": 0.1702551634284073, "FTI0_ICE-US_KC0_Move_uniDR_9_zSeed": 0.027331781798272996, "FTI0_ICE-US_KC0_Move_uniDR_9_volSeed": 0.050672810038471926, "FTI0_HE1_Basis_uniDR_69_smoothSeed": -276.9307688879015, "FTI0_HE1_Basis_uniDR_69_zSeed": -7.531567472970425, "FTI0_HE1_Basis_uniDR_69_volSeed": 0.7814121960604468, "FTI0_NG0_Move_uniDR_35_smoothSeed": -0.0015090053441654265, "FTI0_NG0_Move_uniDR_35_zSeed": 3.2188512687807583e-05, "FTI0_NG0_Move_uniDR_35_volSeed": 0.001202519318431005}, "ALSI0": {"ALSI0_midPrice": 66603.0, "Volatility_ALSI0": 175.1759178479445, "ALSI0_lastTS": "2023_12_13_02", "ALSI0_symbol": "ALJZ23", "GC0_midPrice": 1988.3, "Volatility_GC0": 3.816164704961254, "GC0_symbol": "QGCG24", "GC0_lastTS": "2023_12_13_03", "ZN0_midPrice": 110.546875, "Volatility_ZN0": 0.12177820588944399, "ZN0_symbol": "@TYH24", "ZN0_lastTS": "2023_12_13_03", "ZAR=_midPrice": 19.02520011418925, "Volatility_ZAR=": 0.049015722411015254, "ZAR=_symbol": "ZARUSD.COMP", "ZAR=_lastTS": "2023_12_13_03", "AUD=_midPrice": 0.65435, "Volatility_AUD=": 0.0017061544124677209, "AUD=_symbol": "AUDUSD.COMP", "AUD=_lastTS": "2023_12_13_03", "ZF0_midPrice": 107.0703125, "Volatility_ZF0": 0.07467725606556114, "ZF0_symbol": "@FVH24", "ZF0_lastTS": "2023_12_13_03", "GC1_midPrice": 1979.3, "Volatility_GC1": 3.8237039759171263, "GC1_symbol": "QGCF24", "GC1_lastTS": "2023_12_13_03", "NQ0_midPrice": 16593.75, "Volatility_NQ0": 30.90191232838797, "NQ0_symbol": "@NQH24", "NQ0_lastTS": "2023_12_13_03", "ES0_midPrice": 4701.5, "Volatility_ES0": 8.51873776662344, "ES0_symbol": "@ESH24", "ES0_lastTS": "2023_12_13_03", "ALSI0_ZF0_Move_uniDR_18_smoothSeed": -0.01227253548212977, "ALSI0_ZF0_Move_uniDR_18_zSeed": -0.000978915971490453, "ALSI0_ZF0_Move_uniDR_18_volSeed": 0.0029658019280692565, "ALSI0_GC1_Basis_uniDR_8_smoothSeed": -62124.646493999964, "ALSI0_GC1_Basis_uniDR_8_zSeed": -12001.958607139395, "ALSI0_GC1_Basis_uniDR_8_volSeed": 1158.852281486837, "ALSI0_ES0_Move_uniDR_18_smoothSeed": 0.8281515782069987, "ALSI0_ES0_Move_uniDR_18_zSeed": 0.11184236649346828, "ALSI0_ES0_Move_uniDR_18_volSeed": 0.31336788580139613, "ALSI0_NQ0_Move_uniDR_18_smoothSeed": 6.067160587927945, "ALSI0_NQ0_Move_uniDR_18_zSeed": 0.6837852583903605, "ALSI0_NQ0_Move_uniDR_18_volSeed": 1.0647037934735089, "ALSI0_AUD=_VSR_uniDR_69_smoothSeed": 0.08978539183293989, "ALSI0_AUD=_VSR_uniDR_69_zSeed": 0.0018339531508597031, "ALSI0_AUD=_VSR_uniDR_69_volSeed": 0.01859872087805825, "ALSI0_ZN0_Move_uniDR_18_smoothSeed": -0.018531187613194937, "ALSI0_ZN0_Move_uniDR_18_zSeed": -0.0015401166317779446, "ALSI0_ZN0_Move_uniDR_18_volSeed": 0.004802514405875418}, "ZC0": {"ZC0_midPrice": 484.25, "Volatility_ZC0": 2.089734033688845, "ZC0_lastTS": "2023_12_13_03", "ZC0_symbol": "@CH24", "CNH=_midPrice": 7.199789996525381, "Volatility_CNH=": 0.004421653427479307, "CNH=_symbol": "CNHUSD.COMP", "CNH=_lastTS": "2023_12_13_03", "RB0_midPrice": 1.9735, "Volatility_RB0": 0.010440885487055171, "RB0_symbol": "QRBF24", "RB0_lastTS": "2023_12_13_03", "ZC1_midPrice": 484.25, "Volatility_ZC1": 1.812377405514906, "ZC1_symbol": "@CH24", "ZC1_lastTS": "2023_12_13_03", "ZC0_ZC1_Basis_uniDR_6_smoothSeed": -0.001927666893049269, "ZC0_ZC1_Basis_uniDR_6_zSeed": 0.0001225863753130694, "ZC0_ZC1_Basis_uniDR_6_volSeed": 0.04961250155447711, "ZC0_CNH=_Move_uniDR_68_smoothSeed": 8.607340346509072e-05, "ZC0_CNH=_Move_uniDR_68_zSeed": 3.4359006743220895e-06, "ZC0_CNH=_Move_uniDR_68_volSeed": 0.00011033286571786855, "ZC0_RB0_Move_uniDR_38_smoothSeed": -0.0011547842686317894, "ZC0_RB0_Move_uniDR_38_zSeed": -2.0948626765831865e-05, "ZC0_RB0_Move_uniDR_38_volSeed": 0.00029276979316318115}, "ZS0": {"ZS0_midPrice": 1319.75, "Volatility_ZS0": 4.42680446587044, "ZS0_lastTS": "2023_12_13_03", "ZS0_symbol": "@SF24", "IND0_midPrice": 126580.0, "Volatility_IND0": 292.01053253170363, "IND0_symbol": "INDZ23", "IND0_lastTS": "2023_12_12_23", "XT0_midPrice": 95.703, "Volatility_XT0": 0.012391177005284847, "XT0_symbol": "XTZ23", "XT0_lastTS": "2023_12_13_02", "PA0_midPrice": 979.5, "Volatility_PA0": 9.146364951121999, "PA0_symbol": "QPAH24", "PA0_lastTS": "2023_12_13_02", "NQ0_midPrice": 16593.75, "Volatility_NQ0": 28.2049105667048, "NQ0_symbol": "@NQH24", "NQ0_lastTS": "2023_12_13_03", "ZS1_midPrice": 1338.25, "Volatility_ZS1": 3.929407950347353, "ZS1_symbol": "@SH24", "ZS1_lastTS": "2023_12_13_03", "ZS0_PA0_VSR_uniDR_68_smoothSeed": -0.0018596129448779333, "ZS0_PA0_VSR_uniDR_68_zSeed": -0.0014456655096421176, "ZS0_PA0_VSR_uniDR_68_volSeed": 0.0278207119131781, "ZS0_IND0_Move_uniDR_9_smoothSeed": -11.023241263992938, "ZS0_IND0_Move_uniDR_9_zSeed": -1.6957840347969064, "ZS0_IND0_Move_uniDR_9_volSeed": 16.740643302821546, "ZS0_NQ0_VSR_uniDR_68_smoothSeed": 0.10353830537251249, "ZS0_NQ0_VSR_uniDR_68_zSeed": 0.002900276881848249, "ZS0_NQ0_VSR_uniDR_68_volSeed": 0.029013793586477297, "ZS0_ZS1_Basis_uniDR_6_smoothSeed": -0.047770711412763456, "ZS0_ZS1_Basis_uniDR_6_zSeed": 0.02597812798115049, "ZS0_ZS1_Basis_uniDR_6_volSeed": 0.06560248955770585, "ZS0_XT0_VSR_uniDR_68_smoothSeed": 0.010291294932063998, "ZS0_XT0_VSR_uniDR_68_zSeed": -0.0017981780956038906, "ZS0_XT0_VSR_uniDR_68_volSeed": 0.034603560690253665}, "ZM0": {"ZM0_midPrice": 404.6, "Volatility_ZM0": 1.6469125405584697, "ZM0_lastTS": "2023_12_13_03", "ZM0_symbol": "@SMF24", "YM0_midPrice": 36631.0, "Volatility_YM0": 66.89978174975612, "YM0_symbol": "@YMZ23", "YM0_lastTS": "2023_12_13_03", "FESX0_midPrice": 4536.0, "Volatility_FESX0": 9.149511690036258, "FESX0_symbol": "EXZ23", "FESX0_lastTS": "2023_12_13_03", "FSMI0_midPrice": 11147.0, "Volatility_FSMI0": 21.037573504952917, "FSMI0_symbol": "SWZ23", "FSMI0_lastTS": "2023_12_13_03", "HG0_midPrice": 3.769, "Volatility_HG0": 0.01023932907623463, "HG0_symbol": "QHGH24", "HG0_lastTS": "2023_12_13_03", "FCE0_midPrice": 7564.0, "Volatility_FCE0": 14.064752678754092, "FCE0_symbol": "MTZ23", "FCE0_lastTS": "2023_12_12_16", "FTI0_midPrice": 788.55, "Volatility_FTI0": 1.4051166340530032, "FTI0_symbol": "AEXZ23", "FTI0_lastTS": "2023_12_12_16", "ICE-US_SB0_midPrice": 22.41, "Volatility_ICE-US_SB0": 0.06639157055349489, "ICE-US_SB0_symbol": "@SBH24", "ICE-US_SB0_lastTS": "2023_12_12_13", "CNH=_midPrice": 7.199789996525381, "Volatility_CNH=": 0.004370681663054765, "CNH=_symbol": "CNHUSD.COMP", "CNH=_lastTS": "2023_12_13_03", "ZM0_HG0_VSR_uniDR_18_smoothSeed": 0.07983648726024833, "ZM0_HG0_VSR_uniDR_18_zSeed": 0.0031169015138364994, "ZM0_HG0_VSR_uniDR_18_volSeed": 0.054475204025341596, "ZM0_FESX0_VSR_uniDR_68_smoothSeed": 0.09535177090395948, "ZM0_FESX0_VSR_uniDR_68_zSeed": 0.0027100917565412394, "ZM0_FESX0_VSR_uniDR_68_volSeed": 0.02743764085689267, "ZM0_FSMI0_VSR_uniDR_68_smoothSeed": 0.06078257081424361, "ZM0_FSMI0_VSR_uniDR_68_zSeed": 0.00131663304166549, "ZM0_FSMI0_VSR_uniDR_68_volSeed": 0.027545542879009993, "ZM0_FCE0_VSR_uniDR_68_smoothSeed": 0.10675291519252877, "ZM0_FCE0_VSR_uniDR_68_zSeed": 0.003249135909850926, "ZM0_FCE0_VSR_uniDR_68_volSeed": 0.026350985993831025, "ZM0_ICE-US_SB0_VSR_uniDR_68_smoothSeed": -0.14573505120942112, "ZM0_ICE-US_SB0_VSR_uniDR_68_zSeed": -0.0069630208744499485, "ZM0_ICE-US_SB0_VSR_uniDR_68_volSeed": 0.030454323462900754, "ZM0_FTI0_VSR_uniDR_35_smoothSeed": 0.1804590947702258, "ZM0_FTI0_VSR_uniDR_35_zSeed": 0.00808203548983413, "ZM0_FTI0_VSR_uniDR_35_volSeed": 0.03977827447563989, "ZM0_YM0_VSR_uniDR_18_smoothSeed": 0.2411015909463016, "ZM0_YM0_VSR_uniDR_18_zSeed": 0.01510476893616226, "ZM0_YM0_VSR_uniDR_18_volSeed": 0.055144919168907826, "ZM0_CNH=_VSR_uniDR_68_smoothSeed": 0.061066413726740494, "ZM0_CNH=_VSR_uniDR_68_zSeed": 0.0010183549886703322, "ZM0_CNH=_VSR_uniDR_68_volSeed": 0.03663461720636189}, "ZW0": {"ZW0_midPrice": 625.25, "Volatility_ZW0": 3.671120940725688, "ZW0_lastTS": "2023_12_13_03", "ZW0_symbol": "@WH24", "ICE-LL_Z0_midPrice": 7595.0, "Volatility_ICE-LL_Z0": 10.067231355976467, "ICE-LL_Z0_symbol": "TUKZ23", "ICE-LL_Z0_lastTS": "2023_12_12_05", "HE0_midPrice": 68.225, "Volatility_HE0": 0.27253231643080034, "HE0_symbol": "@HEG24", "HE0_lastTS": "2023_12_12_15", "ICE-LX_C0_midPrice": 3545.0, "Volatility_ICE-LX_C0": 5.85729289026591, "ICE-LX_C0_symbol": "QCH24", "ICE-LX_C0_lastTS": "2023_12_12_12", "ZW0_ICE-LL_Z0_Move_uniDR_35_smoothSeed": 0.7445018501255867, "ZW0_ICE-LL_Z0_Move_uniDR_35_zSeed": 0.06602471243791677, "ZW0_ICE-LL_Z0_Move_uniDR_35_volSeed": 0.2998192670372989, "ZW0_ICE-LX_C0_Move_uniDR_5_smoothSeed": 0.007425549795237109, "ZW0_ICE-LX_C0_Move_uniDR_5_zSeed": 0.5292268166466401, "ZW0_ICE-LX_C0_Move_uniDR_5_volSeed": 0.49022855558254375, "ZW0_HE0_VSR_uniDR_68_smoothSeed": -0.01132908656064266, "ZW0_HE0_VSR_uniDR_68_zSeed": 0.0005350994819333249, "ZW0_HE0_VSR_uniDR_68_volSeed": 0.030447931669742724}, "KE0": {"KE0_midPrice": 658.25, "Volatility_KE0": 3.735446221157407, "KE0_lastTS": "2023_12_13_02", "KE0_symbol": "@KWH24", "ICE-LX_C0_midPrice": 3545.0, "Volatility_ICE-LX_C0": 5.8391183351395055, "ICE-LX_C0_symbol": "QCH24", "ICE-LX_C0_lastTS": "2023_12_12_12", "W0_midPrice": 637.9, "Volatility_W0": 1.427481314418857, "W0_symbol": "QWH24", "W0_lastTS": "2023_12_12_13", "ZAR=_midPrice": 19.02520011418925, "Volatility_ZAR=": 0.03343496707502222, "ZAR=_symbol": "ZARUSD.COMP", "ZAR=_lastTS": "2023_12_13_03", "KE0_ZAR=_Move_uniDR_38_smoothSeed": 0.0017947658163744553, "KE0_ZAR=_Move_uniDR_38_zSeed": 0.00014822942494217416, "KE0_ZAR=_Move_uniDR_38_volSeed": 0.0008731730160505716, "KE0_ICE-LX_C0_Move_uniDR_18_smoothSeed": 0.49557454298573805, "KE0_ICE-LX_C0_Move_uniDR_18_zSeed": 0.22025566329335605, "KE0_ICE-LX_C0_Move_uniDR_18_volSeed": 0.2490164606438929, "KE0_W0_Move_uniDR_5_smoothSeed": 0.05758498887632382, "KE0_W0_Move_uniDR_5_zSeed": -0.13831416392466933, "KE0_W0_Move_uniDR_5_volSeed": 0.11197057654137833}, "LE0": {"LE0_midPrice": 168.575, "Volatility_LE0": 0.4432587038425685, "LE0_lastTS": "2023_12_12_15", "LE0_symbol": "@LEG24", "FESX0_midPrice": 4536.0, "Volatility_FESX0": 13.506573555383223, "FESX0_symbol": "EXZ23", "FESX0_lastTS": "2023_12_13_03", "FCE0_midPrice": 7564.0, "Volatility_FCE0": 19.21287826524716, "FCE0_symbol": "MTZ23", "FCE0_lastTS": "2023_12_12_16", "KE0_midPrice": 658.25, "Volatility_KE0": 4.602593033615261, "KE0_symbol": "@KWH24", "KE0_lastTS": "2023_12_13_02", "EUR=_midPrice": 1.07812, "Volatility_EUR=": 0.001984216730452375, "EUR=_symbol": "EURUSD.COMP", "EUR=_lastTS": "2023_12_13_03", "ICE-US_CC0_midPrice": 4465.0, "Volatility_ICE-US_CC0": 15.469996580411435, "ICE-US_CC0_symbol": "@CCZ23", "ICE-US_CC0_lastTS": "2023_12_12_14", "VX0_midPrice": 12.35, "Volatility_VX0": 0.354719852206146, "VX0_symbol": "@VXZ23", "VX0_lastTS": "2023_12_13_02", "LE0_FCE0_Move_uniDR_5_smoothSeed": 2.0132801663410005, "LE0_FCE0_Move_uniDR_5_zSeed": 0.7312811971781062, "LE0_FCE0_Move_uniDR_5_volSeed": 1.3505415406235828, "LE0_VX0_VSR_uniDR_5_smoothSeed": -0.7942999134340651, "LE0_VX0_VSR_uniDR_5_zSeed": -0.1269256937632722, "LE0_VX0_VSR_uniDR_5_volSeed": 0.1317186118374683, "LE0_ICE-US_CC0_VSR_uniDR_5_smoothSeed": -0.05861466222157838, "LE0_ICE-US_CC0_VSR_uniDR_5_zSeed": 0.04424029660151321, "LE0_ICE-US_CC0_VSR_uniDR_5_volSeed": 0.11903315860209869, "LE0_EUR=_VSR_uniDR_79_smoothSeed": -0.07934815152563675, "LE0_EUR=_VSR_uniDR_79_zSeed": -0.0006372916737223454, "LE0_EUR=_VSR_uniDR_79_volSeed": 0.04621016559494151, "LE0_FESX0_Move_uniDR_5_smoothSeed": 1.668349130551527, "LE0_FESX0_Move_uniDR_5_zSeed": 0.488705158727266, "LE0_FESX0_Move_uniDR_5_volSeed": 0.9768505373043922, "LE0_KE0_VSR_uniDR_79_smoothSeed": -0.08658347975799442, "LE0_KE0_VSR_uniDR_79_zSeed": -0.0007194124368365876, "LE0_KE0_VSR_uniDR_79_volSeed": 0.036147130808099864}, "CL0": {"CL0_midPrice": 68.04, "Volatility_CL0": 0.3194977301672251, "CL0_lastTS": "2023_12_13_03", "CL0_symbol": "QCLF24", "ALSI0_midPrice": 66603.0, "Volatility_ALSI0": 103.63768646259507, "ALSI0_symbol": "ALJZ23", "ALSI0_lastTS": "2023_12_13_02", "SGD=_midPrice": 1.3449200002513924, "Volatility_SGD=": 0.0008824305271568204, "SGD=_symbol": "SGDUSD.COMP", "SGD=_lastTS": "2023_12_13_03", "THB=_midPrice": 35.81900000229242, "Volatility_THB=": 0.036013694819146944, "THB=_symbol": "THBUSD.COMP", "THB=_lastTS": "2023_12_13_03", "ZF0_midPrice": 107.0703125, "Volatility_ZF0": 0.05384033323689724, "ZF0_symbol": "@FVH24", "ZF0_lastTS": "2023_12_13_03", "CL0_ZF0_VSR_uniDR_68_smoothSeed": 0.0337420229789971, "CL0_ZF0_VSR_uniDR_68_zSeed": -0.004018777207880976, "CL0_ZF0_VSR_uniDR_68_volSeed": 0.04248805886628995, "CL0_THB=_Move_uniDR_35_smoothSeed": 0.003321246079563487, "CL0_THB=_Move_uniDR_35_zSeed": 0.00045141404698918606, "CL0_THB=_Move_uniDR_35_volSeed": 0.0008615927212287696, "CL0_ALSI0_Move_uniDR_6_smoothSeed": -44.901008263854536, "CL0_ALSI0_Move_uniDR_6_zSeed": -15.812197428088002, "CL0_ALSI0_Move_uniDR_6_volSeed": 7.284315308999363, "CL0_SGD=_Move_uniDR_68_smoothSeed": 1.6971988197829668e-05, "CL0_SGD=_Move_uniDR_68_zSeed": -7.405231174123959e-08, "CL0_SGD=_Move_uniDR_68_volSeed": 1.7403720454666065e-05}, "HO0": {"HO0_midPrice": 2.496, "Volatility_HO0": 0.010676333213600975, "HO0_lastTS": "2023_12_13_03", "HO0_symbol": "QHOF24", "ALSI0_midPrice": 66603.0, "Volatility_ALSI0": 100.68244311670783, "ALSI0_symbol": "ALJZ23", "ALSI0_lastTS": "2023_12_13_02", "ICE-US_CC0_midPrice": 4465.0, "Volatility_ICE-US_CC0": 9.708506201522711, "ICE-US_CC0_symbol": "@CCZ23", "ICE-US_CC0_lastTS": "2023_12_12_14", "W0_midPrice": 637.9, "Volatility_W0": 1.3394442652803984, "W0_symbol": "QWH24", "W0_lastTS": "2023_12_12_13", "HO0_ICE-US_CC0_VSR_uniDR_68_smoothSeed": 0.24718501816003605, "HO0_ICE-US_CC0_VSR_uniDR_68_zSeed": 0.010819743204355612, "HO0_ICE-US_CC0_VSR_uniDR_68_volSeed": 0.030379803160993767, "HO0_W0_VSR_uniDR_68_smoothSeed": 0.060019323885584744, "HO0_W0_VSR_uniDR_68_zSeed": -0.001973213771734669, "HO0_W0_VSR_uniDR_68_volSeed": 0.030209956949231353, "HO0_ALSI0_Move_uniDR_8_smoothSeed": -33.67044351550852, "HO0_ALSI0_Move_uniDR_8_zSeed": -7.596111192322285, "HO0_ALSI0_Move_uniDR_8_volSeed": 6.043114839613804}, "RS0": {"RS0_midPrice": 671.0, "Volatility_RS0": 2.3063553650626716, "RS0_lastTS": "2023_12_13_02", "RS0_symbol": "@RSH24", "CONF0_midPrice": 150.67, "Volatility_CONF0": 0.14917821466257344, "CONF0_symbol": "COH24", "CONF0_lastTS": "2023_12_12_07", "HG0_midPrice": 3.769, "Volatility_HG0": 0.01161651303440204, "HG0_symbol": "QHGH24", "HG0_lastTS": "2023_12_13_03", "AUD=_midPrice": 0.65435, "Volatility_AUD=": 0.0013267066281385956, "AUD=_symbol": "AUDUSD.COMP", "AUD=_lastTS": "2023_12_13_03", "KE0_midPrice": 658.25, "Volatility_KE0": 3.2520829450223414, "KE0_symbol": "@KWH24", "KE0_lastTS": "2023_12_13_02", "CAD=_midPrice": 1.3601926032726235, "Volatility_CAD=": 0.001624803237804364, "CAD=_symbol": "CADUSD.COMP", "CAD=_lastTS": "2023_12_13_03", "ZC0_midPrice": 484.25, "Volatility_ZC0": 1.7505599737992201, "ZC0_symbol": "@CH24", "ZC0_lastTS": "2023_12_13_03", "ZW0_midPrice": 625.25, "Volatility_ZW0": 3.2626634845667892, "ZW0_symbol": "@WH24", "ZW0_lastTS": "2023_12_13_03", "CNH=_midPrice": 7.199789996525381, "Volatility_CNH=": 0.00524303404629107, "CNH=_symbol": "CNHUSD.COMP", "CNH=_lastTS": "2023_12_13_03", "RS0_ZW0_Move_uniDR_5_smoothSeed": 0.3715163454032998, "RS0_ZW0_Move_uniDR_5_zSeed": -0.12783280172810357, "RS0_ZW0_Move_uniDR_5_volSeed": 0.254148427339397, "RS0_AUD=_Move_uniDR_68_smoothSeed": -6.197493195465459e-05, "RS0_AUD=_Move_uniDR_68_zSeed": -1.0849068831749424e-06, "RS0_AUD=_Move_uniDR_68_volSeed": 2.38853623314782e-05, "RS0_CNH=_VSR_uniDR_68_smoothSeed": 0.05786192884813153, "RS0_CNH=_VSR_uniDR_68_zSeed": 0.0007499374925210524, "RS0_CNH=_VSR_uniDR_68_volSeed": 0.04298184916389146, "RS0_KE0_Move_uniDR_5_smoothSeed": 0.8813154961092504, "RS0_KE0_Move_uniDR_5_zSeed": 0.0022883001889703464, "RS0_KE0_Move_uniDR_5_volSeed": 0.2442660001530585, "RS0_HG0_Move_uniDR_68_smoothSeed": -4.422120176042854e-05, "RS0_HG0_Move_uniDR_68_zSeed": 2.2793748877296685e-05, "RS0_HG0_Move_uniDR_68_volSeed": 0.00021462496009008026, "RS0_CONF0_VSR_uniDR_17_smoothSeed": 0.15224682172415557, "RS0_CONF0_VSR_uniDR_17_zSeed": -0.019411577221102715, "RS0_CONF0_VSR_uniDR_17_volSeed": 0.06473307360697506, "RS0_ZC0_Move_uniDR_5_smoothSeed": 0.03797223962931413, "RS0_ZC0_Move_uniDR_5_zSeed": -0.06260626654354856, "RS0_ZC0_Move_uniDR_5_volSeed": 0.12943662714982943}, "W0": {"W0_midPrice": 637.9, "Volatility_W0": 2.025398453397788, "W0_lastTS": "2023_12_12_13", "W0_symbol": "QWH24", "KE0_midPrice": 658.25, "Volatility_KE0": 4.036301338561442, "KE0_symbol": "@KWH24", "KE0_lastTS": "2023_12_13_02", "ECO0_midPrice": 439.25, "Volatility_ECO0": 2.267838863703597, "ECO0_symbol": "PGG24", "ECO0_lastTS": "2023_12_12_13", "RB0_midPrice": 1.9735, "Volatility_RB0": 0.01429827134819376, "RB0_symbol": "QRBF24", "RB0_lastTS": "2023_12_13_03", "W0_KE0_Move_uniDR_5_smoothSeed": 1.9560573642597974, "W0_KE0_Move_uniDR_5_zSeed": 0.006367848441602441, "W0_KE0_Move_uniDR_5_volSeed": 0.3166979000460251, "W0_RB0_Move_uniDR_8_smoothSeed": -0.004865028836593854, "W0_RB0_Move_uniDR_8_zSeed": -0.00023951754649237906, "W0_RB0_Move_uniDR_8_volSeed": 0.0009145371313889209, "W0_ECO0_Move_uniDR_5_smoothSeed": -0.6071645283851906, "W0_ECO0_Move_uniDR_5_zSeed": 0.01121734025700264, "W0_ECO0_Move_uniDR_5_volSeed": 0.1978328213149975}, "ICE-US_CT0": {"ICE-US_CT0_midPrice": 81.12, "Volatility_ICE-US_CT0": 0.35891792933506644, "ICE-US_CT0_lastTS": "2023_12_13_02", "ICE-US_CT0_symbol": "@CTH24", "CL0_midPrice": 68.04, "Volatility_CL0": 0.3835786538168603, "CL0_symbol": "QCLF24", "CL0_lastTS": "2023_12_13_03", "ICE-EU_BRN0_midPrice": 72.62, "Volatility_ICE-EU_BRN0": 0.3712334240148842, "ICE-EU_BRN0_symbol": "QBZG24", "ICE-EU_BRN0_lastTS": "2023_12_13_03", "ZM0_midPrice": 404.6, "Volatility_ZM0": 1.5072569965676323, "ZM0_symbol": "@SMF24", "ZM0_lastTS": "2023_12_13_03", "ZF0_midPrice": 107.0703125, "Volatility_ZF0": 0.06256041042616643, "ZF0_symbol": "@FVH24", "ZF0_lastTS": "2023_12_13_03", "ZT0_midPrice": 102.14453125, "Volatility_ZT0": 0.021958551650287244, "ZT0_symbol": "@TUH24", "ZT0_lastTS": "2023_12_13_03", "ICE-US_MME0_midPrice": 971.8, "Volatility_ICE-US_MME0": 3.0066069178309376, "ICE-US_MME0_symbol": "MEFZ23", "ICE-US_MME0_lastTS": "2023_12_13_01", "ICE-EU_G0_midPrice": 719.25, "Volatility_ICE-EU_G0": 4.028621268499384, "ICE-EU_G0_symbol": "GASF24", "ICE-EU_G0_lastTS": "2023_12_13_03", "FESB0_midPrice": 118.5, "Volatility_FESB0": 0.4674572369157084, "FESB0_symbol": "SXZ23", "FESB0_lastTS": "2023_12_13_03", "ICE-US_CT0_ZF0_Move_uniDR_68_smoothSeed": -0.00205463657115266, "ICE-US_CT0_ZF0_Move_uniDR_68_zSeed": -8.110655935987323e-05, "ICE-US_CT0_ZF0_Move_uniDR_68_volSeed": 0.0013770801757582312, "ICE-US_CT0_ZM0_Move_uniDR_68_smoothSeed": -0.05503638646563085, "ICE-US_CT0_ZM0_Move_uniDR_68_zSeed": -0.0021043123162073703, "ICE-US_CT0_ZM0_Move_uniDR_68_volSeed": 0.0386358662623645, "ICE-US_CT0_CL0_VSR_uniDR_18_smoothSeed": -0.1555911680576957, "ICE-US_CT0_CL0_VSR_uniDR_18_zSeed": -0.01647588692621011, "ICE-US_CT0_CL0_VSR_uniDR_18_volSeed": 0.04601052659412023, "ICE-US_CT0_ICE-EU_BRN0_VSR_uniDR_18_smoothSeed": -0.17326008343513885, "ICE-US_CT0_ICE-EU_BRN0_VSR_uniDR_18_zSeed": -0.01765460992458306, "ICE-US_CT0_ICE-EU_BRN0_VSR_uniDR_18_volSeed": 0.047255399695050083, "ICE-US_CT0_ICE-EU_G0_VSR_uniDR_18_smoothSeed": -0.18822351069038845, "ICE-US_CT0_ICE-EU_G0_VSR_uniDR_18_zSeed": -0.024584520000251294, "ICE-US_CT0_ICE-EU_G0_VSR_uniDR_18_volSeed": 0.04812039342680347, "ICE-US_CT0_ICE-US_MME0_VSR_uniDR_5_smoothSeed": -0.23403084571845975, "ICE-US_CT0_ICE-US_MME0_VSR_uniDR_5_zSeed": -0.006130453546104244, "ICE-US_CT0_ICE-US_MME0_VSR_uniDR_5_volSeed": 0.0912731036587845, "ICE-US_CT0_FESB0_VSR_uniDR_5_smoothSeed": 0.03430002740306355, "ICE-US_CT0_FESB0_VSR_uniDR_5_zSeed": -0.008459915927213466, "ICE-US_CT0_FESB0_VSR_uniDR_5_volSeed": 0.09327648102894577, "ICE-US_CT0_ZT0_Move_uniDR_68_smoothSeed": -0.0009661975879561171, "ICE-US_CT0_ZT0_Move_uniDR_68_zSeed": -4.219942932668786e-05, "ICE-US_CT0_ZT0_Move_uniDR_68_volSeed": 0.000525167537155534}, "ICE-EU_G0": {"ICE-EU_G0_midPrice": 719.25, "Volatility_ICE-EU_G0": 3.5824913022921527, "ICE-EU_G0_lastTS": "2023_12_13_03", "ICE-EU_G0_symbol": "GASF24", "ALSI0_midPrice": 66603.0, "Volatility_ALSI0": 106.65096253452663, "ALSI0_symbol": "ALJZ23", "ALSI0_lastTS": "2023_12_13_02", "ZN0_midPrice": 110.546875, "Volatility_ZN0": 0.0881028721085856, "ZN0_symbol": "@TYH24", "ZN0_lastTS": "2023_12_13_03", "ZL0_midPrice": 50.34, "Volatility_ZL0": 0.18998255114569063, "ZL0_symbol": "@BOF24", "ZL0_lastTS": "2023_12_13_03", "W0_midPrice": 637.9, "Volatility_W0": 1.420681117540229, "W0_symbol": "QWH24", "W0_lastTS": "2023_12_12_13", "ICE-LX_C0_midPrice": 3545.0, "Volatility_ICE-LX_C0": 5.717492645847259, "ICE-LX_C0_symbol": "QCH24", "ICE-LX_C0_lastTS": "2023_12_12_12", "ICE-EU_G0_ALSI0_Move_uniDR_6_smoothSeed": -48.67832956393096, "ICE-EU_G0_ALSI0_Move_uniDR_6_zSeed": -15.989734732919558, "ICE-EU_G0_ALSI0_Move_uniDR_6_volSeed": 7.4757483809511385, "ICE-EU_G0_ICE-LX_C0_VSR_uniDR_68_smoothSeed": 0.05726335615564315, "ICE-EU_G0_ICE-LX_C0_VSR_uniDR_68_zSeed": 0.00040014909344411397, "ICE-EU_G0_ICE-LX_C0_VSR_uniDR_68_volSeed": 0.03771751629202296, "ICE-EU_G0_W0_VSR_uniDR_68_smoothSeed": 0.004483246301752109, "ICE-EU_G0_W0_VSR_uniDR_68_zSeed": -0.0032122425821854853, "ICE-EU_G0_W0_VSR_uniDR_68_volSeed": 0.03191257694396586, "ICE-EU_G0_ZN0_VSR_uniDR_35_smoothSeed": 0.14411504113147836, "ICE-EU_G0_ZN0_VSR_uniDR_35_zSeed": 0.0014708858367389072, "ICE-EU_G0_ZN0_VSR_uniDR_35_volSeed": 0.05869603734753553, "ICE-EU_G0_ZL0_Move_uniDR_68_smoothSeed": -0.0006763424091835666, "ICE-EU_G0_ZL0_Move_uniDR_68_zSeed": 0.00037572614389134323, "ICE-EU_G0_ZL0_Move_uniDR_68_volSeed": 0.0040706175166526064}, "ICE-US_KC0": {"ICE-US_KC0_midPrice": 185.45, "Volatility_ICE-US_KC0": 1.0061717408671078, "ICE-US_KC0_lastTS": "2023_12_12_14", "ICE-US_KC0_symbol": "@KCH24", "NG0_midPrice": 2.253, "Volatility_NG0": 0.04363868998065887, "NG0_symbol": "QNGF24", "NG0_lastTS": "2023_12_13_03", "RB0_midPrice": 1.9735, "Volatility_RB0": 0.01449582326574565, "RB0_symbol": "QRBF24", "RB0_lastTS": "2023_12_13_03", "RS0_midPrice": 671.0, "Volatility_RS0": 2.699740625648113, "RS0_symbol": "@RSH24", "RS0_lastTS": "2023_12_13_02", "RS1_midPrice": 671.0, "Volatility_RS1": 2.627351206757524, "RS1_symbol": "@RSH24", "RS1_lastTS": "2023_12_13_02", "ICE-US_KC0_RB0_Move_uniDR_35_smoothSeed": -0.0018783549290585975, "ICE-US_KC0_RB0_Move_uniDR_35_zSeed": -4.784555632796517e-05, "ICE-US_KC0_RB0_Move_uniDR_35_volSeed": 0.00041077973849737106, "ICE-US_KC0_NG0_Move_uniDR_35_smoothSeed": -0.001840276117340571, "ICE-US_KC0_NG0_Move_uniDR_35_zSeed": 1.1041669467513933e-06, "ICE-US_KC0_NG0_Move_uniDR_35_volSeed": 0.0013978730143291498, "ICE-US_KC0_RS1_Basis_uniDR_69_smoothSeed": 139.78253403381044, "ICE-US_KC0_RS1_Basis_uniDR_69_zSeed": 2.490598348251978, "ICE-US_KC0_RS1_Basis_uniDR_69_volSeed": 0.21477190067792554}}, "initPositions": {"ZN0": 0, "ZF0": 0, "FBTP0": 0, "AP0": 0, "ES0": 0, "FSMI0": 0, "FTI0": 0, "ALSI0": 0, "ZC0": 0, "ZS0": 0, "ZM0": 0, "ZW0": 0, "KE0": 0, "LE0": 0, "CL0": 0, "HO0": 0, "RS0": 0, "W0": 0, "ICE-US_CT0": -1, "ICE-EU_G0": 0, "ICE-US_KC0": 0}, "trades": {"ZN0": 0, "ZF0": 0, "FBTP0": 0, "AP0": 0, "ES0": 0, "FSMI0": 0, "FTI0": -1, "ALSI0": 5, "ZC0": 0, "ZS0": 0, "ZM0": 0, "ZW0": 0, "KE0": -1, "LE0": 0, "CL0": 0, "HO0": 0, "RS0": 0, "W0": 0, "ICE-US_CT0": 0, "ICE-EU_G0": 0, "ICE-US_KC0": 0}, "seedDump": {"ZN0": {"ZN0_midPrice": 110.6875, "Volatility_ZN0": 0.08531967444249587, "ZN0_lastTS": "2023_12_13_04", "ZN0_symbol": "@TYH24", "ICE-US_CT0_midPrice": 80.94, "Volatility_ICE-US_CT0": 0.2964680113954007, "ICE-US_CT0_symbol": "@CTH24", "ICE-US_CT0_lastTS": "2023_12_13_04", "PL0_midPrice": 934.5, "Volatility_PL0": 3.48075349136918, "PL0_symbol": "QPLF24", "PL0_lastTS": "2023_12_13_04", "AUD=_midPrice": 0.65533, "Volatility_AUD=": 0.0010444669729188613, "AUD=_symbol": "AUDUSD.COMP", "AUD=_lastTS": "2023_12_13_04", "CL0_midPrice": 68.05, "Volatility_CL0": 0.31572903711864403, "CL0_symbol": "QCLF24", "CL0_lastTS": "2023_12_13_04", "CAD=_midPrice": 1.3601371018198636, "Volatility_CAD=": 0.0012782390025411956, "CAD=_symbol": "CADUSD.COMP", "CAD=_lastTS": "2023_12_13_04", "ZN0_CL0_Move_uniDR_9_smoothSeed": -0.0817082368520584, "ZN0_CL0_Move_uniDR_9_zSeed": -0.01025061193774, "ZN0_CL0_Move_uniDR_9_volSeed": 0.018150301227444075, "ZN0_PL0_Move_uniDR_9_smoothSeed": 0.3023538902699226, "ZN0_PL0_Move_uniDR_9_zSeed": 0.17886991030778907, "ZN0_PL0_Move_uniDR_9_volSeed": 0.17881635951377656, "ZN0_AUD=_Move_uniDR_35_smoothSeed": -2.8483266361777302e-05, "ZN0_AUD=_Move_uniDR_35_zSeed": 7.906499500242798e-07, "ZN0_AUD=_Move_uniDR_35_volSeed": 2.6386429252796354e-05, "ZN0_CAD=_Move_uniDR_18_smoothSeed": 5.6774161615280114e-05, "ZN0_CAD=_Move_uniDR_18_zSeed": -4.3534650371010096e-06, "ZN0_CAD=_Move_uniDR_18_volSeed": 4.943464069263698e-05, "ZN0_ICE-US_CT0_Move_uniDR_68_smoothSeed": -0.0025728024826054416, "ZN0_ICE-US_CT0_Move_uniDR_68_zSeed": 0.0007907932768126456, "ZN0_ICE-US_CT0_Move_uniDR_68_volSeed": 0.005408578115744404}, "ZF0": {"ZF0_midPrice": 107.15625, "Volatility_ZF0": 0.05367168357278956, "ZF0_lastTS": "2023_12_13_04", "ZF0_symbol": "@FVH24", "NZD=_midPrice": 0.60945, "Volatility_NZD=": 0.0009785848999041237, "NZD=_symbol": "NZDUSD.COMP", "NZD=_lastTS": "2023_12_13_04", "HO0_midPrice": 2.4914, "Volatility_HO0": 0.010701451196166232, "HO0_symbol": "QHOF24", "HO0_lastTS": "2023_12_13_04", "PL0_midPrice": 934.5, "Volatility_PL0": 3.4054744853557164, "PL0_symbol": "QPLF24", "PL0_lastTS": "2023_12_13_04", "CL0_midPrice": 68.05, "Volatility_CL0": 0.3180117811206931, "CL0_symbol": "QCLF24", "CL0_lastTS": "2023_12_13_04", "ZF0_HO0_Move_uniDR_68_smoothSeed": -0.001079906465344465, "ZF0_HO0_Move_uniDR_68_zSeed": -2.083617131525818e-05, "ZF0_HO0_Move_uniDR_68_volSeed": 0.0002828880593599609, "ZF0_NZD=_Move_uniDR_6_smoothSeed": -0.00017016864405034433, "ZF0_NZD=_Move_uniDR_6_zSeed": -1.7577157895551564e-05, "ZF0_NZD=_Move_uniDR_6_volSeed": 6.394398343660673e-05, "ZF0_PL0_Move_uniDR_9_smoothSeed": 0.39821622919378685, "ZF0_PL0_Move_uniDR_9_zSeed": 0.1813357720400498, "ZF0_PL0_Move_uniDR_9_volSeed": 0.1764214960424826, "ZF0_CL0_Move_uniDR_6_smoothSeed": -0.1297175657530796, "ZF0_CL0_Move_uniDR_6_zSeed": -0.02159567011856573, "ZF0_CL0_Move_uniDR_6_volSeed": 0.022492208011267594}, "FBTP0": {"FBTP0_midPrice": 116.7, "Volatility_FBTP0": 0.23010357931153638, "FBTP0_lastTS": "2023_12_13_04", "FBTP0_symbol": "BTPH24", "ICE-EU_BRN0_midPrice": 72.65, "Volatility_ICE-EU_BRN0": 0.4373455931460167, "ICE-EU_BRN0_symbol": "QBZG24", "ICE-EU_BRN0_lastTS": "2023_12_13_04", "ICE-EU_G0_midPrice": 717.5, "Volatility_ICE-EU_G0": 5.098409045963619, "ICE-EU_G0_symbol": "GASF24", "ICE-EU_G0_lastTS": "2023_12_13_04", "FTI0_midPrice": 787.7, "Volatility_FTI0": 1.7867469359128691, "FTI0_symbol": "AEXZ23", "FTI0_lastTS": "2023_12_13_03", "ICE-LL_R0_midPrice": 99.31, "Volatility_ICE-LL_R0": 0.16117011673454684, "ICE-LL_R0_symbol": "LGH24", "ICE-LL_R0_lastTS": "2023_12_13_04", "EUR=_midPrice": 1.07843, "Volatility_EUR=": 0.0016366467332517161, "EUR=_symbol": "EURUSD.COMP", "EUR=_lastTS": "2023_12_13_04", "CL0_midPrice": 68.05, "Volatility_CL0": 0.44313964326598926, "CL0_symbol": "QCLF24", "CL0_lastTS": "2023_12_13_04", "FBTP0_ICE-LL_R0_Move_uniDR_68_smoothSeed": 0.01689039170618205, "FBTP0_ICE-LL_R0_Move_uniDR_68_zSeed": 0.00013317643124940396, "FBTP0_ICE-LL_R0_Move_uniDR_68_volSeed": 0.0032587945446945726, "FBTP0_FTI0_VSR_uniDR_68_smoothSeed": 0.05364462783852053, "FBTP0_FTI0_VSR_uniDR_68_zSeed": 0.002140689043164383, "FBTP0_FTI0_VSR_uniDR_68_volSeed": 0.02741374817218365, "FBTP0_CL0_VSR_uniDR_68_smoothSeed": -0.08407905269077309, "FBTP0_CL0_VSR_uniDR_68_zSeed": -3.928565539962252e-05, "FBTP0_CL0_VSR_uniDR_68_volSeed": 0.04640746687589992, "FBTP0_ICE-EU_G0_VSR_uniDR_35_smoothSeed": -0.1676209881836302, "FBTP0_ICE-EU_G0_VSR_uniDR_35_zSeed": -0.0012700727381032275, "FBTP0_ICE-EU_G0_VSR_uniDR_35_volSeed": 0.06386846624258201, "FBTP0_ICE-EU_BRN0_VSR_uniDR_68_smoothSeed": -0.09308099227895097, "FBTP0_ICE-EU_BRN0_VSR_uniDR_68_zSeed": -0.00027018031305979447, "FBTP0_ICE-EU_BRN0_VSR_uniDR_68_volSeed": 0.05037632432633147}, "AP0": {"AP0_midPrice": 7272.0, "Volatility_AP0": 12.847514283018016, "AP0_lastTS": "2023_12_13_03", "AP0_symbol": "SPIZ23", "ICE-US_KC0_midPrice": 185.45, "Volatility_ICE-US_KC0": 0.7810215760779852, "ICE-US_KC0_symbol": "@KCH24", "ICE-US_KC0_lastTS": "2023_12_12_14", "ZS0_midPrice": 1315.25, "Volatility_ZS0": 3.9373769756302415, "ZS0_symbol": "@SF24", "ZS0_lastTS": "2023_12_13_04", "NQ0_midPrice": 16607.5, "Volatility_NQ0": 28.37373997938161, "NQ0_symbol": "@NQH24", "NQ0_lastTS": "2023_12_13_04", "JPY=_midPrice": 145.79809879279173, "Volatility_JPY=": 0.18322999750583852, "JPY=_symbol": "JPYUSD.COMP", "JPY=_lastTS": "2023_12_13_04", "FGBL0_midPrice": 135.36, "Volatility_FGBL0": 0.15400732466383665, "FGBL0_symbol": "BDH24", "FGBL0_lastTS": "2023_12_13_04", "AUD=_midPrice": 0.65533, "Volatility_AUD=": 0.0012775456638157148, "AUD=_symbol": "AUDUSD.COMP", "AUD=_lastTS": "2023_12_13_04", "ICE-LL_R0_midPrice": 99.31, "Volatility_ICE-LL_R0": 0.1265933764609292, "ICE-LL_R0_symbol": "LGH24", "ICE-LL_R0_lastTS": "2023_12_13_04", "FBTS0_midPrice": 105.78, "Volatility_FBTS0": 0.0525814389294195, "FBTS0_symbol": "BTSH24", "FBTS0_lastTS": "2023_12_13_04", "ZS1_midPrice": 1333.5, "Volatility_ZS1": 3.837638785231835, "ZS1_symbol": "@SH24", "ZS1_lastTS": "2023_12_13_04", "AP0_FGBL0_Basis_uniDR_6_smoothSeed": -7120.851864348407, "AP0_FGBL0_Basis_uniDR_6_zSeed": -4067.676841754774, "AP0_FGBL0_Basis_uniDR_6_volSeed": 697.7455925839164, "AP0_ICE-LL_R0_Move_uniDR_6_smoothSeed": 0.07993272977727603, "AP0_ICE-LL_R0_Move_uniDR_6_zSeed": 0.010264000262380474, "AP0_ICE-LL_R0_Move_uniDR_6_volSeed": 0.008323851210358111, "AP0_JPY=_Move_uniDR_35_smoothSeed": 0.009935525650620204, "AP0_JPY=_Move_uniDR_35_zSeed": 0.00031057842416271937, "AP0_JPY=_Move_uniDR_35_volSeed": 0.005296405250616949, "AP0_ICE-US_KC0_Move_uniDR_17_smoothSeed": 0.07589254657520442, "AP0_ICE-US_KC0_Move_uniDR_17_zSeed": 0.01566398626895438, "AP0_ICE-US_KC0_Move_uniDR_17_volSeed": 0.03240257641178502, "AP0_ZS1_Basis_uniDR_35_smoothSeed": -4788.409825908168, "AP0_ZS1_Basis_uniDR_35_zSeed": -476.6521631727802, "AP0_ZS1_Basis_uniDR_35_volSeed": 66.74825130454414, "AP0_NQ0_VSR_uniDR_35_smoothSeed": 0.09036322995735817, "AP0_NQ0_VSR_uniDR_35_zSeed": 0.010979666296849277, "AP0_NQ0_VSR_uniDR_35_volSeed": 0.02879970134862702, "AP0_FBTS0_Move_uniDR_6_smoothSeed": 0.0023028885015379747, "AP0_FBTS0_Move_uniDR_6_zSeed": -0.0021957494009082947, "AP0_FBTS0_Move_uniDR_6_volSeed": 0.0031039627831865517}, "ES0": {"ES0_midPrice": 4702.25, "Volatility_ES0": 6.793062234248104, "ES0_lastTS": "2023_12_13_04", "ES0_symbol": "@ESH24", "FTI0_midPrice": 787.7, "Volatility_FTI0": 1.2848875761069571, "FTI0_symbol": "AEXZ23", "FTI0_lastTS": "2023_12_13_03", "ICE-LL_R0_midPrice": 99.31, "Volatility_ICE-LL_R0": 0.11554686694086584, "ICE-LL_R0_symbol": "LGH24", "ICE-LL_R0_lastTS": "2023_12_13_04", "FCE0_midPrice": 7542.0, "Volatility_FCE0": 12.857802595400086, "FCE0_symbol": "MTZ23", "FCE0_lastTS": "2023_12_13_03", "FESX0_midPrice": 4541.0, "Volatility_FESX0": 8.336985681343922, "FESX0_symbol": "EXZ23", "FESX0_lastTS": "2023_12_13_04", "FDAX0_midPrice": 16810.0, "Volatility_FDAX0": 28.986104860350885, "FDAX0_symbol": "DXMZ23", "FDAX0_lastTS": "2023_12_13_04", "ES0_FTI0_VSR_uniDR_5_smoothSeed": -0.14474346879723174, "ES0_FTI0_VSR_uniDR_5_zSeed": -0.03476931927234297, "ES0_FTI0_VSR_uniDR_5_volSeed": 0.0503503256293889, "ES0_FCE0_VSR_uniDR_5_smoothSeed": -0.30451686487809293, "ES0_FCE0_VSR_uniDR_5_zSeed": -0.03907121353956549, "ES0_FCE0_VSR_uniDR_5_volSeed": 0.054064273456576314, "ES0_FDAX0_VSR_uniDR_5_smoothSeed": -0.07045315650395752, "ES0_FDAX0_VSR_uniDR_5_zSeed": -0.06678616201361667, "ES0_FDAX0_VSR_uniDR_5_volSeed": 0.05495833911424681, "ES0_ICE-LL_R0_Move_uniDR_68_smoothSeed": 0.01574465268266553, "ES0_ICE-LL_R0_Move_uniDR_68_zSeed": 0.0002450477942191634, "ES0_ICE-LL_R0_Move_uniDR_68_volSeed": 0.00223033241492008, "ES0_FESX0_VSR_uniDR_5_smoothSeed": -0.13077321935133132, "ES0_FESX0_VSR_uniDR_5_zSeed": -0.05316343853193457, "ES0_FESX0_VSR_uniDR_5_volSeed": 0.051274648761757705}, "FSMI0": {"FSMI0_midPrice": 11164.0, "Volatility_FSMI0": 24.67977053400494, "FSMI0_lastTS": "2023_12_13_04", "FSMI0_symbol": "SWZ23", "CHF=_midPrice": 0.8756030716155753, "Volatility_CHF=": 0.0014652319233022222, "CHF=_symbol": "CHFUSD.COMP", "CHF=_lastTS": "2023_12_13_04", "FBTS0_midPrice": 105.78, "Volatility_FBTS0": 0.05013330315816352, "FBTS0_symbol": "BTSH24", "FBTS0_lastTS": "2023_12_13_04", "NG0_midPrice": 2.291, "Volatility_NG0": 0.03606712656017731, "NG0_symbol": "QNGF24", "NG0_lastTS": "2023_12_13_04", "FSMI0_FBTS0_Move_uniDR_6_smoothSeed": 0.00021667007274479106, "FSMI0_FBTS0_Move_uniDR_6_zSeed": -0.0025825821660081967, "FSMI0_FBTS0_Move_uniDR_6_volSeed": 0.003186047732346503, "FSMI0_NG0_Move_uniDR_6_smoothSeed": -0.004045639242539788, "FSMI0_NG0_Move_uniDR_6_zSeed": -0.0011419042863355631, "FSMI0_NG0_Move_uniDR_6_volSeed": 0.002652988730743378}, "FTI0": {"FTI0_midPrice": 787.7, "Volatility_FTI0": 1.7340864471944715, "FTI0_lastTS": "2023_12_13_03", "FTI0_symbol": "AEXZ23", "HE0_midPrice": 68.225, "Volatility_HE0": 0.3277947063728529, "HE0_symbol": "@HEG24", "HE0_lastTS": "2023_12_12_15", "ICE-US_KC0_midPrice": 185.45, "Volatility_ICE-US_KC0": 0.8636991456797282, "ICE-US_KC0_symbol": "@KCH24", "ICE-US_KC0_lastTS": "2023_12_12_14", "HE1_midPrice": 75.425, "Volatility_HE1": 0.3977248752580436, "HE1_symbol": "@HEJ24", "HE1_lastTS": "2023_12_12_15", "NG0_midPrice": 2.291, "Volatility_NG0": 0.03776233823097323, "NG0_symbol": "QNGF24", "NG0_lastTS": "2023_12_13_04", "EUR=_midPrice": 1.07843, "Volatility_EUR=": 0.0015530184323672036, "EUR=_symbol": "EURUSD.COMP", "EUR=_lastTS": "2023_12_13_04", "FBTS0_midPrice": 105.78, "Volatility_FBTS0": 0.057670055789544844, "FBTS0_symbol": "BTSH24", "FBTS0_lastTS": "2023_12_13_04", "FTI0_FBTS0_Move_uniDR_5_smoothSeed": 0.0008401987711026855, "FTI0_FBTS0_Move_uniDR_5_zSeed": -0.0029783349958134244, "FTI0_FBTS0_Move_uniDR_5_volSeed": 0.0036631099725852965, "FTI0_ICE-US_KC0_Move_uniDR_9_smoothSeed": 0.15763495045470222, "FTI0_ICE-US_KC0_Move_uniDR_9_zSeed": 0.028331474710313855, "FTI0_ICE-US_KC0_Move_uniDR_9_volSeed": 0.0506560486282761, "FTI0_HE1_Basis_uniDR_69_smoothSeed": -281.36263730822463, "FTI0_HE1_Basis_uniDR_69_zSeed": -7.806509401146013, "FTI0_HE1_Basis_uniDR_69_volSeed": 0.8177150949840744, "FTI0_NG0_Move_uniDR_35_smoothSeed": -0.0007342578474801149, "FTI0_NG0_Move_uniDR_35_zSeed": 3.0672128626470796e-05, "FTI0_NG0_Move_uniDR_35_volSeed": 0.0012019409989717767}, "ALSI0": {"ALSI0_midPrice": 66654.0, "Volatility_ALSI0": 175.0987637628001, "ALSI0_lastTS": "2023_12_13_03", "ALSI0_symbol": "ALJZ23", "NQ0_midPrice": 16607.5, "Volatility_NQ0": 30.889986048247838, "NQ0_symbol": "@NQH24", "NQ0_lastTS": "2023_12_13_04", "ZAR=_midPrice": 19.02147014203636, "Volatility_ZAR=": 0.04899227088983909, "ZAR=_symbol": "ZARUSD.COMP", "ZAR=_lastTS": "2023_12_13_04", "GC0_midPrice": 1994.6, "Volatility_GC0": 3.8193312477957426, "GC0_symbol": "QGCG24", "GC0_lastTS": "2023_12_13_04", "AUD=_midPrice": 0.65533, "Volatility_AUD=": 0.0017056042821485381, "AUD=_symbol": "AUDUSD.COMP", "AUD=_lastTS": "2023_12_13_04", "ZN0_midPrice": 110.6875, "Volatility_ZN0": 0.1217977428119069, "ZN0_symbol": "@TYH24", "ZN0_lastTS": "2023_12_13_04", "GC1_midPrice": 1985.1, "Volatility_GC1": 3.826096344476747, "GC1_symbol": "QGCF24", "GC1_lastTS": "2023_12_13_04", "ES0_midPrice": 4702.25, "Volatility_ES0": 8.514670024187067, "ES0_symbol": "@ESH24", "ES0_lastTS": "2023_12_13_04", "ZF0_midPrice": 107.15625, "Volatility_ZF0": 0.074688907112418, "ZF0_symbol": "@FVH24", "ZF0_lastTS": "2023_12_13_04", "ALSI0_ZF0_Move_uniDR_18_smoothSeed": -0.008562537163125043, "ALSI0_ZF0_Move_uniDR_18_zSeed": -0.0010080629580926982, "ALSI0_ZF0_Move_uniDR_18_volSeed": 0.002964539600375304, "ALSI0_GC1_Basis_uniDR_8_smoothSeed": -62331.2693692236, "ALSI0_GC1_Basis_uniDR_8_zSeed": -12436.145169148396, "ALSI0_GC1_Basis_uniDR_8_volSeed": 1220.8457689329282, "ALSI0_ES0_Move_uniDR_18_smoothSeed": 0.8251993114416711, "ALSI0_ES0_Move_uniDR_18_zSeed": 0.11458409169197363, "ALSI0_ES0_Move_uniDR_18_volSeed": 0.31323724886216775, "ALSI0_NQ0_Move_uniDR_18_smoothSeed": 6.357388782674469, "ALSI0_NQ0_Move_uniDR_18_zSeed": 0.7055912586809836, "ALSI0_NQ0_Move_uniDR_18_volSeed": 1.064416477376682, "ALSI0_AUD=_VSR_uniDR_69_smoothSeed": 0.09171975499334467, "ALSI0_AUD=_VSR_uniDR_69_zSeed": 0.0019242035950078052, "ALSI0_AUD=_VSR_uniDR_69_volSeed": 0.018589866322442274, "ALSI0_ZN0_Move_uniDR_18_smoothSeed": -0.012518877510612848, "ALSI0_ZN0_Move_uniDR_18_zSeed": -0.0015823125416419078, "ALSI0_ZN0_Move_uniDR_18_volSeed": 0.004800454199856769}, "ZC0": {"ZC0_midPrice": 483.25, "Volatility_ZC0": 2.088958706336402, "ZC0_lastTS": "2023_12_13_04", "ZC0_symbol": "@CH24", "ZC1_midPrice": 483.25, "Volatility_ZC1": 1.811770795717904, "ZC1_symbol": "@CH24", "ZC1_lastTS": "2023_12_13_04", "CNH=_midPrice": 7.197879999766213, "Volatility_CNH=": 0.004419922689082998, "CNH=_symbol": "CNHUSD.COMP", "CNH=_lastTS": "2023_12_13_04", "RB0_midPrice": 1.9743, "Volatility_RB0": 0.010435890458785454, "RB0_symbol": "QRBF24", "RB0_lastTS": "2023_12_13_04", "ZC0_ZC1_Basis_uniDR_6_smoothSeed": -0.0017173559640191642, "ZC0_ZC1_Basis_uniDR_6_zSeed": 0.00010145283505165473, "ZC0_ZC1_Basis_uniDR_6_volSeed": 0.049588626313820564, "ZC0_CNH=_Move_uniDR_68_smoothSeed": 6.583012843719365e-05, "ZC0_CNH=_Move_uniDR_68_zSeed": 3.4994688335412782e-06, "ZC0_CNH=_Move_uniDR_68_volSeed": 0.00011027982295644845, "ZC0_RB0_Move_uniDR_38_smoothSeed": -0.0011194508385605159, "ZC0_RB0_Move_uniDR_38_zSeed": -2.2950546995662187e-05, "ZC0_RB0_Move_uniDR_38_volSeed": 0.00029262976769703483}, "ZS0": {"ZS0_midPrice": 1315.25, "Volatility_ZS0": 4.426875479338172, "ZS0_lastTS": "2023_12_13_04", "ZS0_symbol": "@SF24", "PA0_midPrice": 978.5, "Volatility_PA0": 9.14201601514404, "PA0_symbol": "QPAH24", "PA0_lastTS": "2023_12_13_04", "NQ0_midPrice": 16607.5, "Volatility_NQ0": 28.19456374214098, "NQ0_symbol": "@NQH24", "NQ0_lastTS": "2023_12_13_04", "XT0_midPrice": 95.716, "Volatility_XT0": 0.012391777217373437, "XT0_symbol": "XTZ23", "XT0_lastTS": "2023_12_13_03", "IND0_midPrice": 126580.0, "Volatility_IND0": 291.87000644088477, "IND0_symbol": "INDZ23", "IND0_lastTS": "2023_12_12_23", "ZS1_midPrice": 1333.5, "Volatility_ZS1": 3.9302799092990197, "ZS1_symbol": "@SH24", "ZS1_lastTS": "2023_12_13_04", "ZS0_PA0_VSR_uniDR_68_smoothSeed": 0.00735899714679364, "ZS0_PA0_VSR_uniDR_68_zSeed": -0.0014366951895070136, "ZS0_PA0_VSR_uniDR_68_volSeed": 0.02780735928734911, "ZS0_IND0_Move_uniDR_9_smoothSeed": -10.206140333772849, "ZS0_IND0_Move_uniDR_9_zSeed": -1.761075945644147, "ZS0_IND0_Move_uniDR_9_volSeed": 16.73267627184643, "ZS0_NQ0_VSR_uniDR_68_smoothSeed": 0.11774321673899923, "ZS0_NQ0_VSR_uniDR_68_zSeed": 0.003017280562281382, "ZS0_NQ0_VSR_uniDR_68_volSeed": 0.028999982132429013, "ZS0_ZS1_Basis_uniDR_6_smoothSeed": -0.01528354509736786, "ZS0_ZS1_Basis_uniDR_6_zSeed": 0.025504197243965177, "ZS0_ZS1_Basis_uniDR_6_volSeed": 0.06557569179988251, "ZS0_XT0_VSR_uniDR_68_smoothSeed": 0.031135352503150197, "ZS0_XT0_VSR_uniDR_68_zSeed": -0.0017646249290400214, "ZS0_XT0_VSR_uniDR_68_volSeed": 0.034586951513904604}, "ZM0": {"ZM0_midPrice": 403.4, "Volatility_ZM0": 1.6465408092988463, "ZM0_lastTS": "2023_12_13_04", "ZM0_symbol": "@SMF24", "FESX0_midPrice": 4541.0, "Volatility_FESX0": 9.146423757822191, "FESX0_symbol": "EXZ23", "FESX0_lastTS": "2023_12_13_04", "YM0_midPrice": 36634.0, "Volatility_YM0": 66.86765189722738, "YM0_symbol": "@YMZ23", "YM0_lastTS": "2023_12_13_04", "FTI0_midPrice": 787.7, "Volatility_FTI0": 1.404687926564921, "FTI0_symbol": "AEXZ23", "FTI0_lastTS": "2023_12_13_03", "FSMI0_midPrice": 11164.0, "Volatility_FSMI0": 21.034060912246478, "FSMI0_symbol": "SWZ23", "FSMI0_lastTS": "2023_12_13_04", "CNH=_midPrice": 7.197879999766213, "Volatility_CNH=": 0.00436898008501949, "CNH=_symbol": "CNHUSD.COMP", "CNH=_lastTS": "2023_12_13_04", "ICE-US_SB0_midPrice": 22.41, "Volatility_ICE-US_SB0": 0.06635962051459622, "ICE-US_SB0_symbol": "@SBH24", "ICE-US_SB0_lastTS": "2023_12_12_13", "FCE0_midPrice": 7542.0, "Volatility_FCE0": 14.07453888127044, "FCE0_symbol": "MTZ23", "FCE0_lastTS": "2023_12_13_03", "HG0_midPrice": 3.7665, "Volatility_HG0": 0.010234695347720993, "HG0_symbol": "QHGH24", "HG0_lastTS": "2023_12_13_04", "ZM0_HG0_VSR_uniDR_18_smoothSeed": 0.09512438684201398, "ZM0_HG0_VSR_uniDR_18_zSeed": 0.003470524258749556, "ZM0_HG0_VSR_uniDR_18_volSeed": 0.05444909500300292, "ZM0_FESX0_VSR_uniDR_68_smoothSeed": 0.10731993930195252, "ZM0_FESX0_VSR_uniDR_68_zSeed": 0.002816669811644902, "ZM0_FESX0_VSR_uniDR_68_volSeed": 0.02742457604926102, "ZM0_FSMI0_VSR_uniDR_68_smoothSeed": 0.07575386327430624, "ZM0_FSMI0_VSR_uniDR_68_zSeed": 0.0013924707893694477, "ZM0_FSMI0_VSR_uniDR_68_volSeed": 0.027532320844876904, "ZM0_FCE0_VSR_uniDR_68_smoothSeed": 0.09720910892281225, "ZM0_FCE0_VSR_uniDR_68_zSeed": 0.003344863715753395, "ZM0_FCE0_VSR_uniDR_68_volSeed": 0.026338509312740635, "ZM0_ICE-US_SB0_VSR_uniDR_68_smoothSeed": -0.13686589074385486, "ZM0_ICE-US_SB0_VSR_uniDR_68_zSeed": -0.0070953678336313514, "ZM0_ICE-US_SB0_VSR_uniDR_68_volSeed": 0.03044046345077186, "ZM0_FTI0_VSR_uniDR_35_smoothSeed": 0.1793457703792015, "ZM0_FTI0_VSR_uniDR_35_zSeed": 0.008420874071850942, "ZM0_FTI0_VSR_uniDR_35_volSeed": 0.039759989800811114, "ZM0_YM0_VSR_uniDR_18_smoothSeed": 0.2612198077102522, "ZM0_YM0_VSR_uniDR_18_zSeed": 0.016050690621395226, "ZM0_YM0_VSR_uniDR_18_volSeed": 0.055120630151336655, "ZM0_CNH=_VSR_uniDR_68_smoothSeed": 0.06340467321149071, "ZM0_CNH=_VSR_uniDR_68_zSeed": 0.0010819150895334943, "ZM0_CNH=_VSR_uniDR_68_volSeed": 0.036617002675937003}, "ZW0": {"ZW0_midPrice": 624.5, "Volatility_ZW0": 3.669428017253037, "ZW0_lastTS": "2023_12_13_04", "ZW0_symbol": "@WH24", "HE0_midPrice": 68.225, "Volatility_HE0": 0.2724011639661348, "HE0_symbol": "@HEG24", "HE0_lastTS": "2023_12_12_15", "ICE-LX_C0_midPrice": 3545.0, "Volatility_ICE-LX_C0": 5.8544741478544156, "ICE-LX_C0_symbol": "QCH24", "ICE-LX_C0_lastTS": "2023_12_12_12", "ICE-LL_Z0_midPrice": 7595.0, "Volatility_ICE-LL_Z0": 10.062386638028936, "ICE-LL_Z0_symbol": "TUKZ23", "ICE-LL_Z0_lastTS": "2023_12_12_05", "ZW0_ICE-LL_Z0_Move_uniDR_35_smoothSeed": 0.7299026229459137, "ZW0_ICE-LL_Z0_Move_uniDR_35_zSeed": 0.06733816884463431, "ZW0_ICE-LL_Z0_Move_uniDR_35_volSeed": 0.2996822629216547, "ZW0_ICE-LX_C0_Move_uniDR_5_smoothSeed": 0.0064643165570270845, "ZW0_ICE-LX_C0_Move_uniDR_5_zSeed": 0.5220297908281161, "ZW0_ICE-LX_C0_Move_uniDR_5_volSeed": 0.49026014755152975, "ZW0_HE0_VSR_uniDR_68_smoothSeed": -0.00914134195367921, "ZW0_HE0_VSR_uniDR_68_zSeed": 0.0005252409807240158, "ZW0_HE0_VSR_uniDR_68_volSeed": 0.030433283378772984}, "KE0": {"KE0_midPrice": 657.25, "Volatility_KE0": 3.7337774470299125, "KE0_lastTS": "2023_12_13_04", "KE0_symbol": "@KWH24", "ICE-LX_C0_midPrice": 3545.0, "Volatility_ICE-LX_C0": 5.83630833898508, "ICE-LX_C0_symbol": "QCH24", "ICE-LX_C0_lastTS": "2023_12_12_12", "W0_midPrice": 637.9, "Volatility_W0": 1.4267943584823946, "W0_symbol": "QWH24", "W0_lastTS": "2023_12_12_13", "ZAR=_midPrice": 19.02147014203636, "Volatility_ZAR=": 0.033419077248446415, "ZAR=_symbol": "ZARUSD.COMP", "ZAR=_lastTS": "2023_12_13_04", "KE0_ZAR=_Move_uniDR_38_smoothSeed": 0.0016949041867145528, "KE0_ZAR=_Move_uniDR_38_zSeed": 0.00015104809882495268, "KE0_ZAR=_Move_uniDR_38_volSeed": 0.0008727653908084892, "KE0_ICE-LX_C0_Move_uniDR_18_smoothSeed": 0.47685363821879934, "KE0_ICE-LX_C0_Move_uniDR_18_zSeed": 0.221241875229359, "KE0_ICE-LX_C0_Move_uniDR_18_volSeed": 0.2489912239781141, "KE0_W0_Move_uniDR_5_smoothSeed": 0.05013064450368475, "KE0_W0_Move_uniDR_5_zSeed": -0.13571978856034386, "KE0_W0_Move_uniDR_5_volSeed": 0.11199584968879484}, "LE0": {"LE0_midPrice": 168.575, "Volatility_LE0": 0.4432587038425685, "LE0_lastTS": "2023_12_12_15", "LE0_symbol": "@LEG24", "KE0_midPrice": 657.25, "Volatility_KE0": 4.602593033615261, "KE0_symbol": "@KWH24", "KE0_lastTS": "2023_12_13_04", "EUR=_midPrice": 1.07843, "Volatility_EUR=": 0.001984216730452375, "EUR=_symbol": "EURUSD.COMP", "EUR=_lastTS": "2023_12_13_04", "FCE0_midPrice": 7542.0, "Volatility_FCE0": 19.21287826524716, "FCE0_symbol": "MTZ23", "FCE0_lastTS": "2023_12_13_03", "ICE-US_CC0_midPrice": 4465.0, "Volatility_ICE-US_CC0": 15.469996580411435, "ICE-US_CC0_symbol": "@CCZ23", "ICE-US_CC0_lastTS": "2023_12_12_14", "FESX0_midPrice": 4541.0, "Volatility_FESX0": 13.506573555383223, "FESX0_symbol": "EXZ23", "FESX0_lastTS": "2023_12_13_04", "VX0_midPrice": 12.35, "Volatility_VX0": 0.354719852206146, "VX0_symbol": "@VXZ23", "VX0_lastTS": "2023_12_13_04", "LE0_FCE0_Move_uniDR_5_smoothSeed": 2.0132801663410005, "LE0_FCE0_Move_uniDR_5_zSeed": 0.7312811971781062, "LE0_FCE0_Move_uniDR_5_volSeed": 1.3505415406235828, "LE0_VX0_VSR_uniDR_5_smoothSeed": -0.7942999134340651, "LE0_VX0_VSR_uniDR_5_zSeed": -0.1269256937632722, "LE0_VX0_VSR_uniDR_5_volSeed": 0.1317186118374683, "LE0_ICE-US_CC0_VSR_uniDR_5_smoothSeed": -0.05861466222157838, "LE0_ICE-US_CC0_VSR_uniDR_5_zSeed": 0.04424029660151321, "LE0_ICE-US_CC0_VSR_uniDR_5_volSeed": 0.11903315860209869, "LE0_EUR=_VSR_uniDR_79_smoothSeed": -0.07934815152563675, "LE0_EUR=_VSR_uniDR_79_zSeed": -0.0006372916737223454, "LE0_EUR=_VSR_uniDR_79_volSeed": 0.04621016559494151, "LE0_FESX0_Move_uniDR_5_smoothSeed": 1.668349130551527, "LE0_FESX0_Move_uniDR_5_zSeed": 0.488705158727266, "LE0_FESX0_Move_uniDR_5_volSeed": 0.9768505373043922, "LE0_KE0_VSR_uniDR_79_smoothSeed": -0.08658347975799442, "LE0_KE0_VSR_uniDR_79_zSeed": -0.0007194124368365876, "LE0_KE0_VSR_uniDR_79_volSeed": 0.036147130808099864}, "CL0": {"CL0_midPrice": 68.05, "Volatility_CL0": 0.319344126896002, "CL0_lastTS": "2023_12_13_04", "CL0_symbol": "QCLF24", "ZF0_midPrice": 107.15625, "Volatility_ZF0": 0.05388040971927395, "ZF0_symbol": "@FVH24", "ZF0_lastTS": "2023_12_13_04", "THB=_midPrice": 35.813999563498975, "Volatility_THB=": 0.035996697921484556, "THB=_symbol": "THBUSD.COMP", "THB=_lastTS": "2023_12_13_04", "SGD=_midPrice": 1.3442800007481188, "Volatility_SGD=": 0.0008822292713228457, "SGD=_symbol": "SGDUSD.COMP", "SGD=_lastTS": "2023_12_13_04", "ALSI0_midPrice": 66654.0, "Volatility_ALSI0": 103.59989205345919, "ALSI0_symbol": "ALJZ23", "ALSI0_lastTS": "2023_12_13_03", "CL0_ZF0_VSR_uniDR_68_smoothSeed": 0.04925771716781942, "CL0_ZF0_VSR_uniDR_68_zSeed": -0.003964498329873449, "CL0_ZF0_VSR_uniDR_68_volSeed": 0.04246779012893197, "CL0_THB=_Move_uniDR_35_smoothSeed": 0.003158062914930376, "CL0_THB=_Move_uniDR_35_zSeed": 0.00045676904561176685, "CL0_THB=_Move_uniDR_35_volSeed": 0.0008612946448579025, "CL0_ALSI0_Move_uniDR_6_smoothSeed": -34.43808533063409, "CL0_ALSI0_Move_uniDR_6_zSeed": -16.026133997445882, "CL0_ALSI0_Move_uniDR_6_volSeed": 7.297762047964626, "CL0_SGD=_Move_uniDR_68_smoothSeed": 1.0309269203123168e-05, "CL0_SGD=_Move_uniDR_68_zSeed": -6.347363068456498e-08, "CL0_SGD=_Move_uniDR_68_volSeed": 1.739534526271373e-05}, "HO0": {"HO0_midPrice": 2.4914, "Volatility_HO0": 0.010672149348953585, "HO0_lastTS": "2023_12_13_04", "HO0_symbol": "QHOF24", "ICE-US_CC0_midPrice": 4465.0, "Volatility_ICE-US_CC0": 9.703834115168968, "ICE-US_CC0_symbol": "@CCZ23", "ICE-US_CC0_lastTS": "2023_12_12_14", "W0_midPrice": 637.9, "Volatility_W0": 1.3387996759745344, "W0_symbol": "QWH24", "W0_lastTS": "2023_12_12_13", "ALSI0_midPrice": 66654.0, "Volatility_ALSI0": 100.64642540321505, "ALSI0_symbol": "ALJZ23", "ALSI0_lastTS": "2023_12_13_03", "HO0_ICE-US_CC0_VSR_uniDR_68_smoothSeed": 0.2490494782564602, "HO0_ICE-US_CC0_VSR_uniDR_68_zSeed": 0.011062455171015274, "HO0_ICE-US_CC0_VSR_uniDR_68_volSeed": 0.030367122247264507, "HO0_W0_VSR_uniDR_68_smoothSeed": 0.06378193701085183, "HO0_W0_VSR_uniDR_68_zSeed": -0.0019062214545877206, "HO0_W0_VSR_uniDR_68_volSeed": 0.030195476716404115, "HO0_ALSI0_Move_uniDR_8_smoothSeed": -26.643139043654053, "HO0_ALSI0_Move_uniDR_8_zSeed": -7.760428235691964, "HO0_ALSI0_Move_uniDR_8_volSeed": 6.045001811470861}, "RS0": {"RS0_midPrice": 671.0, "Volatility_RS0": 2.3063553650626716, "RS0_lastTS": "2023_12_13_02", "RS0_symbol": "@RSH24", "KE0_midPrice": 657.25, "Volatility_KE0": 3.2520829450223414, "KE0_symbol": "@KWH24", "KE0_lastTS": "2023_12_13_04", "CONF0_midPrice": 150.67, "Volatility_CONF0": 0.14917821466257344, "CONF0_symbol": "COH24", "CONF0_lastTS": "2023_12_12_07", "AUD=_midPrice": 0.65533, "Volatility_AUD=": 0.0013267066281385956, "AUD=_symbol": "AUDUSD.COMP", "AUD=_lastTS": "2023_12_13_04", "ZW0_midPrice": 624.5, "Volatility_ZW0": 3.2626634845667892, "ZW0_symbol": "@WH24", "ZW0_lastTS": "2023_12_13_04", "ZC0_midPrice": 483.25, "Volatility_ZC0": 1.7505599737992201, "ZC0_symbol": "@CH24", "ZC0_lastTS": "2023_12_13_04", "CNH=_midPrice": 7.197879999766213, "Volatility_CNH=": 0.00524303404629107, "CNH=_symbol": "CNHUSD.COMP", "CNH=_lastTS": "2023_12_13_04", "HG0_midPrice": 3.7665, "Volatility_HG0": 0.01161651303440204, "HG0_symbol": "QHGH24", "HG0_lastTS": "2023_12_13_04", "CAD=_midPrice": 1.3601371018198636, "Volatility_CAD=": 0.001624803237804364, "CAD=_symbol": "CADUSD.COMP", "CAD=_lastTS": "2023_12_13_04", "RS0_ZW0_Move_uniDR_5_smoothSeed": 0.3715163454032998, "RS0_ZW0_Move_uniDR_5_zSeed": -0.12783280172810357, "RS0_ZW0_Move_uniDR_5_volSeed": 0.254148427339397, "RS0_AUD=_Move_uniDR_68_smoothSeed": -6.197493195465459e-05, "RS0_AUD=_Move_uniDR_68_zSeed": -1.0849068831749424e-06, "RS0_AUD=_Move_uniDR_68_volSeed": 2.38853623314782e-05, "RS0_CNH=_VSR_uniDR_68_smoothSeed": 0.05786192884813153, "RS0_CNH=_VSR_uniDR_68_zSeed": 0.0007499374925210524, "RS0_CNH=_VSR_uniDR_68_volSeed": 0.04298184916389146, "RS0_KE0_Move_uniDR_5_smoothSeed": 0.8813154961092504, "RS0_KE0_Move_uniDR_5_zSeed": 0.0022883001889703464, "RS0_KE0_Move_uniDR_5_volSeed": 0.2442660001530585, "RS0_HG0_Move_uniDR_68_smoothSeed": -4.422120176042854e-05, "RS0_HG0_Move_uniDR_68_zSeed": 2.2793748877296685e-05, "RS0_HG0_Move_uniDR_68_volSeed": 0.00021462496009008026, "RS0_CONF0_VSR_uniDR_17_smoothSeed": 0.15224682172415557, "RS0_CONF0_VSR_uniDR_17_zSeed": -0.019411577221102715, "RS0_CONF0_VSR_uniDR_17_volSeed": 0.06473307360697506, "RS0_ZC0_Move_uniDR_5_smoothSeed": 0.03797223962931413, "RS0_ZC0_Move_uniDR_5_zSeed": -0.06260626654354856, "RS0_ZC0_Move_uniDR_5_volSeed": 0.12943662714982943}, "W0": {"W0_midPrice": 637.9, "Volatility_W0": 2.025398453397788, "W0_lastTS": "2023_12_12_13", "W0_symbol": "QWH24", "KE0_midPrice": 657.25, "Volatility_KE0": 4.036301338561442, "KE0_symbol": "@KWH24", "KE0_lastTS": "2023_12_13_04", "RB0_midPrice": 1.9743, "Volatility_RB0": 0.01429827134819376, "RB0_symbol": "QRBF24", "RB0_lastTS": "2023_12_13_04", "ECO0_midPrice": 439.25, "Volatility_ECO0": 2.267838863703597, "ECO0_symbol": "PGG24", "ECO0_lastTS": "2023_12_12_13", "W0_KE0_Move_uniDR_5_smoothSeed": 1.9560573642597974, "W0_KE0_Move_uniDR_5_zSeed": 0.006367848441602441, "W0_KE0_Move_uniDR_5_volSeed": 0.3166979000460251, "W0_RB0_Move_uniDR_8_smoothSeed": -0.004865028836593854, "W0_RB0_Move_uniDR_8_zSeed": -0.00023951754649237906, "W0_RB0_Move_uniDR_8_volSeed": 0.0009145371313889209, "W0_ECO0_Move_uniDR_5_smoothSeed": -0.6071645283851906, "W0_ECO0_Move_uniDR_5_zSeed": 0.01121734025700264, "W0_ECO0_Move_uniDR_5_volSeed": 0.1978328213149975}, "ICE-US_CT0": {"ICE-US_CT0_midPrice": 80.94, "Volatility_ICE-US_CT0": 0.3587886546470851, "ICE-US_CT0_lastTS": "2023_12_13_04", "ICE-US_CT0_symbol": "@CTH24", "ICE-EU_BRN0_midPrice": 72.65, "Volatility_ICE-EU_BRN0": 0.3710559399515255, "ICE-EU_BRN0_symbol": "QBZG24", "ICE-EU_BRN0_lastTS": "2023_12_13_04", "ICE-EU_G0_midPrice": 717.5, "Volatility_ICE-EU_G0": 4.027048449816513, "ICE-EU_G0_symbol": "GASF24", "ICE-EU_G0_lastTS": "2023_12_13_04", "ZT0_midPrice": 102.1640625, "Volatility_ZT0": 0.0219563449813697, "ZT0_symbol": "@TUH24", "ZT0_lastTS": "2023_12_13_04", "FESB0_midPrice": 118.2, "Volatility_FESB0": 0.4673249455153649, "FESB0_symbol": "SXZ23", "FESB0_lastTS": "2023_12_13_04", "ICE-US_MME0_midPrice": 971.8, "Volatility_ICE-US_MME0": 3.0051600292097342, "ICE-US_MME0_symbol": "MEFZ23", "ICE-US_MME0_lastTS": "2023_12_13_01", "ZM0_midPrice": 403.4, "Volatility_ZM0": 1.506991452775846, "ZM0_symbol": "@SMF24", "ZM0_lastTS": "2023_12_13_04", "CL0_midPrice": 68.05, "Volatility_CL0": 0.3833941873048914, "CL0_symbol": "QCLF24", "CL0_lastTS": "2023_12_13_04", "ZF0_midPrice": 107.15625, "Volatility_ZF0": 0.06258710189631668, "ZF0_symbol": "@FVH24", "ZF0_lastTS": "2023_12_13_04", "ICE-US_CT0_ZF0_Move_uniDR_68_smoothSeed": -0.0011622586105741687, "ICE-US_CT0_ZF0_Move_uniDR_68_zSeed": -8.220805301074328e-05, "ICE-US_CT0_ZF0_Move_uniDR_68_volSeed": 0.0013764198369671707, "ICE-US_CT0_ZM0_Move_uniDR_68_smoothSeed": -0.0666481092194728, "ICE-US_CT0_ZM0_Move_uniDR_68_zSeed": -0.0021700704881612073, "ICE-US_CT0_ZM0_Move_uniDR_68_volSeed": 0.03861733194853493, "ICE-US_CT0_CL0_VSR_uniDR_18_smoothSeed": -0.1297763703511631, "ICE-US_CT0_CL0_VSR_uniDR_18_zSeed": -0.01691134745212058, "ICE-US_CT0_CL0_VSR_uniDR_18_volSeed": 0.04599137656191387, "ICE-US_CT0_ICE-EU_BRN0_VSR_uniDR_18_smoothSeed": -0.1447089148640739, "ICE-US_CT0_ICE-EU_BRN0_VSR_uniDR_18_zSeed": -0.018142932063868432, "ICE-US_CT0_ICE-EU_BRN0_VSR_uniDR_18_volSeed": 0.047236011504184994, "ICE-US_CT0_ICE-EU_G0_VSR_uniDR_18_smoothSeed": -0.17857736108067934, "ICE-US_CT0_ICE-EU_G0_VSR_uniDR_18_zSeed": -0.025176378053599742, "ICE-US_CT0_ICE-EU_G0_VSR_uniDR_18_volSeed": 0.04810357617859267, "ICE-US_CT0_ICE-US_MME0_VSR_uniDR_5_smoothSeed": -0.13879244206412372, "ICE-US_CT0_ICE-US_MME0_VSR_uniDR_5_zSeed": -0.007956850344530407, "ICE-US_CT0_ICE-US_MME0_VSR_uniDR_5_volSeed": 0.09122951360975536, "ICE-US_CT0_FESB0_VSR_uniDR_5_smoothSeed": 0.011702876699104782, "ICE-US_CT0_FESB0_VSR_uniDR_5_zSeed": -0.008182328802887825, "ICE-US_CT0_FESB0_VSR_uniDR_5_volSeed": 0.09323193848980815, "ICE-US_CT0_ZT0_Move_uniDR_68_smoothSeed": -0.0007583213936917142, "ICE-US_CT0_ZT0_Move_uniDR_68_zSeed": -4.292902494287406e-05, "ICE-US_CT0_ZT0_Move_uniDR_68_volSeed": 0.000524916496575636}, "ICE-EU_G0": {"ICE-EU_G0_midPrice": 717.5, "Volatility_ICE-EU_G0": 3.5811787384495055, "ICE-EU_G0_lastTS": "2023_12_13_04", "ICE-EU_G0_symbol": "GASF24", "ICE-LX_C0_midPrice": 3545.0, "Volatility_ICE-LX_C0": 5.714741180398939, "ICE-LX_C0_symbol": "QCH24", "ICE-LX_C0_lastTS": "2023_12_12_12", "ZL0_midPrice": 50.33, "Volatility_ZL0": 0.18989137799739733, "ZL0_symbol": "@BOF24", "ZL0_lastTS": "2023_12_13_04", "W0_midPrice": 637.9, "Volatility_W0": 1.4199974341058774, "W0_symbol": "QWH24", "W0_lastTS": "2023_12_12_13", "ZN0_midPrice": 110.6875, "Volatility_ZN0": 0.08816845093964186, "ZN0_symbol": "@TYH24", "ZN0_lastTS": "2023_12_13_04", "ALSI0_midPrice": 66654.0, "Volatility_ALSI0": 106.61137676689967, "ALSI0_symbol": "ALJZ23", "ALSI0_lastTS": "2023_12_13_03", "ICE-EU_G0_ALSI0_Move_uniDR_6_smoothSeed": -37.803296034876375, "ICE-EU_G0_ALSI0_Move_uniDR_6_zSeed": -16.240284854064686, "ICE-EU_G0_ALSI0_Move_uniDR_6_volSeed": 7.489113788756557, "ICE-EU_G0_ICE-LX_C0_VSR_uniDR_68_smoothSeed": 0.061638453231228, "ICE-EU_G0_ICE-LX_C0_VSR_uniDR_68_zSeed": 0.0004625395806304979, "ICE-EU_G0_ICE-LX_C0_VSR_uniDR_68_volSeed": 0.03769936798146657, "ICE-EU_G0_W0_VSR_uniDR_68_smoothSeed": 0.00939361628496135, "ICE-EU_G0_W0_VSR_uniDR_68_zSeed": -0.003199399547304008, "ICE-EU_G0_W0_VSR_uniDR_68_volSeed": 0.03189737384739189, "ICE-EU_G0_ZN0_VSR_uniDR_35_smoothSeed": 0.18214763254570146, "ICE-EU_G0_ZN0_VSR_uniDR_35_zSeed": 0.0018283476934350886, "ICE-EU_G0_ZN0_VSR_uniDR_35_volSeed": 0.058667818093112466, "ICE-EU_G0_ZL0_Move_uniDR_68_smoothSeed": -0.0007708988874127498, "ICE-EU_G0_ZL0_Move_uniDR_68_zSeed": 0.00037455794540298856, "ICE-EU_G0_ZL0_Move_uniDR_68_volSeed": 0.004068675177174996}, "ICE-US_KC0": {"ICE-US_KC0_midPrice": 185.45, "Volatility_ICE-US_KC0": 1.0061717408671078, "ICE-US_KC0_lastTS": "2023_12_12_14", "ICE-US_KC0_symbol": "@KCH24", "RS1_midPrice": 671.0, "Volatility_RS1": 2.627351206757524, "RS1_symbol": "@RSH24", "RS1_lastTS": "2023_12_13_02", "RS0_midPrice": 671.0, "Volatility_RS0": 2.699740625648113, "RS0_symbol": "@RSH24", "RS0_lastTS": "2023_12_13_02", "NG0_midPrice": 2.291, "Volatility_NG0": 0.04363868998065887, "NG0_symbol": "QNGF24", "NG0_lastTS": "2023_12_13_04", "RB0_midPrice": 1.9743, "Volatility_RB0": 0.01449582326574565, "RB0_symbol": "QRBF24", "RB0_lastTS": "2023_12_13_04", "ICE-US_KC0_RB0_Move_uniDR_35_smoothSeed": -0.0018783549290585975, "ICE-US_KC0_RB0_Move_uniDR_35_zSeed": -4.784555632796517e-05, "ICE-US_KC0_RB0_Move_uniDR_35_volSeed": 0.00041077973849737106, "ICE-US_KC0_NG0_Move_uniDR_35_smoothSeed": -0.001840276117340571, "ICE-US_KC0_NG0_Move_uniDR_35_zSeed": 1.1041669467513933e-06, "ICE-US_KC0_NG0_Move_uniDR_35_volSeed": 0.0013978730143291498, "ICE-US_KC0_RS1_Basis_uniDR_69_smoothSeed": 139.78253403381044, "ICE-US_KC0_RS1_Basis_uniDR_69_zSeed": 2.490598348251978, "ICE-US_KC0_RS1_Basis_uniDR_69_volSeed": 0.21477190067792554}}, "logs": {"ZN0": ["2023_12_13_04", false, 110.6875, 1, 0.08531967444249587, 0.140625, -0.0013944364753223297, -0.18852723347968542, 0, 0, 1, -0.10329851834869277, 2, 110546.88, 1], "ZF0": ["2023_12_13_04", false, 107.15625, 1, 0.05367168357278956, 0.0859375, 6.755381518329173e-05, 0.0, 0, 0, 1, 0.0, 4, 107070.31, 1], "FBTP0": ["2023_12_13_04", false, 116.7, 1, 0.23010357931153638, 0.3200000000000074, 9.342202440013465e-05, 0.0015613915469224646, 0, 0, 2, 0.002796373590159922, 6, 108212.86, 1.07843], "AP0": ["2023_12_13_03", false, 7272.0, 1, 12.847514283018016, 1.0, 0.7118246533034998, 0.004176514014960299, 0, 0, 1, 0.3554480012732169, 2, 333353.71, 0.65435], "ES0": ["2023_12_13_04", false, 4702.25, 1, 6.793062234248104, 0.75, -0.19689745446191326, -0.004197373264905929, 0, 0, 1, -0.151814715889248, 3, 235075.0, 1], "FSMI0": ["2023_12_13_04", false, 11164.0, 1, 24.67977053400494, 17.0, -0.06372868085091218, -5.677587859872354e-05, 0, 0, 1, -0.030722878029612304, 2, 127164.36, 0.8765820877855726], "FTI0": ["2023_12_13_03", false, 787.7, 1, 1.7340864471944715, -0.849999999999909, -0.09132562710415297, -0.02976507017772564, 0, -1, 1, -0.5161722045907507, 3, 146082.73, 1.07843], "ALSI0": ["2023_12_13_03", false, 66654.0, 1, 175.0987637628001, 51.0, 7.820138731529869, 0.0002542653707652488, 0, 5, 5, 0.35761655522538505, 21, 35007.78, 19.02520011418925], "ZC0": ["2023_12_13_04", false, 483.25, 1, 2.088958706336402, -1.0, -0.0035894065636617716, 0.0, 0, 0, 3, 0.0, 11, 24212.5, 1], "ZS0": ["2023_12_13_04", false, 1315.25, 1, 4.426875479338172, -4.5, -0.08095987680340236, -0.002868741491351402, 0, 0, 1, -0.05715876967764654, 2, 65987.5, 1], "ZM0": ["2023_12_13_04", false, 403.4, 1, 1.6465408092988463, -1.2000000000000455, -0.008423655712147931, 0.0, 0, 0, 4, 0.0, 18, 40460.0, 1], "ZW0": ["2023_12_13_04", false, 624.5, 1, 3.669428017253037, -0.75, -0.018486505714822597, -0.0010562621989328115, 0, 0, 3, -0.06291019648200188, 14, 31262.5, 1], "KE0": ["2023_12_13_04", false, 657.25, 1, 3.7337774470299125, -1.0, -0.08369271772513734, -0.0041764095145700635, 0, -1, 2, -0.2160807902819776, 8, 32912.5, 1], "LE0": [], "CL0": ["2023_12_13_04", false, 68.05, 1, 0.319344126896002, 0.009999999999990905, -0.01197471964936329, -0.11717151384981705, 0, 0, 1, -0.34273002819674053, 2, 68040.0, 1], "HO0": ["2023_12_13_04", false, 2.4914, 1, 0.010672149348953585, -0.0045999999999999375, -0.00013950485907421203, -0.9105322176101337, 0, 0, 1, -0.16887705417805848, 2, 104832.0, 1], "RS0": [], "W0": [], "ICE-US_CT0": ["2023_12_13_04", false, 80.94, 1, 0.3587886546470851, -0.18000000000000682, -0.0035340772222763896, -0.029823533333333332, -1, 0, 3, -0.06666666666666667, 15, 40560.0, 1], "ICE-EU_G0": ["2023_12_13_04", false, 717.5, 1, 3.5811787384495055, -1.75, -0.11978673149840177, -0.009133893361088259, 0, 0, 1, -0.22831879417793424, 2, 71925.0, 1], "ICE-US_KC0": []}}