{"initSeeds": {"ZN0": {"ZN0_midPrice": 110.84375, "Volatility_ZN0": 0.08529131124572208, "ZN0_lastTS": "2023_12_13_10", "ZN0_symbol": "@TYH24", "PL0_midPrice": 927.6, "Volatility_PL0": 3.49280755612555, "PL0_symbol": "QPLF24", "PL0_lastTS": "2023_12_13_10", "CAD=_midPrice": 1.355619721555709, "Volatility_CAD=": 0.0012774752033024184, "CAD=_symbol": "CADUSD.COMP", "CAD=_lastTS": "2023_12_13_10", "ICE-US_CT0_midPrice": 81.04, "Volatility_ICE-US_CT0": 0.29594206956426294, "ICE-US_CT0_symbol": "@CTH24", "ICE-US_CT0_lastTS": "2023_12_13_10", "CL0_midPrice": 68.91, "Volatility_CL0": 0.3150848466357357, "CL0_symbol": "QCLF24", "CL0_lastTS": "2023_12_13_10", "AUD=_midPrice": 0.65764, "Volatility_AUD=": 0.0010434824156262345, "AUD=_symbol": "AUDUSD.COMP", "AUD=_lastTS": "2023_12_13_10", "ZN0_CL0_Move_uniDR_9_smoothSeed": -0.0027498265108914155, "ZN0_CL0_Move_uniDR_9_zSeed": -0.010726601677017155, "ZN0_CL0_Move_uniDR_9_volSeed": 0.018116438695510398, "ZN0_PL0_Move_uniDR_9_smoothSeed": -0.1371801308566235, "ZN0_PL0_Move_uniDR_9_zSeed": 0.1600653678984457, "ZN0_PL0_Move_uniDR_9_volSeed": 0.17876981210032244, "ZN0_AUD=_Move_uniDR_35_smoothSeed": 1.9712238702098886e-05, "ZN0_AUD=_Move_uniDR_35_zSeed": 5.857996436194605e-07, "ZN0_AUD=_Move_uniDR_35_volSeed": 2.6310375429922414e-05, "ZN0_CAD=_Move_uniDR_18_smoothSeed": -0.00011881154751638513, "ZN0_CAD=_Move_uniDR_18_zSeed": -4.432440825318524e-06, "ZN0_CAD=_Move_uniDR_18_volSeed": 4.9293045118434736e-05, "ZN0_ICE-US_CT0_Move_uniDR_68_smoothSeed": -0.0015780743442095997, "ZN0_ICE-US_CT0_Move_uniDR_68_zSeed": 0.0007889301819096903, "ZN0_ICE-US_CT0_Move_uniDR_68_volSeed": 0.005393312933694116}, "ZF0": {"ZF0_midPrice": 107.28125, "Volatility_ZF0": 0.05370301917870387, "ZF0_lastTS": "2023_12_13_10", "ZF0_symbol": "@FVH24", "PL0_midPrice": 927.6, "Volatility_PL0": 3.418230817882836, "PL0_symbol": "QPLF24", "PL0_lastTS": "2023_12_13_10", "NZD=_midPrice": 0.61175, "Volatility_NZD=": 0.0009791353339553674, "NZD=_symbol": "NZDUSD.COMP", "NZD=_lastTS": "2023_12_13_10", "HO0_midPrice": 2.5369, "Volatility_HO0": 0.01070627082193183, "HO0_symbol": "QHOF24", "HO0_lastTS": "2023_12_13_10", "CL0_midPrice": 68.91, "Volatility_CL0": 0.31735909698053427, "CL0_symbol": "QCLF24", "CL0_lastTS": "2023_12_13_10", "ZF0_HO0_Move_uniDR_68_smoothSeed": -0.0005727094876165536, "ZF0_HO0_Move_uniDR_68_zSeed": -2.4777518494064642e-05, "ZF0_HO0_Move_uniDR_68_volSeed": 0.0002820777871874241, "ZF0_NZD=_Move_uniDR_6_smoothSeed": 0.0001644653437831548, "ZF0_NZD=_Move_uniDR_6_zSeed": -2.108181869921925e-05, "ZF0_NZD=_Move_uniDR_6_volSeed": 6.378112360671624e-05, "ZF0_PL0_Move_uniDR_9_smoothSeed": -0.07679064150545684, "ZF0_PL0_Move_uniDR_9_zSeed": 0.16574892419459378, "ZF0_PL0_Move_uniDR_9_volSeed": 0.17641327688972328, "ZF0_CL0_Move_uniDR_6_smoothSeed": -0.0019559609008314876, "ZF0_CL0_Move_uniDR_6_zSeed": -0.022155527293749293, "ZF0_CL0_Move_uniDR_6_volSeed": 0.022492347351806677}, "FBTP0": {"FBTP0_midPrice": 116.94, "Volatility_FBTP0": 0.2297000482237473, "FBTP0_lastTS": "2023_12_13_10", "FBTP0_symbol": "BTPH24", "ICE-LL_R0_midPrice": 99.88, "Volatility_ICE-LL_R0": 0.16124875833795385, "ICE-LL_R0_symbol": "LGH24", "ICE-LL_R0_lastTS": "2023_12_13_10", "ICE-EU_G0_midPrice": 733.0, "Volatility_ICE-EU_G0": 5.090865396265563, "ICE-EU_G0_symbol": "GASF24", "ICE-EU_G0_lastTS": "2023_12_13_10", "FTI0_midPrice": 791.0, "Volatility_FTI0": 1.7825351718002407, "FTI0_symbol": "AEXZ23", "FTI0_lastTS": "2023_12_13_09", "ICE-EU_BRN0_midPrice": 73.51, "Volatility_ICE-EU_BRN0": 0.43627551242850743, "ICE-EU_BRN0_symbol": "QBZG24", "ICE-EU_BRN0_lastTS": "2023_12_13_10", "EUR=_midPrice": 1.08006, "Volatility_EUR=": 0.0016332624464060275, "EUR=_symbol": "EURUSD.COMP", "EUR=_lastTS": "2023_12_13_10", "CL0_midPrice": 68.91, "Volatility_CL0": 0.4420514649909808, "CL0_symbol": "QCLF24", "CL0_lastTS": "2023_12_13_10", "FBTP0_ICE-LL_R0_Move_uniDR_68_smoothSeed": 0.021589949245682506, "FBTP0_ICE-LL_R0_Move_uniDR_68_zSeed": 0.0002454966138301102, "FBTP0_ICE-LL_R0_Move_uniDR_68_volSeed": 0.003249431068906236, "FBTP0_FTI0_VSR_uniDR_68_smoothSeed": 0.05836397509328779, "FBTP0_FTI0_VSR_uniDR_68_zSeed": 0.0024775373669674258, "FBTP0_FTI0_VSR_uniDR_68_volSeed": 0.02733526739532841, "FBTP0_CL0_VSR_uniDR_68_smoothSeed": -0.07045245098517817, "FBTP0_CL0_VSR_uniDR_68_zSeed": -0.00047792192651699547, "FBTP0_CL0_VSR_uniDR_68_volSeed": 0.04627363668156994, "FBTP0_ICE-EU_G0_VSR_uniDR_35_smoothSeed": -0.11322154130701453, "FBTP0_ICE-EU_G0_VSR_uniDR_35_zSeed": -0.0026798937585947556, "FBTP0_ICE-EU_G0_VSR_uniDR_35_volSeed": 0.06368448252970992, "FBTP0_ICE-EU_BRN0_VSR_uniDR_68_smoothSeed": -0.07867112448479847, "FBTP0_ICE-EU_BRN0_VSR_uniDR_68_zSeed": -0.0007589949378077347, "FBTP0_ICE-EU_BRN0_VSR_uniDR_68_volSeed": 0.050231060606145427}, "AP0": {"AP0_midPrice": 7292.0, "Volatility_AP0": 12.824201379994228, "AP0_lastTS": "2023_12_13_09", "AP0_symbol": "SPIZ23", "ZS0_midPrice": 1315.25, "Volatility_ZS0": 3.9290805316451047, "ZS0_symbol": "@SF24", "ZS0_lastTS": "2023_12_13_09", "ICE-US_KC0_midPrice": 190.05, "Volatility_ICE-US_KC0": 0.7837606624157092, "ICE-US_KC0_symbol": "@KCH24", "ICE-US_KC0_lastTS": "2023_12_13_10", "FBTS0_midPrice": 105.86, "Volatility_FBTS0": 0.05251455244186327, "FBTS0_symbol": "BTSH24", "FBTS0_lastTS": "2023_12_13_10", "ICE-LL_R0_midPrice": 99.88, "Volatility_ICE-LL_R0": 0.12694222261504598, "ICE-LL_R0_symbol": "LGH24", "ICE-LL_R0_lastTS": "2023_12_13_10", "FGBL0_midPrice": 135.52, "Volatility_FGBL0": 0.15385446308408168, "FGBL0_symbol": "BDH24", "FGBL0_lastTS": "2023_12_13_10", "ZS1_midPrice": 1334.0, "Volatility_ZS1": 3.8295343141437597, "ZS1_symbol": "@SH24", "ZS1_lastTS": "2023_12_13_09", "NQ0_midPrice": 16631.0, "Volatility_NQ0": 28.319302038092754, "NQ0_symbol": "@NQH24", "NQ0_lastTS": "2023_12_13_10", "JPY=_midPrice": 145.20000720192036, "Volatility_JPY=": 0.18354289723891148, "JPY=_symbol": "JPYUSD.COMP", "JPY=_lastTS": "2023_12_13_10", "AUD=_midPrice": 0.65764, "Volatility_AUD=": 0.0012761104315356876, "AUD=_symbol": "AUDUSD.COMP", "AUD=_lastTS": "2023_12_13_10", "AP0_FGBL0_Basis_uniDR_6_smoothSeed": -7130.777560176988, "AP0_FGBL0_Basis_uniDR_6_zSeed": -4239.361529073909, "AP0_FGBL0_Basis_uniDR_6_volSeed": 753.7128503896386, "AP0_ICE-LL_R0_Move_uniDR_6_smoothSeed": 0.09012751016112472, "AP0_ICE-LL_R0_Move_uniDR_6_zSeed": 0.014037647857235836, "AP0_ICE-LL_R0_Move_uniDR_6_volSeed": 0.008348539081071178, "AP0_JPY=_Move_uniDR_35_smoothSeed": -0.002003165040559609, "AP0_JPY=_Move_uniDR_35_zSeed": 0.0003683207847153327, "AP0_JPY=_Move_uniDR_35_volSeed": 0.005283731042392578, "AP0_ICE-US_KC0_Move_uniDR_17_smoothSeed": 0.20205194628468703, "AP0_ICE-US_KC0_Move_uniDR_17_zSeed": 0.018253537700588244, "AP0_ICE-US_KC0_Move_uniDR_17_volSeed": 0.03234603453075226, "AP0_ZS1_Basis_uniDR_35_smoothSeed": -4899.298644318514, "AP0_ZS1_Basis_uniDR_35_zSeed": -519.8008332373684, "AP0_ZS1_Basis_uniDR_35_volSeed": 75.14785749953705, "AP0_NQ0_VSR_uniDR_35_smoothSeed": 0.06902732884200843, "AP0_NQ0_VSR_uniDR_35_zSeed": 0.011589463914013538, "AP0_NQ0_VSR_uniDR_35_volSeed": 0.028741251066734304, "AP0_FBTS0_Move_uniDR_6_smoothSeed": 0.012147601961447863, "AP0_FBTS0_Move_uniDR_6_zSeed": -0.0017366859381296906, "AP0_FBTS0_Move_uniDR_6_volSeed": 0.0030995559455395377}, "ES0": {"ES0_midPrice": 4708.25, "Volatility_ES0": 6.776869801620404, "ES0_lastTS": "2023_12_13_10", "ES0_symbol": "@ESH24", "ICE-LL_R0_midPrice": 99.88, "Volatility_ICE-LL_R0": 0.11597045779096979, "ICE-LL_R0_symbol": "LGH24", "ICE-LL_R0_lastTS": "2023_12_13_10", "FTI0_midPrice": 791.0, "Volatility_FTI0": 1.2824904131998316, "FTI0_symbol": "AEXZ23", "FTI0_lastTS": "2023_12_13_09", "FCE0_midPrice": 7567.0, "Volatility_FCE0": 12.860999946488375, "FCE0_symbol": "MTZ23", "FCE0_lastTS": "2023_12_13_09", "FDAX0_midPrice": 16827.0, "Volatility_FDAX0": 28.92614943986292, "FDAX0_symbol": "DXMZ23", "FDAX0_lastTS": "2023_12_13_10", "FESX0_midPrice": 4549.0, "Volatility_FESX0": 8.321242250004806, "FESX0_symbol": "EXZ23", "FESX0_lastTS": "2023_12_13_10", "ES0_FTI0_VSR_uniDR_5_smoothSeed": 0.07214927284936272, "ES0_FTI0_VSR_uniDR_5_zSeed": -0.028906970047588576, "ES0_FTI0_VSR_uniDR_5_volSeed": 0.05026462691858235, "ES0_FCE0_VSR_uniDR_5_smoothSeed": -0.11791145830796261, "ES0_FCE0_VSR_uniDR_5_zSeed": -0.03869097113033574, "ES0_FCE0_VSR_uniDR_5_volSeed": 0.05398492074341998, "ES0_FDAX0_VSR_uniDR_5_smoothSeed": -0.08591697067238006, "ES0_FDAX0_VSR_uniDR_5_zSeed": -0.06408165569992576, "ES0_FDAX0_VSR_uniDR_5_volSeed": 0.05501877983851311, "ES0_ICE-LL_R0_Move_uniDR_68_smoothSeed": 0.02051218385077671, "ES0_ICE-LL_R0_Move_uniDR_68_zSeed": 0.00034994392408385964, "ES0_ICE-LL_R0_Move_uniDR_68_volSeed": 0.002224020079245422, "ES0_FESX0_VSR_uniDR_5_smoothSeed": -0.10262309737926997, "ES0_FESX0_VSR_uniDR_5_zSeed": -0.050519881962220056, "ES0_FESX0_VSR_uniDR_5_volSeed": 0.051271467355127616}, "FSMI0": {"FSMI0_midPrice": 11239.0, "Volatility_FSMI0": 24.676688222935706, "FSMI0_lastTS": "2023_12_13_10", "FSMI0_symbol": "SWZ23", "NG0_midPrice": 2.305, "Volatility_NG0": 0.036002174815063855, "NG0_symbol": "QNGF24", "NG0_lastTS": "2023_12_13_10", "FBTS0_midPrice": 105.86, "Volatility_FBTS0": 0.05005977994132266, "FBTS0_symbol": "BTSH24", "FBTS0_lastTS": "2023_12_13_10", "CHF=_midPrice": 0.8754808514009608, "Volatility_CHF=": 0.0014617737532509616, "CHF=_symbol": "CHFUSD.COMP", "CHF=_lastTS": "2023_12_13_10", "FSMI0_FBTS0_Move_uniDR_6_smoothSeed": 0.00905156903456671, "FSMI0_FBTS0_Move_uniDR_6_zSeed": -0.002316649275977474, "FSMI0_FBTS0_Move_uniDR_6_volSeed": 0.003182551321237919, "FSMI0_NG0_Move_uniDR_6_smoothSeed": -0.0016071255672865537, "FSMI0_NG0_Move_uniDR_6_zSeed": -0.0011304951808321182, "FSMI0_NG0_Move_uniDR_6_volSeed": 0.0026467748092136763}, "FTI0": {"FTI0_midPrice": 791.0, "Volatility_FTI0": 1.7308876004342826, "FTI0_lastTS": "2023_12_13_09", "FTI0_symbol": "AEXZ23", "NG0_midPrice": 2.305, "Volatility_NG0": 0.03770804449679532, "NG0_symbol": "QNGF24", "NG0_lastTS": "2023_12_13_10", "ICE-US_KC0_midPrice": 190.05, "Volatility_ICE-US_KC0": 0.8657998098339469, "ICE-US_KC0_symbol": "@KCH24", "ICE-US_KC0_lastTS": "2023_12_13_10", "FBTS0_midPrice": 105.86, "Volatility_FBTS0": 0.057585690959837385, "FBTS0_symbol": "BTSH24", "FBTS0_lastTS": "2023_12_13_10", "EUR=_midPrice": 1.08006, "Volatility_EUR=": 0.0015506178916072386, "EUR=_symbol": "EURUSD.COMP", "EUR=_lastTS": "2023_12_13_10", "HE1_midPrice": 75.425, "Volatility_HE1": 0.39676879750904454, "HE1_symbol": "@HEJ24", "HE1_lastTS": "2023_12_12_15", "HE0_midPrice": 68.225, "Volatility_HE0": 0.3270067314572799, "HE0_symbol": "@HEG24", "HE0_lastTS": "2023_12_12_15", "FTI0_FBTS0_Move_uniDR_5_smoothSeed": 0.01305940298939331, "FTI0_FBTS0_Move_uniDR_5_zSeed": -0.0024002009600183447, "FTI0_FBTS0_Move_uniDR_5_volSeed": 0.003659179396530557, "FTI0_ICE-US_KC0_Move_uniDR_9_smoothSeed": 0.3525894596895287, "FTI0_ICE-US_KC0_Move_uniDR_9_zSeed": 0.03722889028652166, "FTI0_ICE-US_KC0_Move_uniDR_9_volSeed": 0.05058580289003847, "FTI0_HE1_Basis_uniDR_69_smoothSeed": -302.8971623079849, "FTI0_HE1_Basis_uniDR_69_zSeed": -9.242245761495596, "FTI0_HE1_Basis_uniDR_69_volSeed": 1.0131212689848714, "FTI0_NG0_Move_uniDR_35_smoothSeed": -0.0005723112827032478, "FTI0_NG0_Move_uniDR_35_zSeed": 2.6239790619661757e-05, "FTI0_NG0_Move_uniDR_35_volSeed": 0.001199053246746497}, "ALSI0": {"ALSI0_midPrice": 66923.0, "Volatility_ALSI0": 174.83482690315358, "ALSI0_lastTS": "2023_12_13_09", "ALSI0_symbol": "ALJZ23", "ZAR=_midPrice": 19.062600072693318, "Volatility_ZAR=": 0.048947500411215074, "ZAR=_symbol": "ZARUSD.COMP", "ZAR=_lastTS": "2023_12_13_10", "ZF0_midPrice": 107.28125, "Volatility_ZF0": 0.07464278232103085, "ZF0_symbol": "@FVH24", "ZF0_lastTS": "2023_12_13_10", "GC1_midPrice": 1990.8, "Volatility_GC1": 3.820542254298785, "GC1_symbol": "QGCF24", "GC1_lastTS": "2023_12_13_10", "GC0_midPrice": 1999.7, "Volatility_GC0": 3.8117917763229423, "GC0_symbol": "QGCG24", "GC0_lastTS": "2023_12_13_10", "ZN0_midPrice": 110.84375, "Volatility_ZN0": 0.12165749335096508, "ZN0_symbol": "@TYH24", "ZN0_lastTS": "2023_12_13_10", "AUD=_midPrice": 0.65764, "Volatility_AUD=": 0.0017027298545897965, "AUD=_symbol": "AUDUSD.COMP", "AUD=_lastTS": "2023_12_13_10", "NQ0_midPrice": 16631.0, "Volatility_NQ0": 30.828378286441087, "NQ0_symbol": "@NQH24", "NQ0_lastTS": "2023_12_13_10", "ES0_midPrice": 4708.25, "Volatility_ES0": 8.496912180523895, "ES0_symbol": "@ESH24", "ES0_lastTS": "2023_12_13_10", "ALSI0_ZF0_Move_uniDR_18_smoothSeed": -0.002512418936817207, "ALSI0_ZF0_Move_uniDR_18_zSeed": -0.001129415329985094, "ALSI0_ZF0_Move_uniDR_18_volSeed": 0.002958384477988199, "ALSI0_GC1_Basis_uniDR_8_smoothSeed": -63186.06789797802, "ALSI0_GC1_Basis_uniDR_8_zSeed": -14574.171815081092, "ALSI0_GC1_Basis_uniDR_8_volSeed": 1545.8128608064462, "ALSI0_ES0_Move_uniDR_18_smoothSeed": 0.9033656562591157, "ALSI0_ES0_Move_uniDR_18_zSeed": 0.12768980748461622, "ALSI0_ES0_Move_uniDR_18_volSeed": 0.31259952777430355, "ALSI0_NQ0_Move_uniDR_18_smoothSeed": 6.164190387691422, "ALSI0_NQ0_Move_uniDR_18_zSeed": 0.8033993990633653, "ALSI0_NQ0_Move_uniDR_18_volSeed": 1.0631790200480353, "ALSI0_AUD=_VSR_uniDR_69_smoothSeed": 0.08427939106906007, "ALSI0_AUD=_VSR_uniDR_69_zSeed": 0.0023307566842520897, "ALSI0_AUD=_VSR_uniDR_69_volSeed": 0.018545791702219556, "ALSI0_ZN0_Move_uniDR_18_smoothSeed": -0.004343501772320752, "ALSI0_ZN0_Move_uniDR_18_zSeed": -0.0017501309783267722, "ALSI0_ZN0_Move_uniDR_18_volSeed": 0.004790362561572522}, "ZC0": {"ZC0_midPrice": 481.0, "Volatility_ZC0": 2.0856738425188874, "ZC0_lastTS": "2023_12_13_09", "ZC0_symbol": "@CH24", "CNH=_midPrice": 7.187600004223435, "Volatility_CNH=": 0.0044147344251463045, "CNH=_symbol": "CNHUSD.COMP", "CNH=_lastTS": "2023_12_13_10", "ZC1_midPrice": 481.0, "Volatility_ZC1": 1.8091312692710992, "ZC1_symbol": "@CH24", "ZC1_lastTS": "2023_12_13_09", "RB0_midPrice": 1.9856, "Volatility_RB0": 0.010418694150372878, "RB0_symbol": "QRBF24", "RB0_lastTS": "2023_12_13_10", "ZC0_ZC1_Basis_uniDR_6_smoothSeed": -0.0010818664646151236, "ZC0_ZC1_Basis_uniDR_6_zSeed": 3.838386666164767e-05, "ZC0_ZC1_Basis_uniDR_6_volSeed": 0.049493239941795525, "ZC0_CNH=_Move_uniDR_68_smoothSeed": 3.152498133787451e-05, "ZC0_CNH=_Move_uniDR_68_zSeed": 3.636129588098022e-06, "ZC0_CNH=_Move_uniDR_68_volSeed": 0.00011006791853964169, "ZC0_RB0_Move_uniDR_38_smoothSeed": -0.000837565911246171, "ZC0_RB0_Move_uniDR_38_zSeed": -2.9712835111807306e-05, "ZC0_RB0_Move_uniDR_38_volSeed": 0.0002920718074443093}, "ZS0": {"ZS0_midPrice": 1315.25, "Volatility_ZS0": 4.417280544329144, "ZS0_lastTS": "2023_12_13_09", "ZS0_symbol": "@SF24", "PA0_midPrice": 980.0, "Volatility_PA0": 9.124027359241962, "PA0_symbol": "QPAH24", "PA0_lastTS": "2023_12_13_10", "ZS1_midPrice": 1334.0, "Volatility_ZS1": 3.921934670914884, "ZS1_symbol": "@SH24", "ZS1_lastTS": "2023_12_13_09", "NQ0_midPrice": 16631.0, "Volatility_NQ0": 28.131611936286266, "NQ0_symbol": "@NQH24", "NQ0_lastTS": "2023_12_13_10", "IND0_midPrice": 127100.0, "Volatility_IND0": 291.2080854338757, "IND0_symbol": "INDZ23", "IND0_lastTS": "2023_12_13_09", "XT0_midPrice": 95.739, "Volatility_XT0": 0.012367542696678049, "XT0_symbol": "XTZ23", "XT0_lastTS": "2023_12_13_09", "ZS0_PA0_VSR_uniDR_68_smoothSeed": -0.0024476241201909135, "ZS0_PA0_VSR_uniDR_68_zSeed": -0.0014034018170682027, "ZS0_PA0_VSR_uniDR_68_volSeed": 0.027740685845681907, "ZS0_IND0_Move_uniDR_9_smoothSeed": -18.433626448757217, "ZS0_IND0_Move_uniDR_9_zSeed": -2.090161001529026, "ZS0_IND0_Move_uniDR_9_volSeed": 16.692992216324566, "ZS0_NQ0_VSR_uniDR_68_smoothSeed": 0.11189848418525959, "ZS0_NQ0_VSR_uniDR_68_zSeed": 0.0035992597573244736, "ZS0_NQ0_VSR_uniDR_68_volSeed": 0.028931214466887477, "ZS0_ZS1_Basis_uniDR_6_smoothSeed": -0.05005952290495753, "ZS0_ZS1_Basis_uniDR_6_zSeed": 0.021642871533123463, "ZS0_ZS1_Basis_uniDR_6_volSeed": 0.06543794862240672, "ZS0_XT0_VSR_uniDR_68_smoothSeed": 0.03971766448804929, "ZS0_XT0_VSR_uniDR_68_zSeed": -0.001540826983405593, "ZS0_XT0_VSR_uniDR_68_volSeed": 0.034503994927129626}, "ZM0": {"ZM0_midPrice": 403.6, "Volatility_ZM0": 1.6433361492976175, "ZM0_lastTS": "2023_12_13_09", "ZM0_symbol": "@SMF24", "FSMI0_midPrice": 11239.0, "Volatility_FSMI0": 21.063366887748455, "FSMI0_symbol": "SWZ23", "FSMI0_lastTS": "2023_12_13_10", "HG0_midPrice": 3.7885, "Volatility_HG0": 0.010213792601425888, "HG0_symbol": "QHGH24", "HG0_lastTS": "2023_12_13_10", "YM0_midPrice": 36675.0, "Volatility_YM0": 66.71390883448142, "YM0_symbol": "@YMZ23", "YM0_lastTS": "2023_12_13_10", "FTI0_midPrice": 791.0, "Volatility_FTI0": 1.4020141720861028, "FTI0_symbol": "AEXZ23", "FTI0_lastTS": "2023_12_13_09", "FCE0_midPrice": 7567.0, "Volatility_FCE0": 14.076494452659905, "FCE0_symbol": "MTZ23", "FCE0_lastTS": "2023_12_13_09", "CNH=_midPrice": 7.187600004223435, "Volatility_CNH=": 0.004362474393629865, "CNH=_symbol": "CNHUSD.COMP", "CNH=_lastTS": "2023_12_13_10", "FESX0_midPrice": 4549.0, "Volatility_FESX0": 9.131532076967103, "FESX0_symbol": "EXZ23", "FESX0_lastTS": "2023_12_13_10", "ICE-US_SB0_midPrice": 22.76, "Volatility_ICE-US_SB0": 0.06744093218583529, "ICE-US_SB0_symbol": "@SBH24", "ICE-US_SB0_lastTS": "2023_12_13_10", "ZM0_HG0_VSR_uniDR_18_smoothSeed": 0.09308746315716022, "ZM0_HG0_VSR_uniDR_18_zSeed": 0.005557866771640736, "ZM0_HG0_VSR_uniDR_18_volSeed": 0.054319233190830304, "ZM0_FESX0_VSR_uniDR_68_smoothSeed": 0.10563705250275397, "ZM0_FESX0_VSR_uniDR_68_zSeed": 0.003399610399856321, "ZM0_FESX0_VSR_uniDR_68_volSeed": 0.027359538905140195, "ZM0_FSMI0_VSR_uniDR_68_smoothSeed": 0.10593658876132869, "ZM0_FSMI0_VSR_uniDR_68_zSeed": 0.0019317599751796377, "ZM0_FSMI0_VSR_uniDR_68_volSeed": 0.027466395918060698, "ZM0_FCE0_VSR_uniDR_68_smoothSeed": 0.1041115075219137, "ZM0_FCE0_VSR_uniDR_68_zSeed": 0.003923347095346767, "ZM0_FCE0_VSR_uniDR_68_volSeed": 0.026276450326688593, "ZM0_ICE-US_SB0_VSR_uniDR_68_smoothSeed": -0.04886825997104054, "ZM0_ICE-US_SB0_VSR_uniDR_68_zSeed": -0.007404831928442232, "ZM0_ICE-US_SB0_VSR_uniDR_68_volSeed": 0.03037151802155483, "ZM0_FTI0_VSR_uniDR_35_smoothSeed": 0.18675643350339965, "ZM0_FTI0_VSR_uniDR_35_zSeed": 0.010313170905990744, "ZM0_FTI0_VSR_uniDR_35_volSeed": 0.03966998291433137, "ZM0_YM0_VSR_uniDR_18_smoothSeed": 0.20803029127715444, "ZM0_YM0_VSR_uniDR_18_zSeed": 0.020554023453218516, "ZM0_YM0_VSR_uniDR_18_volSeed": 0.05500381462151341, "ZM0_CNH=_VSR_uniDR_68_smoothSeed": 0.04602385445844422, "ZM0_CNH=_VSR_uniDR_68_zSeed": 0.001367648490180196, "ZM0_CNH=_VSR_uniDR_68_volSeed": 0.03652908580254763}, "ZW0": {"ZW0_midPrice": 614.75, "Volatility_ZW0": 3.6652617274608743, "ZW0_lastTS": "2023_12_13_09", "ZW0_symbol": "@WH24", "ICE-LX_C0_midPrice": 3543.0, "Volatility_ICE-LX_C0": 5.871539828363245, "ICE-LX_C0_symbol": "QCH24", "ICE-LX_C0_lastTS": "2023_12_13_10", "HE0_midPrice": 68.225, "Volatility_HE0": 0.27174634776561307, "HE0_symbol": "@HEG24", "HE0_lastTS": "2023_12_12_15", "ICE-LL_Z0_midPrice": 7595.0, "Volatility_ICE-LL_Z0": 10.038197997677482, "ICE-LL_Z0_symbol": "TUKZ23", "ICE-LL_Z0_lastTS": "2023_12_12_05", "ZW0_ICE-LL_Z0_Move_uniDR_35_smoothSeed": 0.6610900782104094, "ZW0_ICE-LL_Z0_Move_uniDR_35_zSeed": 0.07345385647727148, "ZW0_ICE-LL_Z0_Move_uniDR_35_volSeed": 0.2990024502084784, "ZW0_ICE-LX_C0_Move_uniDR_5_smoothSeed": 0.07113384140199713, "ZW0_ICE-LX_C0_Move_uniDR_5_zSeed": 0.5345273816111886, "ZW0_ICE-LX_C0_Move_uniDR_5_volSeed": 0.49047983012804003, "ZW0_HE0_VSR_uniDR_68_smoothSeed": 0.017439002812507202, "ZW0_HE0_VSR_uniDR_68_zSeed": 0.0005858824549089869, "ZW0_HE0_VSR_uniDR_68_volSeed": 0.030360150250247055}, "KE0": {"KE0_midPrice": 646.75, "Volatility_KE0": 3.7301904307718132, "KE0_lastTS": "2023_12_13_09", "KE0_symbol": "@KWH24", "ICE-LX_C0_midPrice": 3543.0, "Volatility_ICE-LX_C0": 5.853514093200033, "ICE-LX_C0_symbol": "QCH24", "ICE-LX_C0_lastTS": "2023_12_13_10", "ZAR=_midPrice": 19.062600072693318, "Volatility_ZAR=": 0.03344932075248205, "ZAR=_symbol": "ZARUSD.COMP", "ZAR=_lastTS": "2023_12_13_10", "W0_midPrice": 644.6, "Volatility_W0": 1.4677359965268622, "W0_symbol": "QWH24", "W0_lastTS": "2023_12_13_10", "KE0_ZAR=_Move_uniDR_38_smoothSeed": 0.002884100410121963, "KE0_ZAR=_Move_uniDR_38_zSeed": 0.00017297715298538965, "KE0_ZAR=_Move_uniDR_38_volSeed": 0.0008707411459494007, "KE0_ICE-LX_C0_Move_uniDR_18_smoothSeed": 0.5010067140686609, "KE0_ICE-LX_C0_Move_uniDR_18_zSeed": 0.22992696737976615, "KE0_ICE-LX_C0_Move_uniDR_18_volSeed": 0.24888924315252522, "KE0_W0_Move_uniDR_5_smoothSeed": 1.1456416797159585, "KE0_W0_Move_uniDR_5_zSeed": -0.06405273307767578, "KE0_W0_Move_uniDR_5_volSeed": 0.11195485042962694}, "LE0": {"LE0_midPrice": 168.575, "Volatility_LE0": 0.4432587038425685, "LE0_lastTS": "2023_12_12_15", "LE0_symbol": "@LEG24", "ICE-US_CC0_midPrice": 4465.0, "Volatility_ICE-US_CC0": 15.469996580411435, "ICE-US_CC0_symbol": "@CCZ23", "ICE-US_CC0_lastTS": "2023_12_12_14", "VX0_midPrice": 12.25, "Volatility_VX0": 0.354719852206146, "VX0_symbol": "@VXZ23", "VX0_lastTS": "2023_12_13_10", "FCE0_midPrice": 7567.0, "Volatility_FCE0": 19.21287826524716, "FCE0_symbol": "MTZ23", "FCE0_lastTS": "2023_12_13_09", "EUR=_midPrice": 1.08006, "Volatility_EUR=": 0.001984216730452375, "EUR=_symbol": "EURUSD.COMP", "EUR=_lastTS": "2023_12_13_10", "FESX0_midPrice": 4549.0, "Volatility_FESX0": 13.506573555383223, "FESX0_symbol": "EXZ23", "FESX0_lastTS": "2023_12_13_10", "KE0_midPrice": 646.75, "Volatility_KE0": 4.602593033615261, "KE0_symbol": "@KWH24", "KE0_lastTS": "2023_12_13_09", "LE0_FCE0_Move_uniDR_5_smoothSeed": 2.0132801663410005, "LE0_FCE0_Move_uniDR_5_zSeed": 0.7312811971781062, "LE0_FCE0_Move_uniDR_5_volSeed": 1.3505415406235828, "LE0_VX0_VSR_uniDR_5_smoothSeed": -0.7942999134340651, "LE0_VX0_VSR_uniDR_5_zSeed": -0.1269256937632722, "LE0_VX0_VSR_uniDR_5_volSeed": 0.1317186118374683, "LE0_ICE-US_CC0_VSR_uniDR_5_smoothSeed": -0.05861466222157838, "LE0_ICE-US_CC0_VSR_uniDR_5_zSeed": 0.04424029660151321, "LE0_ICE-US_CC0_VSR_uniDR_5_volSeed": 0.11903315860209869, "LE0_EUR=_VSR_uniDR_79_smoothSeed": -0.07934815152563675, "LE0_EUR=_VSR_uniDR_79_zSeed": -0.0006372916737223454, "LE0_EUR=_VSR_uniDR_79_volSeed": 0.04621016559494151, "LE0_FESX0_Move_uniDR_5_smoothSeed": 1.668349130551527, "LE0_FESX0_Move_uniDR_5_zSeed": 0.488705158727266, "LE0_FESX0_Move_uniDR_5_volSeed": 0.9768505373043922, "LE0_KE0_VSR_uniDR_79_smoothSeed": -0.08658347975799442, "LE0_KE0_VSR_uniDR_79_zSeed": -0.0007194124368365876, "LE0_KE0_VSR_uniDR_79_volSeed": 0.036147130808099864}, "CL0": {"CL0_midPrice": 68.91, "Volatility_CL0": 0.31868649795642573, "CL0_lastTS": "2023_12_13_10", "CL0_symbol": "QCLF24", "THB=_midPrice": 35.744999605196476, "Volatility_THB=": 0.03594339219569728, "THB=_symbol": "THBUSD.COMP", "THB=_lastTS": "2023_12_13_10", "ZF0_midPrice": 107.28125, "Volatility_ZF0": 0.053910424841044885, "ZF0_symbol": "@FVH24", "ZF0_lastTS": "2023_12_13_10", "SGD=_midPrice": 1.341319999718323, "Volatility_SGD=": 0.0008821174056392101, "SGD=_symbol": "SGDUSD.COMP", "SGD=_lastTS": "2023_12_13_10", "ALSI0_midPrice": 66923.0, "Volatility_ALSI0": 103.5663323089323, "ALSI0_symbol": "ALJZ23", "ALSI0_lastTS": "2023_12_13_09", "CL0_ZF0_VSR_uniDR_68_smoothSeed": 0.04369698734536491, "CL0_ZF0_VSR_uniDR_68_zSeed": -0.003770406241782374, "CL0_ZF0_VSR_uniDR_68_volSeed": 0.04234632553181165, "CL0_THB=_Move_uniDR_35_smoothSeed": 0.0014730317946193162, "CL0_THB=_Move_uniDR_35_zSeed": 0.000481367332897176, "CL0_THB=_Move_uniDR_35_volSeed": 0.0008595599312806336, "CL0_ALSI0_Move_uniDR_6_smoothSeed": 6.691828719712706, "CL0_ALSI0_Move_uniDR_6_zSeed": -15.68102973764719, "CL0_ALSI0_Move_uniDR_6_volSeed": 7.378516337590238, "CL0_SGD=_Move_uniDR_68_smoothSeed": -2.009374875744463e-05, "CL0_SGD=_Move_uniDR_68_zSeed": -5.5593356496764066e-08, "CL0_SGD=_Move_uniDR_68_volSeed": 1.734517835862605e-05}, "HO0": {"HO0_midPrice": 2.5369, "Volatility_HO0": 0.010677151121754875, "HO0_lastTS": "2023_12_13_10", "HO0_symbol": "QHOF24", "ICE-US_CC0_midPrice": 4465.0, "Volatility_ICE-US_CC0": 9.675848775130827, "ICE-US_CC0_symbol": "@CCZ23", "ICE-US_CC0_lastTS": "2023_12_12_14", "ALSI0_midPrice": 66923.0, "Volatility_ALSI0": 100.62914526625302, "ALSI0_symbol": "ALJZ23", "ALSI0_lastTS": "2023_12_13_09", "W0_midPrice": 644.6, "Volatility_W0": 1.391851094867216, "W0_symbol": "QWH24", "W0_lastTS": "2023_12_13_10", "HO0_ICE-US_CC0_VSR_uniDR_68_smoothSeed": 0.19281981573576087, "HO0_ICE-US_CC0_VSR_uniDR_68_zSeed": 0.012246640909572148, "HO0_ICE-US_CC0_VSR_uniDR_68_volSeed": 0.030292739873637575, "HO0_W0_VSR_uniDR_68_smoothSeed": 0.06639484897585443, "HO0_W0_VSR_uniDR_68_zSeed": -0.0013803713243258546, "HO0_W0_VSR_uniDR_68_volSeed": 0.030108646954579057, "HO0_ALSI0_Move_uniDR_8_smoothSeed": 3.2727265918141835, "HO0_ALSI0_Move_uniDR_8_zSeed": -7.879218498062713, "HO0_ALSI0_Move_uniDR_8_volSeed": 6.057923289923726}, "RS0": {"RS0_midPrice": 670.0, "Volatility_RS0": 2.301667149156025, "RS0_lastTS": "2023_12_13_09", "RS0_symbol": "@RSH24", "CNH=_midPrice": 7.187600004223435, "Volatility_CNH=": 0.0052350727070805785, "CNH=_symbol": "CNHUSD.COMP", "CNH=_lastTS": "2023_12_13_10", "HG0_midPrice": 3.7885, "Volatility_HG0": 0.011599168767095203, "HG0_symbol": "QHGH24", "HG0_lastTS": "2023_12_13_10", "ZC0_midPrice": 481.0, "Volatility_ZC0": 1.747226506188065, "ZC0_symbol": "@CH24", "ZC0_lastTS": "2023_12_13_09", "KE0_midPrice": 646.75, "Volatility_KE0": 3.2503007233478867, "KE0_symbol": "@KWH24", "KE0_lastTS": "2023_12_13_09", "CONF0_midPrice": 150.18, "Volatility_CONF0": 0.14950437004800343, "CONF0_symbol": "COH24", "CONF0_lastTS": "2023_12_13_09", "CAD=_midPrice": 1.355619721555709, "Volatility_CAD=": 0.001623072886196742, "CAD=_symbol": "CADUSD.COMP", "CAD=_lastTS": "2023_12_13_10", "ZW0_midPrice": 614.75, "Volatility_ZW0": 3.259906644552026, "ZW0_symbol": "@WH24", "ZW0_lastTS": "2023_12_13_09", "AUD=_midPrice": 0.65764, "Volatility_AUD=": 0.0013250926778341492, "AUD=_symbol": "AUDUSD.COMP", "AUD=_lastTS": "2023_12_13_10", "RS0_ZW0_Move_uniDR_5_smoothSeed": -0.5270711327332878, "RS0_ZW0_Move_uniDR_5_zSeed": -0.15558609720091382, "RS0_ZW0_Move_uniDR_5_volSeed": 0.2537338967821811, "RS0_AUD=_Move_uniDR_68_smoothSeed": -3.7899755533937386e-05, "RS0_AUD=_Move_uniDR_68_zSeed": -1.363858175013218e-06, "RS0_AUD=_Move_uniDR_68_volSeed": 2.3828106484288956e-05, "RS0_CNH=_VSR_uniDR_68_smoothSeed": 0.03458258538311562, "RS0_CNH=_VSR_uniDR_68_zSeed": 0.000972234827524689, "RS0_CNH=_VSR_uniDR_68_volSeed": 0.04287857146645121, "RS0_KE0_Move_uniDR_5_smoothSeed": -0.3176403263331758, "RS0_KE0_Move_uniDR_5_zSeed": -0.01726895590618599, "RS0_KE0_Move_uniDR_5_volSeed": 0.24367990843348789, "RS0_HG0_Move_uniDR_68_smoothSeed": 0.00010107074434891595, "RS0_HG0_Move_uniDR_68_zSeed": 2.249412484464759e-05, "RS0_HG0_Move_uniDR_68_volSeed": 0.00021411472735279144, "RS0_CONF0_VSR_uniDR_17_smoothSeed": 0.013673890426177199, "RS0_CONF0_VSR_uniDR_17_zSeed": -0.017059011012573032, "RS0_CONF0_VSR_uniDR_17_volSeed": 0.06458902999715366, "RS0_ZC0_Move_uniDR_5_smoothSeed": -0.16382409278516782, "RS0_ZC0_Move_uniDR_5_zSeed": -0.07036553394874251, "RS0_ZC0_Move_uniDR_5_volSeed": 0.12921004877558875}, "W0": {"W0_midPrice": 644.6, "Volatility_W0": 2.0576199870185232, "W0_lastTS": "2023_12_13_10", "W0_symbol": "QWH24", "RB0_midPrice": 1.9856, "Volatility_RB0": 0.014259169405937935, "RB0_symbol": "QRBF24", "RB0_lastTS": "2023_12_13_10", "ECO0_midPrice": 439.0, "Volatility_ECO0": 2.263777519456417, "ECO0_symbol": "PGG24", "ECO0_lastTS": "2023_12_13_09", "KE0_midPrice": 646.75, "Volatility_KE0": 4.02964359852073, "KE0_symbol": "@KWH24", "KE0_lastTS": "2023_12_13_09", "W0_KE0_Move_uniDR_5_smoothSeed": 0.06689846399452856, "W0_KE0_Move_uniDR_5_zSeed": 0.03451897924031175, "W0_KE0_Move_uniDR_5_volSeed": 0.3157937279416498, "W0_RB0_Move_uniDR_8_smoothSeed": -0.0021567741081035064, "W0_RB0_Move_uniDR_8_zSeed": -0.0003840993131656335, "W0_RB0_Move_uniDR_8_volSeed": 0.000912258108332651, "W0_ECO0_Move_uniDR_5_smoothSeed": -0.18241297255459676, "W0_ECO0_Move_uniDR_5_zSeed": -0.030677821425598786, "W0_ECO0_Move_uniDR_5_volSeed": 0.1972690283759911}, "ICE-US_CT0": {"ICE-US_CT0_midPrice": 81.04, "Volatility_ICE-US_CT0": 0.3581980538344648, "ICE-US_CT0_lastTS": "2023_12_13_10", "ICE-US_CT0_symbol": "@CTH24", "ICE-EU_G0_midPrice": 733.0, "Volatility_ICE-EU_G0": 4.025685689488885, "ICE-EU_G0_symbol": "GASF24", "ICE-EU_G0_lastTS": "2023_12_13_10", "ZF0_midPrice": 107.28125, "Volatility_ZF0": 0.06259580544867684, "ZF0_symbol": "@FVH24", "ZF0_lastTS": "2023_12_13_10", "ICE-US_MME0_midPrice": 972.8, "Volatility_ICE-US_MME0": 2.998096349064204, "ICE-US_MME0_symbol": "MEFZ23", "ICE-US_MME0_lastTS": "2023_12_13_08", "ZM0_midPrice": 403.6, "Volatility_ZM0": 1.5041917069316937, "ZM0_symbol": "@SMF24", "ZM0_lastTS": "2023_12_13_09", "ZT0_midPrice": 102.265625, "Volatility_ZT0": 0.022083142863750915, "ZT0_symbol": "@TUH24", "ZT0_lastTS": "2023_12_13_10", "ICE-EU_BRN0_midPrice": 73.51, "Volatility_ICE-EU_BRN0": 0.3703017913203958, "ICE-EU_BRN0_symbol": "QBZG24", "ICE-EU_BRN0_lastTS": "2023_12_13_10", "FESB0_midPrice": 118.4, "Volatility_FESB0": 0.4663636142158864, "FESB0_symbol": "SXZ23", "FESB0_lastTS": "2023_12_13_10", "CL0_midPrice": 68.91, "Volatility_CL0": 0.3826418064926941, "CL0_symbol": "QCLF24", "CL0_lastTS": "2023_12_13_10", "ICE-US_CT0_ZF0_Move_uniDR_68_smoothSeed": 9.339860884636543e-05, "ICE-US_CT0_ZF0_Move_uniDR_68_zSeed": -8.724616125342114e-05, "ICE-US_CT0_ZF0_Move_uniDR_68_volSeed": 0.0013731240294104635, "ICE-US_CT0_ZM0_Move_uniDR_68_smoothSeed": -0.06107751566229062, "ICE-US_CT0_ZM0_Move_uniDR_68_zSeed": -0.0025084569698770815, "ICE-US_CT0_ZM0_Move_uniDR_68_volSeed": 0.038524855420461794, "ICE-US_CT0_CL0_VSR_uniDR_18_smoothSeed": -0.05397930997740819, "ICE-US_CT0_CL0_VSR_uniDR_18_zSeed": -0.01844018712717764, "ICE-US_CT0_CL0_VSR_uniDR_18_volSeed": 0.04589768678569053, "ICE-US_CT0_ICE-EU_BRN0_VSR_uniDR_18_smoothSeed": -0.06966149868357854, "ICE-US_CT0_ICE-EU_BRN0_VSR_uniDR_18_zSeed": -0.01997372558563182, "ICE-US_CT0_ICE-EU_BRN0_VSR_uniDR_18_volSeed": 0.047141570768649714, "ICE-US_CT0_ICE-EU_G0_VSR_uniDR_18_smoothSeed": -0.04485552648763281, "ICE-US_CT0_ICE-EU_G0_VSR_uniDR_18_zSeed": -0.026441121590245757, "ICE-US_CT0_ICE-EU_G0_VSR_uniDR_18_volSeed": 0.048022006274207094, "ICE-US_CT0_ICE-US_MME0_VSR_uniDR_5_smoothSeed": -0.008822382938496937, "ICE-US_CT0_ICE-US_MME0_VSR_uniDR_5_zSeed": -0.018303693269652824, "ICE-US_CT0_ICE-US_MME0_VSR_uniDR_5_volSeed": 0.09101676278941938, "ICE-US_CT0_FESB0_VSR_uniDR_5_smoothSeed": 0.08690999352087075, "ICE-US_CT0_FESB0_VSR_uniDR_5_zSeed": -0.010914956339705515, "ICE-US_CT0_FESB0_VSR_uniDR_5_volSeed": 0.09301068637053365, "ICE-US_CT0_ZT0_Move_uniDR_68_smoothSeed": 0.0003081527196647589, "ICE-US_CT0_ZT0_Move_uniDR_68_zSeed": -4.52805205224136e-05, "ICE-US_CT0_ZT0_Move_uniDR_68_volSeed": 0.0005236638753305753}, "ICE-EU_G0": {"ICE-EU_G0_midPrice": 733.0, "Volatility_ICE-EU_G0": 3.5810367655489337, "ICE-EU_G0_lastTS": "2023_12_13_10", "ICE-EU_G0_symbol": "GASF24", "ZL0_midPrice": 50.45, "Volatility_ZL0": 0.18937414294341048, "ZL0_symbol": "@BOF24", "ZL0_lastTS": "2023_12_13_09", "ALSI0_midPrice": 66923.0, "Volatility_ALSI0": 106.56165878145879, "ALSI0_symbol": "ALJZ23", "ALSI0_lastTS": "2023_12_13_09", "ZN0_midPrice": 110.84375, "Volatility_ZN0": 0.08812485528595164, "ZN0_symbol": "@TYH24", "ZN0_lastTS": "2023_12_13_10", "W0_midPrice": 644.6, "Volatility_W0": 1.4696827612822623, "W0_symbol": "QWH24", "W0_lastTS": "2023_12_13_10", "ICE-LX_C0_midPrice": 3543.0, "Volatility_ICE-LX_C0": 5.733162961191125, "ICE-LX_C0_symbol": "QCH24", "ICE-LX_C0_lastTS": "2023_12_13_10", "ICE-EU_G0_ALSI0_Move_uniDR_6_smoothSeed": 5.009223367591567, "ICE-EU_G0_ALSI0_Move_uniDR_6_zSeed": -16.03360028032345, "ICE-EU_G0_ALSI0_Move_uniDR_6_volSeed": 7.570511013739343, "ICE-EU_G0_ICE-LX_C0_VSR_uniDR_68_smoothSeed": 0.011659806254402941, "ICE-EU_G0_ICE-LX_C0_VSR_uniDR_68_zSeed": 0.0006695875002459331, "ICE-EU_G0_ICE-LX_C0_VSR_uniDR_68_volSeed": 0.037590673620134386, "ICE-EU_G0_W0_VSR_uniDR_68_smoothSeed": 0.011775165506525076, "ICE-EU_G0_W0_VSR_uniDR_68_zSeed": -0.0030035658507147965, "ICE-EU_G0_W0_VSR_uniDR_68_volSeed": 0.03180625414109338, "ICE-EU_G0_ZN0_VSR_uniDR_35_smoothSeed": 0.1184509400297543, "ICE-EU_G0_ZN0_VSR_uniDR_35_zSeed": 0.0030549488165521332, "ICE-EU_G0_ZN0_VSR_uniDR_35_volSeed": 0.05849895414063306, "ICE-EU_G0_ZL0_Move_uniDR_68_smoothSeed": 0.0004614740782495693, "ICE-EU_G0_ZL0_Move_uniDR_68_zSeed": 0.0003719876247802185, "ICE-EU_G0_ZL0_Move_uniDR_68_volSeed": 0.004057039882809831}, "ICE-US_KC0": {"ICE-US_KC0_midPrice": 190.05, "Volatility_ICE-US_KC0": 1.0072031776814052, "ICE-US_KC0_lastTS": "2023_12_13_10", "ICE-US_KC0_symbol": "@KCH24", "NG0_midPrice": 2.305, "Volatility_NG0": 0.04354512998801104, "NG0_symbol": "QNGF24", "NG0_lastTS": "2023_12_13_10", "RS1_midPrice": 670.0, "Volatility_RS1": 2.620525663511921, "RS1_symbol": "@RSH24", "RS1_lastTS": "2023_12_13_09", "RB0_midPrice": 1.9856, "Volatility_RB0": 0.014456122522669706, "RB0_symbol": "QRBF24", "RB0_lastTS": "2023_12_13_10", "RS0_midPrice": 670.0, "Volatility_RS0": 2.6926861677906104, "RS0_symbol": "@RSH24", "RS0_lastTS": "2023_12_13_09", "ICE-US_KC0_RB0_Move_uniDR_35_smoothSeed": -0.0014587139277407984, "ICE-US_KC0_RB0_Move_uniDR_35_zSeed": -6.633383828279938e-05, "ICE-US_KC0_RB0_Move_uniDR_35_volSeed": 0.00040961974994186746, "ICE-US_KC0_NG0_Move_uniDR_35_smoothSeed": -0.001399998607489415, "ICE-US_KC0_NG0_Move_uniDR_35_zSeed": -1.4676767031216621e-05, "ICE-US_KC0_NG0_Move_uniDR_35_volSeed": 0.0013938418132348012, "ICE-US_KC0_RS1_Basis_uniDR_69_smoothSeed": 159.86966700229857, "ICE-US_KC0_RS1_Basis_uniDR_69_zSeed": 3.3868249686613034, "ICE-US_KC0_RS1_Basis_uniDR_69_volSeed": 0.3134271664892113}}, "initPositions": {"ZN0": 0, "ZF0": 0, "FBTP0": 0, "AP0": 0, "ES0": 0, "FSMI0": 0, "FTI0": 0, "ALSI0": 0, "ZC0": 0, "ZS0": 0, "ZM0": 0, "ZW0": 0, "KE0": 0, "LE0": 0, "CL0": 0, "HO0": 0, "RS0": 0, "W0": 0, "ICE-US_CT0": -1, "ICE-EU_G0": 0, "ICE-US_KC0": 0}, "trades": {"ZN0": 0, "ZF0": 0, "FBTP0": 0, "AP0": 0, "ES0": 0, "FSMI0": 0, "FTI0": -1, "ALSI0": 4, "ZC0": 0, "ZS0": 0, "ZM0": 0, "ZW0": 0, "KE0": -1, "LE0": 1, "CL0": 0, "HO0": 0, "RS0": -1, "W0": 0, "ICE-US_CT0": 0, "ICE-EU_G0": 0, "ICE-US_KC0": -2}, "seedDump": {"ZN0": {"ZN0_midPrice": 110.765625, "Volatility_ZN0": 0.08528470496483775, "ZN0_lastTS": "2023_12_13_11", "ZN0_symbol": "@TYH24", "AUD=_midPrice": 0.65737, "Volatility_AUD=": 0.0010430138817226974, "AUD=_symbol": "AUDUSD.COMP", "AUD=_lastTS": "2023_12_13_11", "CAD=_midPrice": 1.3570914815367703, "Volatility_CAD=": 0.0012776763523294095, "CAD=_symbol": "CADUSD.COMP", "CAD=_lastTS": "2023_12_13_11", "PL0_midPrice": 934.9, "Volatility_PL0": 3.4984630050738565, "PL0_symbol": "QPLF24", "PL0_lastTS": "2023_12_13_11", "CL0_midPrice": 69.39, "Volatility_CL0": 0.3150848466357357, "CL0_symbol": "QCLG24", "CL0_lastTS": "2023_12_13_11", "ICE-US_CT0_midPrice": 80.94, "Volatility_ICE-US_CT0": 0.295815916110473, "ICE-US_CT0_symbol": "@CTH24", "ICE-US_CT0_lastTS": "2023_12_13_11", "ZN0_CL0_Move_uniDR_9_smoothSeed": -0.0027498265108914155, "ZN0_CL0_Move_uniDR_9_zSeed": -0.010726601677017155, "ZN0_CL0_Move_uniDR_9_volSeed": 0.018116438695510398, "ZN0_PL0_Move_uniDR_9_smoothSeed": 0.41410298611436713, "ZN0_PL0_Move_uniDR_9_zSeed": 0.1620143581566321, "ZN0_PL0_Move_uniDR_9_volSeed": 0.17875444421778564, "ZN0_AUD=_Move_uniDR_35_smoothSeed": 1.4031158408168114e-05, "ZN0_AUD=_Move_uniDR_35_zSeed": 6.124007585690438e-07, "ZN0_AUD=_Move_uniDR_35_volSeed": 2.6297720781478688e-05, "ZN0_CAD=_Move_uniDR_18_smoothSeed": -5.872585802130964e-05, "ZN0_CAD=_Move_uniDR_18_zSeed": -4.641112838808238e-06, "ZN0_CAD=_Move_uniDR_18_volSeed": 4.9269533851391166e-05, "ZN0_ICE-US_CT0_Move_uniDR_68_smoothSeed": -0.0025762266873102647, "ZN0_ICE-US_CT0_Move_uniDR_68_zSeed": 0.0007855017104736288, "ZN0_ICE-US_CT0_Move_uniDR_68_volSeed": 0.005390772543330535}, "ZF0": {"ZF0_midPrice": 107.2109375, "Volatility_ZF0": 0.05372146987368349, "ZF0_lastTS": "2023_12_13_11", "ZF0_symbol": "@FVH24", "NZD=_midPrice": 0.61147, "Volatility_NZD=": 0.0009787026798398503, "NZD=_symbol": "NZDUSD.COMP", "NZD=_lastTS": "2023_12_13_11", "PL0_midPrice": 934.9, "Volatility_PL0": 3.4240818681453216, "PL0_symbol": "QPLF24", "PL0_lastTS": "2023_12_13_11", "CL0_midPrice": 69.39, "Volatility_CL0": 0.31735909698053427, "CL0_symbol": "QCLG24", "CL0_lastTS": "2023_12_13_11", "HO0_midPrice": 2.5434, "Volatility_HO0": 0.010703017959638421, "HO0_symbol": "QHOF24", "HO0_lastTS": "2023_12_13_11", "ZF0_HO0_Move_uniDR_68_smoothSeed": -0.0005009811455820389, "ZF0_HO0_Move_uniDR_68_zSeed": -2.5262681770746737e-05, "ZF0_HO0_Move_uniDR_68_volSeed": 0.00028194313015588064, "ZF0_NZD=_Move_uniDR_6_smoothSeed": 0.00011597360503421152, "ZF0_NZD=_Move_uniDR_6_zSeed": -1.9507602891691873e-05, "ZF0_NZD=_Move_uniDR_6_volSeed": 6.37533017067855e-05, "ZF0_PL0_Move_uniDR_9_smoothSeed": 0.47001608719255494, "ZF0_PL0_Move_uniDR_9_zSeed": 0.16808327821953586, "ZF0_PL0_Move_uniDR_9_volSeed": 0.17640545048830644, "ZF0_CL0_Move_uniDR_6_smoothSeed": -0.0019559609008314876, "ZF0_CL0_Move_uniDR_6_zSeed": -0.022155527293749293, "ZF0_CL0_Move_uniDR_6_volSeed": 0.022492347351806677}, "FBTP0": {"FBTP0_midPrice": 117.01, "Volatility_FBTP0": 0.22959977626159656, "FBTP0_lastTS": "2023_12_13_11", "FBTP0_symbol": "BTPH24", "ICE-EU_BRN0_midPrice": 73.8, "Volatility_ICE-EU_BRN0": 0.43615834026379025, "ICE-EU_BRN0_symbol": "QBZG24", "ICE-EU_BRN0_lastTS": "2023_12_13_11", "FTI0_midPrice": 792.75, "Volatility_FTI0": 1.7825351718002407, "FTI0_symbol": "AEXF24", "FTI0_lastTS": "2023_12_13_10", "EUR=_midPrice": 1.07903, "Volatility_EUR=": 0.0016327890977431492, "EUR=_symbol": "EURUSD.COMP", "EUR=_lastTS": "2023_12_13_11", "CL0_midPrice": 69.39, "Volatility_CL0": 0.4420514649909808, "CL0_symbol": "QCLG24", "CL0_lastTS": "2023_12_13_11", "ICE-EU_G0_midPrice": 735.5, "Volatility_ICE-EU_G0": 5.089006403220101, "ICE-EU_G0_symbol": "GASF24", "ICE-EU_G0_lastTS": "2023_12_13_11", "ICE-LL_R0_midPrice": 99.96, "Volatility_ICE-LL_R0": 0.16119026341713913, "ICE-LL_R0_symbol": "LGH24", "ICE-LL_R0_lastTS": "2023_12_13_11", "FBTP0_ICE-LL_R0_Move_uniDR_68_smoothSeed": 0.022182318564130343, "FBTP0_ICE-LL_R0_Move_uniDR_68_zSeed": 0.000267846171481491, "FBTP0_ICE-LL_R0_Move_uniDR_68_volSeed": 0.003247877951841013, "FBTP0_FTI0_VSR_uniDR_68_smoothSeed": 0.05836397509328779, "FBTP0_FTI0_VSR_uniDR_68_zSeed": 0.0024775373669674258, "FBTP0_FTI0_VSR_uniDR_68_volSeed": 0.02733526739532841, "FBTP0_CL0_VSR_uniDR_68_smoothSeed": -0.07045245098517817, "FBTP0_CL0_VSR_uniDR_68_zSeed": -0.00047792192651699547, "FBTP0_CL0_VSR_uniDR_68_volSeed": 0.04627363668156994, "FBTP0_ICE-EU_G0_VSR_uniDR_35_smoothSeed": -0.10734660281729681, "FBTP0_ICE-EU_G0_VSR_uniDR_35_zSeed": -0.0028869727371346474, "FBTP0_ICE-EU_G0_VSR_uniDR_35_volSeed": 0.06365389823626798, "FBTP0_ICE-EU_BRN0_VSR_uniDR_68_smoothSeed": -0.07422213228872898, "FBTP0_ICE-EU_BRN0_VSR_uniDR_68_zSeed": -0.0008338402653212422, "FBTP0_ICE-EU_BRN0_VSR_uniDR_68_volSeed": 0.050206894255302906}, "AP0": {"AP0_midPrice": 7285.0, "Volatility_AP0": 12.819868974910982, "AP0_lastTS": "2023_12_13_10", "AP0_symbol": "SPIZ23", "AUD=_midPrice": 0.65737, "Volatility_AUD=": 0.0012755238185507942, "AUD=_symbol": "AUDUSD.COMP", "AUD=_lastTS": "2023_12_13_11", "FBTS0_midPrice": 105.87, "Volatility_FBTS0": 0.052490197128197295, "FBTS0_symbol": "BTSH24", "FBTS0_lastTS": "2023_12_13_11", "JPY=_midPrice": 145.25300822611362, "Volatility_JPY=": 0.1834619366272944, "JPY=_symbol": "JPYUSD.COMP", "JPY=_lastTS": "2023_12_13_11", "FGBL0_midPrice": 135.61, "Volatility_FGBL0": 0.15380576245796057, "FGBL0_symbol": "BDH24", "FGBL0_lastTS": "2023_12_13_11", "ZS0_midPrice": 1309.5, "Volatility_ZS0": 3.931238120166011, "ZS0_symbol": "@SF24", "ZS0_lastTS": "2023_12_13_11", "NQ0_midPrice": 16614.75, "Volatility_NQ0": 28.310161758678824, "NQ0_symbol": "@NQH24", "NQ0_lastTS": "2023_12_13_11", "ICE-US_KC0_midPrice": 185.85, "Volatility_ICE-US_KC0": 0.7941433270336892, "ICE-US_KC0_symbol": "@KCH24", "ICE-US_KC0_lastTS": "2023_12_13_11", "ZS1_midPrice": 1328.5, "Volatility_ZS1": 3.8314917814466045, "ZS1_symbol": "@SH24", "ZS1_lastTS": "2023_12_13_11", "ICE-LL_R0_midPrice": 99.96, "Volatility_ICE-LL_R0": 0.12690539923997432, "ICE-LL_R0_symbol": "LGH24", "ICE-LL_R0_lastTS": "2023_12_13_11", "AP0_FGBL0_Basis_uniDR_6_smoothSeed": -7133.581729308599, "AP0_FGBL0_Basis_uniDR_6_zSeed": -4272.604483388041, "AP0_FGBL0_Basis_uniDR_6_volSeed": 764.9197891723596, "AP0_ICE-LL_R0_Move_uniDR_6_smoothSeed": 0.08902258582049909, "AP0_ICE-LL_R0_Move_uniDR_6_zSeed": 0.014898923328521222, "AP0_ICE-LL_R0_Move_uniDR_6_volSeed": 0.00835731025459989, "AP0_JPY=_Move_uniDR_35_smoothSeed": -0.0009245664389270409, "AP0_JPY=_Move_uniDR_35_zSeed": 0.0003657628580541535, "AP0_JPY=_Move_uniDR_35_volSeed": 0.005281200506485351, "AP0_ICE-US_KC0_Move_uniDR_17_smoothSeed": 0.02617538639330727, "AP0_ICE-US_KC0_Move_uniDR_17_zSeed": 0.018285771982609642, "AP0_ICE-US_KC0_Move_uniDR_17_volSeed": 0.03233544392386005, "AP0_ZS1_Basis_uniDR_35_smoothSeed": -4920.431710570508, "AP0_ZS1_Basis_uniDR_35_zSeed": -528.5073088226297, "AP0_ZS1_Basis_uniDR_35_volSeed": 76.8800344493999, "AP0_NQ0_VSR_uniDR_35_smoothSeed": 0.06712524257622254, "AP0_NQ0_VSR_uniDR_35_zSeed": 0.011699339273821954, "AP0_NQ0_VSR_uniDR_35_volSeed": 0.028729711984781137, "AP0_FBTS0_Move_uniDR_6_smoothSeed": 0.011913295834530137, "AP0_FBTS0_Move_uniDR_6_zSeed": -0.0015799025253055814, "AP0_FBTS0_Move_uniDR_6_volSeed": 0.0030984519382074873}, "ES0": {"ES0_midPrice": 4700.5, "Volatility_ES0": 6.777873343808145, "ES0_lastTS": "2023_12_13_11", "ES0_symbol": "@ESH24", "FTI0_midPrice": 792.75, "Volatility_FTI0": 1.2824904131998316, "FTI0_symbol": "AEXF24", "FTI0_lastTS": "2023_12_13_10", "ICE-LL_R0_midPrice": 99.96, "Volatility_ICE-LL_R0": 0.11594120967429905, "ICE-LL_R0_symbol": "LGH24", "ICE-LL_R0_lastTS": "2023_12_13_11", "FESX0_midPrice": 4546.0, "Volatility_FESX0": 8.31775836501915, "FESX0_symbol": "EXZ23", "FESX0_lastTS": "2023_12_13_11", "FCE0_midPrice": 7560.0, "Volatility_FCE0": 12.85664457131275, "FCE0_symbol": "MTZ23", "FCE0_lastTS": "2023_12_13_10", "FDAX0_midPrice": 16810.0, "Volatility_FDAX0": 28.917037895407038, "FDAX0_symbol": "DXMZ23", "FDAX0_lastTS": "2023_12_13_11", "ES0_FTI0_VSR_uniDR_5_smoothSeed": 0.07214927284936272, "ES0_FTI0_VSR_uniDR_5_zSeed": -0.028906970047588576, "ES0_FTI0_VSR_uniDR_5_volSeed": 0.05026462691858235, "ES0_FCE0_VSR_uniDR_5_smoothSeed": -0.02511272818686612, "ES0_FCE0_VSR_uniDR_5_zSeed": -0.03850403544727203, "ES0_FCE0_VSR_uniDR_5_volSeed": 0.053972158751174656, "ES0_FDAX0_VSR_uniDR_5_smoothSeed": -0.0028810126643288025, "ES0_FDAX0_VSR_uniDR_5_zSeed": -0.06323908836205824, "ES0_FDAX0_VSR_uniDR_5_volSeed": 0.055027280008266316, "ES0_ICE-LL_R0_Move_uniDR_68_smoothSeed": 0.021115483396885404, "ES0_ICE-LL_R0_Move_uniDR_68_zSeed": 0.00037110016187713986, "ES0_ICE-LL_R0_Move_uniDR_68_volSeed": 0.002222979605876673, "ES0_FESX0_VSR_uniDR_5_smoothSeed": 0.011988262316014256, "ES0_FESX0_VSR_uniDR_5_zSeed": -0.049659313868369866, "ES0_FESX0_VSR_uniDR_5_volSeed": 0.05126994044076977}, "FSMI0": {"FSMI0_midPrice": 11191.0, "Volatility_FSMI0": 24.676688222935706, "FSMI0_lastTS": "2023_12_13_11", "FSMI0_symbol": "SWH24", "NG0_midPrice": 2.334, "Volatility_NG0": 0.03599609174625885, "NG0_symbol": "QNGF24", "NG0_lastTS": "2023_12_13_11", "CHF=_midPrice": 0.876516952610075, "Volatility_CHF=": 0.001461423749976311, "CHF=_symbol": "CHFUSD.COMP", "CHF=_lastTS": "2023_12_13_11", "FBTS0_midPrice": 105.87, "Volatility_FBTS0": 0.05003665089975527, "FBTS0_symbol": "BTSH24", "FBTS0_lastTS": "2023_12_13_11", "FSMI0_FBTS0_Move_uniDR_6_smoothSeed": 0.009155044068651436, "FSMI0_FBTS0_Move_uniDR_6_zSeed": -0.0021848856397032497, "FSMI0_FBTS0_Move_uniDR_6_volSeed": 0.0031817416928040395, "FSMI0_NG0_Move_uniDR_6_smoothSeed": 0.0017321510661439956, "FSMI0_NG0_Move_uniDR_6_zSeed": -0.0010976148843024924, "FSMI0_NG0_Move_uniDR_6_volSeed": 0.0026457201776321957}, "FTI0": {"FTI0_midPrice": 792.75, "Volatility_FTI0": 1.7308876004342826, "FTI0_lastTS": "2023_12_13_10", "FTI0_symbol": "AEXF24", "EUR=_midPrice": 1.07903, "Volatility_EUR=": 0.0015502009739121606, "EUR=_symbol": "EURUSD.COMP", "EUR=_lastTS": "2023_12_13_11", "HE1_midPrice": 74.375, "Volatility_HE1": 0.3979131416356248, "HE1_symbol": "@HEJ24", "HE1_lastTS": "2023_12_13_11", "FBTS0_midPrice": 105.87, "Volatility_FBTS0": 0.05755881451306642, "FBTS0_symbol": "BTSH24", "FBTS0_lastTS": "2023_12_13_11", "NG0_midPrice": 2.334, "Volatility_NG0": 0.03770063205214781, "NG0_symbol": "QNGF24", "NG0_lastTS": "2023_12_13_11", "ICE-US_KC0_midPrice": 185.85, "Volatility_ICE-US_KC0": 0.8751353837796848, "ICE-US_KC0_symbol": "@KCH24", "ICE-US_KC0_lastTS": "2023_12_13_11", "HE0_midPrice": 66.55, "Volatility_HE0": 0.3309534628440823, "HE0_symbol": "@HEG24", "HE0_lastTS": "2023_12_13_11", "FTI0_FBTS0_Move_uniDR_5_smoothSeed": 0.012663364995766854, "FTI0_FBTS0_Move_uniDR_5_zSeed": -0.0021928163961212757, "FTI0_FBTS0_Move_uniDR_5_volSeed": 0.003658050945531714, "FTI0_ICE-US_KC0_Move_uniDR_9_smoothSeed": 0.015127456152192242, "FTI0_ICE-US_KC0_Move_uniDR_9_zSeed": 0.03705932689617707, "FTI0_ICE-US_KC0_Move_uniDR_9_volSeed": 0.050574526082864515, "FTI0_HE1_Basis_uniDR_69_smoothSeed": -302.8971623079849, "FTI0_HE1_Basis_uniDR_69_zSeed": -9.242245761495596, "FTI0_HE1_Basis_uniDR_69_volSeed": 1.0131212689848714, "FTI0_NG0_Move_uniDR_35_smoothSeed": 7.583704221717099e-06, "FTI0_NG0_Move_uniDR_35_zSeed": 2.6202880284469393e-05, "FTI0_NG0_Move_uniDR_35_volSeed": 0.0011984764943332935}, "ALSI0": {"ALSI0_midPrice": 66738.0, "Volatility_ALSI0": 174.8448923129461, "ALSI0_lastTS": "2023_12_13_10", "ALSI0_symbol": "ALJZ23", "AUD=_midPrice": 0.65737, "Volatility_AUD=": 0.0017019310473413837, "AUD=_symbol": "AUDUSD.COMP", "AUD=_lastTS": "2023_12_13_11", "ZN0_midPrice": 110.765625, "Volatility_ZN0": 0.12162309422181812, "ZN0_symbol": "@TYH24", "ZN0_lastTS": "2023_12_13_11", "GC1_midPrice": 1988.5, "Volatility_GC1": 3.8193701022524915, "GC1_symbol": "QGCF24", "GC1_lastTS": "2023_12_13_11", "ES0_midPrice": 4700.5, "Volatility_ES0": 8.49622503180128, "ES0_symbol": "@ESH24", "ES0_lastTS": "2023_12_13_11", "ZAR=_midPrice": 19.03855306996668, "Volatility_ZAR=": 0.04892963138513601, "ZAR=_symbol": "ZARUSD.COMP", "ZAR=_lastTS": "2023_12_13_11", "ZF0_midPrice": 107.2109375, "Volatility_ZF0": 0.07463873629990195, "ZF0_symbol": "@FVH24", "ZF0_lastTS": "2023_12_13_11", "NQ0_midPrice": 16614.75, "Volatility_NQ0": 30.817665327680043, "NQ0_symbol": "@NQH24", "NQ0_lastTS": "2023_12_13_11", "GC0_midPrice": 1997.2, "Volatility_GC0": 3.810746570351846, "GC0_symbol": "QGCG24", "GC0_lastTS": "2023_12_13_11", "ALSI0_ZF0_Move_uniDR_18_smoothSeed": -0.005073645857650182, "ALSI0_ZF0_Move_uniDR_18_zSeed": -0.0011445746360001195, "ALSI0_ZF0_Move_uniDR_18_volSeed": 0.0029571739436078034, "ALSI0_GC1_Basis_uniDR_8_smoothSeed": -63330.267737652255, "ALSI0_GC1_Basis_uniDR_8_zSeed": -14994.786390267172, "ALSI0_GC1_Basis_uniDR_8_volSeed": 1613.56495854252, "ALSI0_ES0_Move_uniDR_18_smoothSeed": 0.5764747038136686, "ALSI0_ES0_Move_uniDR_18_zSeed": 0.12941467309038013, "ALSI0_ES0_Move_uniDR_18_volSeed": 0.3124748818736206, "ALSI0_NQ0_Move_uniDR_18_smoothSeed": 5.317468275720307, "ALSI0_NQ0_Move_uniDR_18_zSeed": 0.8207488290711124, "ALSI0_NQ0_Move_uniDR_18_volSeed": 1.062972319928385, "ALSI0_AUD=_VSR_uniDR_69_smoothSeed": 0.09242715782022591, "ALSI0_AUD=_VSR_uniDR_69_zSeed": 0.0024212185820378634, "ALSI0_AUD=_VSR_uniDR_69_volSeed": 0.018537018946763024, "ALSI0_ZN0_Move_uniDR_18_smoothSeed": -0.007130683683563904, "ALSI0_ZN0_Move_uniDR_18_zSeed": -0.0017708106633544491, "ALSI0_ZN0_Move_uniDR_18_volSeed": 0.004788372347554929}, "ZC0": {"ZC0_midPrice": 480.0, "Volatility_ZC0": 2.084900917410493, "ZC0_lastTS": "2023_12_13_11", "ZC0_symbol": "@CH24", "CNH=_midPrice": 7.187189989543788, "Volatility_CNH=": 0.004412628224084985, "CNH=_symbol": "CNHUSD.COMP", "CNH=_lastTS": "2023_12_13_11", "RB0_midPrice": 1.9923, "Volatility_RB0": 0.010415754044134582, "RB0_symbol": "QRBF24", "RB0_lastTS": "2023_12_13_11", "ZC1_midPrice": 480.0, "Volatility_ZC1": 1.8085266980807602, "ZC1_symbol": "@CH24", "ZC1_lastTS": "2023_12_13_11", "ZC0_ZC1_Basis_uniDR_6_smoothSeed": -0.0009638334465246343, "ZC0_ZC1_Basis_uniDR_6_zSeed": 2.6872419000414927e-05, "ZC0_ZC1_Basis_uniDR_6_volSeed": 0.049469422001326556, "ZC0_CNH=_Move_uniDR_68_smoothSeed": 2.704707822587247e-05, "ZC0_CNH=_Move_uniDR_68_zSeed": 3.659981007753926e-06, "ZC0_CNH=_Move_uniDR_68_volSeed": 0.00011001500843466752, "ZC0_RB0_Move_uniDR_38_smoothSeed": -0.0007013216912028756, "ZC0_RB0_Move_uniDR_38_zSeed": -3.093678108215297e-05, "ZC0_RB0_Move_uniDR_38_volSeed": 0.0002919328291952615}, "ZS0": {"ZS0_midPrice": 1309.5, "Volatility_ZS0": 4.418756148815769, "ZS0_lastTS": "2023_12_13_11", "ZS0_symbol": "@SF24", "IND0_midPrice": 126855.0, "Volatility_IND0": 291.1671468921123, "IND0_symbol": "INDZ23", "IND0_lastTS": "2023_12_13_10", "ZS1_midPrice": 1328.5, "Volatility_ZS1": 3.923758220997229, "ZS1_symbol": "@SH24", "ZS1_lastTS": "2023_12_13_11", "NQ0_midPrice": 16614.75, "Volatility_NQ0": 28.122591918670977, "NQ0_symbol": "@NQH24", "NQ0_lastTS": "2023_12_13_11", "XT0_midPrice": 95.739, "Volatility_XT0": 0.012361590985234181, "XT0_symbol": "XTZ23", "XT0_lastTS": "2023_12_13_10", "PA0_midPrice": 984.0, "Volatility_PA0": 9.120480611145862, "PA0_symbol": "QPAH24", "PA0_lastTS": "2023_12_13_11", "ZS0_PA0_VSR_uniDR_68_smoothSeed": 0.015221945003620375, "ZS0_PA0_VSR_uniDR_68_zSeed": -0.0013864636685941437, "ZS0_PA0_VSR_uniDR_68_volSeed": 0.027727369373641564, "ZS0_IND0_Move_uniDR_9_smoothSeed": -35.227924074268316, "ZS0_IND0_Move_uniDR_9_zSeed": -2.3443957005489278, "ZS0_IND0_Move_uniDR_9_volSeed": 16.68511742636969, "ZS0_NQ0_VSR_uniDR_68_smoothSeed": 0.11810051190979158, "ZS0_NQ0_VSR_uniDR_68_zSeed": 0.0037159153212860453, "ZS0_NQ0_VSR_uniDR_68_volSeed": 0.02891752144854222, "ZS0_ZS1_Basis_uniDR_6_smoothSeed": -0.07187328525165879, "ZS0_ZS1_Basis_uniDR_6_zSeed": 0.020568746859618084, "ZS0_ZS1_Basis_uniDR_6_volSeed": 0.06540956949430755, "ZS0_XT0_VSR_uniDR_68_smoothSeed": 0.05251179123127278, "ZS0_XT0_VSR_uniDR_68_zSeed": -0.001485757378987324, "ZS0_XT0_VSR_uniDR_68_volSeed": 0.03448742114524509}, "ZM0": {"ZM0_midPrice": 394.1, "Volatility_ZM0": 1.6433361492976175, "ZM0_lastTS": "2023_12_13_11", "ZM0_symbol": "@SMH24", "FSMI0_midPrice": 11191.0, "Volatility_FSMI0": 21.063366887748455, "FSMI0_symbol": "SWH24", "FSMI0_lastTS": "2023_12_13_11", "HG0_midPrice": 3.783, "Volatility_HG0": 0.010210302865308803, "HG0_symbol": "QHGH24", "HG0_lastTS": "2023_12_13_11", "FTI0_midPrice": 792.75, "Volatility_FTI0": 1.4020141720861028, "FTI0_symbol": "AEXF24", "FTI0_lastTS": "2023_12_13_10", "FESX0_midPrice": 4546.0, "Volatility_FESX0": 9.127612057972971, "FESX0_symbol": "EXZ23", "FESX0_lastTS": "2023_12_13_11", "CNH=_midPrice": 7.187189989543788, "Volatility_CNH=": 0.004360393561576019, "CNH=_symbol": "CNHUSD.COMP", "CNH=_lastTS": "2023_12_13_11", "YM0_midPrice": 36577.0, "Volatility_YM0": 66.75106220479489, "YM0_symbol": "@YMZ23", "YM0_lastTS": "2023_12_13_11", "FCE0_midPrice": 7560.0, "Volatility_FCE0": 14.071395809327324, "FCE0_symbol": "MTZ23", "FCE0_lastTS": "2023_12_13_10", "ICE-US_SB0_midPrice": 22.54, "Volatility_ICE-US_SB0": 0.06775304616715472, "ICE-US_SB0_symbol": "@SBH24", "ICE-US_SB0_lastTS": "2023_12_13_11", "ZM0_HG0_VSR_uniDR_18_smoothSeed": 0.06922203041317813, "ZM0_HG0_VSR_uniDR_18_zSeed": 0.005802554431772013, "ZM0_HG0_VSR_uniDR_18_volSeed": 0.054293391163958656, "ZM0_FESX0_VSR_uniDR_68_smoothSeed": 0.10123246853181948, "ZM0_FESX0_VSR_uniDR_68_zSeed": 0.0034992839582219503, "ZM0_FESX0_VSR_uniDR_68_volSeed": 0.027346587932079128, "ZM0_FSMI0_VSR_uniDR_68_smoothSeed": 0.10593658876132869, "ZM0_FSMI0_VSR_uniDR_68_zSeed": 0.0019317599751796377, "ZM0_FSMI0_VSR_uniDR_68_volSeed": 0.027466395918060698, "ZM0_FCE0_VSR_uniDR_68_smoothSeed": 0.09801059974924436, "ZM0_FCE0_VSR_uniDR_68_zSeed": 0.0040192045756241015, "ZM0_FCE0_VSR_uniDR_68_volSeed": 0.02626410106275305, "ZM0_ICE-US_SB0_VSR_uniDR_68_smoothSeed": -0.08130319747125725, "ZM0_ICE-US_SB0_VSR_uniDR_68_zSeed": -0.007480120672854882, "ZM0_ICE-US_SB0_VSR_uniDR_68_volSeed": 0.030357788904814585, "ZM0_FTI0_VSR_uniDR_35_smoothSeed": 0.18675643350339965, "ZM0_FTI0_VSR_uniDR_35_zSeed": 0.010313170905990744, "ZM0_FTI0_VSR_uniDR_35_volSeed": 0.03966998291433137, "ZM0_YM0_VSR_uniDR_18_smoothSeed": 0.14471095489513458, "ZM0_YM0_VSR_uniDR_18_zSeed": 0.021031209790176544, "ZM0_YM0_VSR_uniDR_18_volSeed": 0.05498121543054155, "ZM0_CNH=_VSR_uniDR_68_smoothSeed": 0.044603473223370965, "ZM0_CNH=_VSR_uniDR_68_zSeed": 0.0014116977859108485, "ZM0_CNH=_VSR_uniDR_68_volSeed": 0.03651153293840095}, "ZW0": {"ZW0_midPrice": 614.5, "Volatility_ZW0": 3.663506078188512, "ZW0_lastTS": "2023_12_13_11", "ZW0_symbol": "@WH24", "ICE-LL_Z0_midPrice": 7595.0, "Volatility_ICE-LL_Z0": 10.033367251638122, "ICE-LL_Z0_symbol": "TUKZ23", "ICE-LL_Z0_lastTS": "2023_12_12_05", "ICE-LX_C0_midPrice": 3544.0, "Volatility_ICE-LX_C0": 5.868796209812016, "ICE-LX_C0_symbol": "QCH24", "ICE-LX_C0_lastTS": "2023_12_13_11", "HE0_midPrice": 66.55, "Volatility_HE0": 0.27654060761515425, "HE0_symbol": "@HEG24", "HE0_lastTS": "2023_12_13_11", "ZW0_ICE-LL_Z0_Move_uniDR_35_smoothSeed": 0.6481265050018359, "ZW0_ICE-LL_Z0_Move_uniDR_35_zSeed": 0.07459082377204464, "ZW0_ICE-LL_Z0_Move_uniDR_35_volSeed": 0.29886751614553086, "ZW0_ICE-LX_C0_Move_uniDR_5_smoothSeed": 0.19137504240580164, "ZW0_ICE-LX_C0_Move_uniDR_5_zSeed": 0.5298031019535531, "ZW0_ICE-LX_C0_Move_uniDR_5_volSeed": 0.49051918383332166, "ZW0_HE0_VSR_uniDR_68_smoothSeed": -0.043473010550486274, "ZW0_HE0_VSR_uniDR_68_zSeed": 0.000540994605086847, "ZW0_HE0_VSR_uniDR_68_volSeed": 0.030345544481812984}, "KE0": {"KE0_midPrice": 640.75, "Volatility_KE0": 3.73303795850996, "KE0_lastTS": "2023_12_13_11", "KE0_symbol": "@KWH24", "W0_midPrice": 638.0, "Volatility_W0": 1.4812465269744377, "W0_symbol": "QWH24", "W0_lastTS": "2023_12_13_11", "ICE-LX_C0_midPrice": 3544.0, "Volatility_ICE-LX_C0": 5.850779401739915, "ICE-LX_C0_symbol": "QCH24", "ICE-LX_C0_lastTS": "2023_12_13_11", "ZAR=_midPrice": 19.03855306996668, "Volatility_ZAR=": 0.033441544109997674, "ZAR=_symbol": "ZARUSD.COMP", "ZAR=_lastTS": "2023_12_13_11", "KE0_ZAR=_Move_uniDR_38_smoothSeed": 0.002397311016174684, "KE0_ZAR=_Move_uniDR_38_zSeed": 0.00017703079885956615, "KE0_ZAR=_Move_uniDR_38_volSeed": 0.0008703394383958192, "KE0_ICE-LX_C0_Move_uniDR_18_smoothSeed": 0.5198567658267297, "KE0_ICE-LX_C0_Move_uniDR_18_zSeed": 0.23104128727225326, "KE0_ICE-LX_C0_Move_uniDR_18_volSeed": 0.2488726843426718, "KE0_W0_Move_uniDR_5_smoothSeed": 0.14297272736666178, "KE0_W0_Move_uniDR_5_zSeed": -0.06120255238634021, "KE0_W0_Move_uniDR_5_volSeed": 0.11191707746530419}, "LE0": {"LE0_midPrice": 168.3, "Volatility_LE0": 0.443127508210129, "LE0_lastTS": "2023_12_13_11", "LE0_symbol": "@LEG24", "ICE-US_CC0_midPrice": 4465.0, "Volatility_ICE-US_CC0": 15.462551855299711, "ICE-US_CC0_symbol": "@CCZ23", "ICE-US_CC0_lastTS": "2023_12_12_14", "EUR=_midPrice": 1.07903, "Volatility_EUR=": 0.0019835192007986303, "EUR=_symbol": "EURUSD.COMP", "EUR=_lastTS": "2023_12_13_11", "FESX0_midPrice": 4546.0, "Volatility_FESX0": 13.500394442349425, "FESX0_symbol": "EXZ23", "FESX0_lastTS": "2023_12_13_11", "VX0_midPrice": 12.45, "Volatility_VX0": 0.35460342366060454, "VX0_symbol": "@VXZ23", "VX0_lastTS": "2023_12_13_11", "FCE0_midPrice": 7560.0, "Volatility_FCE0": 19.20485991765017, "FCE0_symbol": "MTZ23", "FCE0_lastTS": "2023_12_13_10", "KE0_midPrice": 640.75, "Volatility_KE0": 4.60414154108912, "KE0_symbol": "@KWH24", "KE0_lastTS": "2023_12_13_11", "LE0_FCE0_Move_uniDR_5_smoothSeed": 0.8465161259539413, "LE0_FCE0_Move_uniDR_5_zSeed": 0.7328676704952499, "LE0_FCE0_Move_uniDR_5_volSeed": 1.3500830256442888, "LE0_VX0_VSR_uniDR_5_smoothSeed": -0.53813253559423, "LE0_VX0_VSR_uniDR_5_zSeed": -0.1325868998691115, "LE0_VX0_VSR_uniDR_5_volSeed": 0.131719450091102, "LE0_ICE-US_CC0_VSR_uniDR_5_smoothSeed": 0.029307852552710026, "LE0_ICE-US_CC0_VSR_uniDR_5_zSeed": 0.04403471723165696, "LE0_ICE-US_CC0_VSR_uniDR_5_volSeed": 0.11898371651041924, "LE0_EUR=_VSR_uniDR_79_smoothSeed": -0.07776998945798042, "LE0_EUR=_VSR_uniDR_79_zSeed": -0.000704938337042325, "LE0_EUR=_VSR_uniDR_79_volSeed": 0.04618793275865303, "LE0_FESX0_Move_uniDR_5_smoothSeed": 1.0640339652646031, "LE0_FESX0_Move_uniDR_5_zSeed": 0.4966258804203485, "LE0_FESX0_Move_uniDR_5_volSeed": 0.9765019665440915, "LE0_KE0_VSR_uniDR_79_smoothSeed": -0.09178993763655392, "LE0_KE0_VSR_uniDR_79_zSeed": -0.0007992828074256002, "LE0_KE0_VSR_uniDR_79_volSeed": 0.036129744001085436}, "CL0": {"CL0_midPrice": 69.39, "Volatility_CL0": 0.31868649795642573, "CL0_lastTS": "2023_12_13_11", "CL0_symbol": "QCLG24", "SGD=_midPrice": 1.342100000324654, "Volatility_SGD=": 0.0008820248272999621, "SGD=_symbol": "SGDUSD.COMP", "SGD=_lastTS": "2023_12_13_11", "THB=_midPrice": 35.724999386423136, "Volatility_THB=": 0.03593145142701284, "THB=_symbol": "THBUSD.COMP", "THB=_lastTS": "2023_12_13_11", "ALSI0_midPrice": 66738.0, "Volatility_ALSI0": 103.67544023220691, "ALSI0_symbol": "ALJZ23", "ALSI0_lastTS": "2023_12_13_10", "ZF0_midPrice": 107.2109375, "Volatility_ZF0": 0.05392860545340154, "ZF0_symbol": "@FVH24", "ZF0_lastTS": "2023_12_13_11", "CL0_ZF0_VSR_uniDR_68_smoothSeed": 0.030031186991114296, "CL0_ZF0_VSR_uniDR_68_zSeed": -0.0037359686802076538, "CL0_ZF0_VSR_uniDR_68_volSeed": 0.04232610559420153, "CL0_THB=_Move_uniDR_35_smoothSeed": 0.0010519544483712138, "CL0_THB=_Move_uniDR_35_zSeed": 0.0004824962171250552, "CL0_THB=_Move_uniDR_35_volSeed": 0.0008592766389778175, "CL0_ALSI0_Move_uniDR_6_smoothSeed": -14.221995515630477, "CL0_ALSI0_Move_uniDR_6_zSeed": -15.664271300268677, "CL0_ALSI0_Move_uniDR_6_volSeed": 7.390955354981497, "CL0_SGD=_Move_uniDR_68_smoothSeed": -1.1979539957811363e-05, "CL0_SGD=_Move_uniDR_68_zSeed": -6.774164910732698e-08, "CL0_SGD=_Move_uniDR_68_volSeed": 1.7336831355177596e-05}, "HO0": {"HO0_midPrice": 2.5434, "Volatility_HO0": 0.010673917452172572, "HO0_lastTS": "2023_12_13_11", "HO0_symbol": "QHOF24", "W0_midPrice": 638.0, "Volatility_W0": 1.4061652087482197, "W0_symbol": "QWH24", "W0_lastTS": "2023_12_13_11", "ICE-US_CC0_midPrice": 4465.0, "Volatility_ICE-US_CC0": 9.671192404718655, "ICE-US_CC0_symbol": "@CCZ23", "ICE-US_CC0_lastTS": "2023_12_12_14", "ALSI0_midPrice": 66738.0, "Volatility_ALSI0": 100.7442986500744, "ALSI0_symbol": "ALJZ23", "ALSI0_lastTS": "2023_12_13_10", "HO0_ICE-US_CC0_VSR_uniDR_68_smoothSeed": 0.18468850305932488, "HO0_ICE-US_CC0_VSR_uniDR_68_zSeed": 0.01242232722130677, "HO0_ICE-US_CC0_VSR_uniDR_68_volSeed": 0.030280613861823468, "HO0_W0_VSR_uniDR_68_smoothSeed": 0.01194506874410562, "HO0_W0_VSR_uniDR_68_zSeed": -0.0013667951695066124, "HO0_W0_VSR_uniDR_68_volSeed": 0.030094187444484412, "HO0_ALSI0_Move_uniDR_8_smoothSeed": -12.353148490138775, "HO0_ALSI0_Move_uniDR_8_zSeed": -7.917814700802526, "HO0_ALSI0_Move_uniDR_8_volSeed": 6.059987331907316}, "RS0": {"RS0_midPrice": 669.6, "Volatility_RS0": 2.300592964070127, "RS0_lastTS": "2023_12_13_10", "RS0_symbol": "@RSH24", "AUD=_midPrice": 0.65737, "Volatility_AUD=": 0.0013244814763718508, "AUD=_symbol": "AUDUSD.COMP", "AUD=_lastTS": "2023_12_13_11", "HG0_midPrice": 3.783, "Volatility_HG0": 0.011594842097557139, "HG0_symbol": "QHGH24", "HG0_lastTS": "2023_12_13_11", "CAD=_midPrice": 1.3570914815367703, "Volatility_CAD=": 0.0016229340675977765, "CAD=_symbol": "CADUSD.COMP", "CAD=_lastTS": "2023_12_13_11", "CONF0_midPrice": 150.3, "Volatility_CONF0": 0.14947877892294034, "CONF0_symbol": "COH24", "CONF0_lastTS": "2023_12_13_10", "CNH=_midPrice": 7.187189989543788, "Volatility_CNH=": 0.005232568857126873, "CNH=_symbol": "CNHUSD.COMP", "CNH=_lastTS": "2023_12_13_11", "ZC0_midPrice": 480.0, "Volatility_ZC0": 1.746661150542295, "ZC0_symbol": "@CH24", "ZC0_lastTS": "2023_12_13_11", "KE0_midPrice": 640.75, "Volatility_KE0": 3.254063601234602, "KE0_symbol": "@KWH24", "KE0_lastTS": "2023_12_13_11", "ZW0_midPrice": 614.5, "Volatility_ZW0": 3.2583470875177545, "ZW0_symbol": "@WH24", "ZW0_lastTS": "2023_12_13_11", "RS0_ZW0_Move_uniDR_5_smoothSeed": -0.49120443067405883, "RS0_ZW0_Move_uniDR_5_zSeed": -0.1602066539752849, "RS0_ZW0_Move_uniDR_5_volSeed": 0.25366047678045783, "RS0_AUD=_Move_uniDR_68_smoothSeed": -4.025361521819342e-05, "RS0_AUD=_Move_uniDR_68_zSeed": -1.4034796329005055e-06, "RS0_AUD=_Move_uniDR_68_volSeed": 2.381667932368845e-05, "RS0_CNH=_VSR_uniDR_68_smoothSeed": 0.0352004848923021, "RS0_CNH=_VSR_uniDR_68_zSeed": 0.0010071070733705897, "RS0_CNH=_VSR_uniDR_68_volSeed": 0.0428579481241251, "RS0_KE0_Move_uniDR_5_smoothSeed": -1.0532185852381661, "RS0_KE0_Move_uniDR_5_zSeed": -0.03153118058319436, "RS0_KE0_Move_uniDR_5_volSeed": 0.2435646047089065, "RS0_HG0_Move_uniDR_68_smoothSeed": 4.426712208596222e-05, "RS0_HG0_Move_uniDR_68_zSeed": 2.2516307495269938e-05, "RS0_HG0_Move_uniDR_68_volSeed": 0.00021401282730714564, "RS0_CONF0_VSR_uniDR_17_smoothSeed": 0.05214828641260778, "RS0_CONF0_VSR_uniDR_17_zSeed": -0.01677740407590024, "RS0_CONF0_VSR_uniDR_17_volSeed": 0.06456004512236992, "RS0_ZC0_Move_uniDR_5_smoothSeed": -0.2720665929594802, "RS0_ZC0_Move_uniDR_5_zSeed": -0.07314241203214572, "RS0_ZC0_Move_uniDR_5_volSeed": 0.12916779656831034}, "W0": {"W0_midPrice": 638.0, "Volatility_W0": 2.066794934075079, "W0_lastTS": "2023_12_13_11", "W0_symbol": "QWH24", "RB0_midPrice": 1.9923, "Volatility_RB0": 0.014253822663231207, "RB0_symbol": "QRBF24", "RB0_lastTS": "2023_12_13_11", "KE0_midPrice": 640.75, "Volatility_KE0": 4.032002395154834, "KE0_symbol": "@KWH24", "KE0_lastTS": "2023_12_13_11", "ECO0_midPrice": 436.75, "Volatility_ECO0": 2.2637643024638936, "ECO0_symbol": "PGG24", "ECO0_lastTS": "2023_12_13_10", "W0_KE0_Move_uniDR_5_smoothSeed": -0.7184581247091729, "W0_KE0_Move_uniDR_5_zSeed": 0.02415252094050461, "W0_KE0_Move_uniDR_5_volSeed": 0.3156426456799975, "W0_RB0_Move_uniDR_8_smoothSeed": -0.001421697666881367, "W0_RB0_Move_uniDR_8_zSeed": -0.000393050583412025, "W0_RB0_Move_uniDR_8_volSeed": 0.0009119006087675038, "W0_ECO0_Move_uniDR_5_smoothSeed": -0.45006094859364537, "W0_ECO0_Move_uniDR_5_zSeed": -0.036451592867820404, "W0_ECO0_Move_uniDR_5_volSeed": 0.1971773374966079}, "ICE-US_CT0": {"ICE-US_CT0_midPrice": 80.94, "Volatility_ICE-US_CT0": 0.35803911380712783, "ICE-US_CT0_lastTS": "2023_12_13_11", "ICE-US_CT0_symbol": "@CTH24", "ICE-EU_BRN0_midPrice": 73.8, "Volatility_ICE-EU_BRN0": 0.37023289338038967, "ICE-EU_BRN0_symbol": "QBZG24", "ICE-EU_BRN0_lastTS": "2023_12_13_11", "FESB0_midPrice": 118.4, "Volatility_FESB0": 0.4661391830796609, "FESB0_symbol": "SXZ23", "FESB0_lastTS": "2023_12_13_11", "ZT0_midPrice": 102.2265625, "Volatility_ZT0": 0.022105750625335676, "ZT0_symbol": "@TUH24", "ZT0_lastTS": "2023_12_13_11", "CL0_midPrice": 69.39, "Volatility_CL0": 0.3826418064926941, "CL0_symbol": "QCLG24", "CL0_lastTS": "2023_12_13_11", "ZM0_midPrice": 394.1, "Volatility_ZM0": 1.5041917069316937, "ZM0_symbol": "@SMH24", "ZM0_lastTS": "2023_12_13_11", "ZF0_midPrice": 107.2109375, "Volatility_ZF0": 0.06260368796342572, "ZF0_symbol": "@FVH24", "ZF0_lastTS": "2023_12_13_11", "ICE-US_MME0_midPrice": 972.8, "Volatility_ICE-US_MME0": 2.996653556038283, "ICE-US_MME0_symbol": "MEFZ23", "ICE-US_MME0_lastTS": "2023_12_13_08", "ICE-EU_G0_midPrice": 735.5, "Volatility_ICE-EU_G0": 4.024495627742617, "ICE-EU_G0_symbol": "GASF24", "ICE-EU_G0_lastTS": "2023_12_13_11", "ICE-US_CT0_ZF0_Move_uniDR_68_smoothSeed": -0.0006206273787196203, "ICE-US_CT0_ZF0_Move_uniDR_68_zSeed": -8.778957790223801e-05, "ICE-US_CT0_ZF0_Move_uniDR_68_volSeed": 0.0013724659338868114, "ICE-US_CT0_ZM0_Move_uniDR_68_smoothSeed": -0.06107751566229062, "ICE-US_CT0_ZM0_Move_uniDR_68_zSeed": -0.0025084569698770815, "ICE-US_CT0_ZM0_Move_uniDR_68_volSeed": 0.038524855420461794, "ICE-US_CT0_CL0_VSR_uniDR_18_smoothSeed": -0.05397930997740819, "ICE-US_CT0_CL0_VSR_uniDR_18_zSeed": -0.01844018712717764, "ICE-US_CT0_CL0_VSR_uniDR_18_volSeed": 0.04589768678569053, "ICE-US_CT0_ICE-EU_BRN0_VSR_uniDR_18_smoothSeed": -0.026889387370941813, "ICE-US_CT0_ICE-EU_BRN0_VSR_uniDR_18_zSeed": -0.020000305328515662, "ICE-US_CT0_ICE-EU_BRN0_VSR_uniDR_18_volSeed": 0.047122968789770306, "ICE-US_CT0_ICE-EU_G0_VSR_uniDR_18_smoothSeed": -0.009143812766979058, "ICE-US_CT0_ICE-EU_G0_VSR_uniDR_18_zSeed": -0.026374640892464756, "ICE-US_CT0_ICE-EU_G0_VSR_uniDR_18_volSeed": 0.04800586844827244, "ICE-US_CT0_ICE-US_MME0_VSR_uniDR_5_smoothSeed": 0.028474779916282007, "ICE-US_CT0_ICE-US_MME0_VSR_uniDR_5_zSeed": -0.017659680205952585, "ICE-US_CT0_ICE-US_MME0_VSR_uniDR_5_volSeed": 0.09097461152617338, "ICE-US_CT0_FESB0_VSR_uniDR_5_smoothSeed": 0.11181465416866117, "ICE-US_CT0_FESB0_VSR_uniDR_5_zSeed": -0.009225301524421903, "ICE-US_CT0_FESB0_VSR_uniDR_5_volSeed": 0.09296636668831408, "ICE-US_CT0_ZT0_Move_uniDR_68_smoothSeed": -9.112730863877755e-05, "ICE-US_CT0_ZT0_Move_uniDR_68_zSeed": -4.532722990613649e-05, "ICE-US_CT0_ZT0_Move_uniDR_68_volSeed": 0.000523413757771909}, "ICE-EU_G0": {"ICE-EU_G0_midPrice": 735.5, "Volatility_ICE-EU_G0": 3.5801534480852397, "ICE-EU_G0_lastTS": "2023_12_13_11", "ICE-EU_G0_symbol": "GASF24", "W0_midPrice": 638.0, "Volatility_W0": 1.4831737033950487, "W0_symbol": "QWH24", "W0_lastTS": "2023_12_13_11", "ZN0_midPrice": 110.765625, "Volatility_ZN0": 0.0881157784836169, "ZN0_symbol": "@TYH24", "ZN0_lastTS": "2023_12_13_11", "ALSI0_midPrice": 66738.0, "Volatility_ALSI0": 106.66486396758052, "ALSI0_symbol": "ALJZ23", "ALSI0_lastTS": "2023_12_13_10", "ICE-LX_C0_midPrice": 3544.0, "Volatility_ICE-LX_C0": 5.730487913280733, "ICE-LX_C0_symbol": "QCH24", "ICE-LX_C0_lastTS": "2023_12_13_11", "ZL0_midPrice": 50.17, "Volatility_ZL0": 0.18948218197402183, "ZL0_symbol": "@BOF24", "ZL0_lastTS": "2023_12_13_11", "ICE-EU_G0_ALSI0_Move_uniDR_6_smoothSeed": -15.721026466971274, "ICE-EU_G0_ALSI0_Move_uniDR_6_zSeed": -16.03001006386507, "ICE-EU_G0_ALSI0_Move_uniDR_6_volSeed": 7.58318845189983, "ICE-EU_G0_ICE-LX_C0_VSR_uniDR_68_smoothSeed": 0.006229518660372358, "ICE-EU_G0_ICE-LX_C0_VSR_uniDR_68_zSeed": 0.0006752520400905141, "ICE-EU_G0_ICE-LX_C0_VSR_uniDR_68_volSeed": 0.03757258945921963, "ICE-EU_G0_W0_VSR_uniDR_68_smoothSeed": -0.0405551706621244, "ICE-EU_G0_W0_VSR_uniDR_68_zSeed": -0.0030418239793779133, "ICE-EU_G0_W0_VSR_uniDR_68_volSeed": 0.03179108784346936, "ICE-EU_G0_ZN0_VSR_uniDR_35_smoothSeed": 0.08504903778030828, "ICE-EU_G0_ZN0_VSR_uniDR_35_zSeed": 0.0032171709055202773, "ICE-EU_G0_ZN0_VSR_uniDR_35_volSeed": 0.058470887481194445, "ICE-EU_G0_ZL0_Move_uniDR_68_smoothSeed": -0.00238284415303245, "ICE-EU_G0_ZL0_Move_uniDR_68_zSeed": 0.00036918096154624734, "ICE-EU_G0_ZL0_Move_uniDR_68_volSeed": 0.004055103658431327}, "ICE-US_KC0": {"ICE-US_KC0_midPrice": 185.85, "Volatility_ICE-US_KC0": 1.0151137974742321, "ICE-US_KC0_lastTS": "2023_12_13_11", "ICE-US_KC0_symbol": "@KCH24", "RS0_midPrice": 669.6, "Volatility_RS0": 2.6914189511563906, "RS0_symbol": "@RSH24", "RS0_lastTS": "2023_12_13_10", "RS1_midPrice": 669.6, "Volatility_RS1": 2.619293960729294, "RS1_symbol": "@RSH24", "RS1_lastTS": "2023_12_13_10", "NG0_midPrice": 2.334, "Volatility_NG0": 0.043533469992993575, "NG0_symbol": "QNGF24", "NG0_lastTS": "2023_12_13_11", "RB0_midPrice": 1.9923, "Volatility_RB0": 0.014450660356516171, "RB0_symbol": "QRBF24", "RB0_lastTS": "2023_12_13_11", "ICE-US_KC0_RB0_Move_uniDR_35_smoothSeed": -0.0012987265239419274, "ICE-US_KC0_RB0_Move_uniDR_35_zSeed": -6.877207887335044e-05, "ICE-US_KC0_RB0_Move_uniDR_35_volSeed": 0.0004094281838242399, "ICE-US_KC0_NG0_Move_uniDR_35_smoothSeed": -0.0008038731769648127, "ICE-US_KC0_NG0_Move_uniDR_35_zSeed": -1.6238161173691678e-05, "ICE-US_KC0_NG0_Move_uniDR_35_volSeed": 0.0013931711369090873, "ICE-US_KC0_RS1_Basis_uniDR_69_smoothSeed": 163.06897321839682, "ICE-US_KC0_RS1_Basis_uniDR_69_zSeed": 3.547154904053281, "ICE-US_KC0_RS1_Basis_uniDR_69_volSeed": 0.3320380641493132}}, "logs": {"ZN0": ["2023_12_13_11", false, 110.765625, 1, 0.08528470496483775, -0.078125, -0.0011674168529993995, -0.157469905894916, 0, 0, 1, -0.08628147596090235, 2, 110843.75, 1], "ZF0": ["2023_12_13_11", false, 107.2109375, 1, 0.05372146987368349, -0.0703125, 0.0001505793102091641, 0.0, 0, 0, 1, 0.0, 4, 107281.25, 1], "FBTP0": ["2023_12_13_11", false, 117.01, 1, 0.22959977626159656, 0.07000000000000739, 0.0002862360866836668, 0.005225847701929063, 0, 0, 2, 0.009359229930939303, 6, 108271.76, 1.08006], "AP0": ["2023_12_13_10", false, 7285.0, 1, 12.819868974910982, -7.0, 0.788150253878078, 0.004658957858170206, 0, 0, 1, 0.39650705175916645, 2, 332644.0, 0.65764], "ES0": ["2023_12_13_11", false, 4700.5, 1, 6.777873343808145, -7.75, -0.17676022435261907, -0.003777864822020902, 0, 0, 1, -0.13664152278721434, 3, 235412.5, 1], "FSMI0": ["2023_12_13_11", true, 11191.0, 0, 24.676688222935706, 0, -0.041808952779035485, -2.0793468627060082e-05, 0, 0, 1, -0.01125187696269485, 2, 128375.17, 0.8754808514009608], "FTI0": ["2023_12_13_10", true, 792.75, 0, 1.7308876004342826, 0, -0.08924819433691605, -0.02918178063178902, 0, -1, 1, -0.506057064628267, 3, 146473.34, 1.08006], "ALSI0": ["2023_12_13_10", false, 66738.0, 1, 174.8448923129461, -185.0, 7.6004037422996396, 0.00024781652790830966, 0, 4, 4, 0.3485464527543033, 20, 35106.96, 19.062600072693318], "ZC0": ["2023_12_13_11", false, 480.0, 1, 2.084900917410493, -1.0, -0.004192376168579599, 0.0, 0, 0, 3, 0.0, 11, 24050.0, 1], "ZS0": ["2023_12_13_11", false, 1309.5, 1, 4.418756148815769, -5.75, -0.0737633586389439, -0.0025107216148665098, 0, 0, 1, -0.050025336525264696, 2, 65762.5, 1], "ZM0": ["2023_12_13_11", true, 394.1, 0, 1.6433361492976175, 0, -0.011825226159737613, -0.0001242064395122915, 0, 0, 4, -0.00098148890558038, 17, 40360.0, 1], "ZW0": ["2023_12_13_11", false, 614.5, 1, 3.663506078188512, -0.25, -0.018206236419338048, -0.001038797324782004, 0, 0, 3, -0.06187000147599785, 14, 30737.5, 1], "KE0": ["2023_12_13_11", false, 640.75, 1, 3.73303795850996, -6.0, -0.06521453851686898, -0.0028520922841886614, 0, -1, 2, -0.147562721657112, 8, 32337.5, 1], "LE0": ["2023_12_13_11", false, 168.3, 1, 0.443127508210129, -0.27499999999997726, 0.020503886825501045, 0.09194682718601173, 0, 1, 3, 0.12788385212251643, 11, 67320.0, 1], "CL0": ["2023_12_13_11", true, 69.39, 0, 0.31868649795642573, 0, -0.011708258695052043, -0.11503194173649851, 0, 0, 1, -0.3364717185903074, 2, 68910.0, 1], "HO0": ["2023_12_13_11", false, 2.5434, 1, 0.010673917452172572, 0.00649999999999995, -0.00014413556355376582, -0.9508748641055833, 0, 0, 1, -0.17635943334722198, 2, 106549.8, 1], "RS0": ["2023_12_13_10", false, 669.6, 1, 2.300592964070127, -0.39999999999997726, -0.043331204059594466, -0.007428608490961785, 0, -1, 6, -0.05027891065166219, 29, 9884.78, 1.355619721555709], "W0": ["2023_12_13_11", false, 638.0, 1, 2.066794934075079, -6.600000000000023, -0.015960772624569793, -0.001108747737106052, 0, 0, 3, -0.02336665410128666, 15, 32230.0, 1], "ICE-US_CT0": ["2023_12_13_11", false, 80.94, 1, 0.35803911380712783, -0.10000000000000853, -0.0044421822855446975, -0.029823533333333332, -1, 0, 3, -0.06666666666666667, 15, 40520.0, 1], "ICE-EU_G0": ["2023_12_13_11", false, 735.5, 1, 3.5801534480852397, 2.5, -0.11733687702069037, -0.008947992084818881, 0, 0, 1, -0.2236718431400795, 2, 73300.0, 1], "ICE-US_KC0": ["2023_12_13_11", false, 185.85, 1, 1.0151137974742321, -4.200000000000017, -0.026330408837721676, -0.025393717231561412, 0, -2, 2, -0.36894457534087016, 6, 71268.75, 1]}}