{"initSeeds": {"ZN0": {"ZN0_midPrice": 112.34375, "Volatility_ZN0": 0.0891987091092882, "ZN0_lastTS": "2023_12_14_23", "ZN0_symbol": "@TYH24", "CL0_midPrice": 72.27, "Volatility_CL0": 0.31360037041238353, "CL0_symbol": "QCLG24", "CL0_lastTS": "2023_12_14_23", "AUD=_midPrice": 0.6716, "Volatility_AUD=": 0.001060715612808575, "AUD=_symbol": "AUDUSD.COMP", "AUD=_lastTS": "2023_12_14_23", "PL0_midPrice": 966.7, "Volatility_PL0": 3.517472062210483, "PL0_symbol": "QPLF24", "PL0_lastTS": "2023_12_14_23", "ICE-US_CT0_midPrice": 80.98, "Volatility_ICE-US_CT0": 0.2934614972705228, "ICE-US_CT0_symbol": "@CTH24", "ICE-US_CT0_lastTS": "2023_12_14_22", "CAD=_midPrice": 1.3392079923932987, "Volatility_CAD=": 0.0012804805685788581, "CAD=_symbol": "CADUSD.COMP", "CAD=_lastTS": "2023_12_14_23", "ZN0_CL0_Move_uniDR_9_smoothSeed": 0.06878752451149864, "ZN0_CL0_Move_uniDR_9_zSeed": 0.005624048338473253, "ZN0_CL0_Move_uniDR_9_volSeed": 0.017859930249881077, "ZN0_PL0_Move_uniDR_9_smoothSeed": 0.8465020637098339, "ZN0_PL0_Move_uniDR_9_zSeed": 0.30860415350118586, "ZN0_PL0_Move_uniDR_9_volSeed": 0.1804271228922131, "ZN0_AUD=_Move_uniDR_35_smoothSeed": 0.00019493895194225004, "ZN0_AUD=_Move_uniDR_35_zSeed": 1.3452447128995244e-05, "ZN0_AUD=_Move_uniDR_35_volSeed": 2.5912652899209088e-05, "ZN0_CAD=_Move_uniDR_18_smoothSeed": -0.00038754868055461986, "ZN0_CAD=_Move_uniDR_18_zSeed": -4.568754622702068e-05, "ZN0_CAD=_Move_uniDR_18_volSeed": 4.871316631960647e-05, "ZN0_ICE-US_CT0_Move_uniDR_68_smoothSeed": -0.0023967813220397986, "ZN0_ICE-US_CT0_Move_uniDR_68_zSeed": 0.0007810608034702624, "ZN0_ICE-US_CT0_Move_uniDR_68_volSeed": 0.005305158666167278}, "ZF0": {"ZF0_midPrice": 108.3359375, "Volatility_ZF0": 0.05748008379959312, "ZF0_lastTS": "2023_12_14_23", "ZF0_symbol": "@FVH24", "CL0_midPrice": 72.27, "Volatility_CL0": 0.3158119864827697, "CL0_symbol": "QCLG24", "CL0_lastTS": "2023_12_14_23", "HO0_midPrice": 2.6104, "Volatility_HO0": 0.010665383409782134, "HO0_symbol": "QHOF24", "HO0_lastTS": "2023_12_14_22", "PL0_midPrice": 966.7, "Volatility_PL0": 3.44590829929656, "PL0_symbol": "QPLF24", "PL0_lastTS": "2023_12_14_23", "NZD=_midPrice": 0.62173, "Volatility_NZD=": 0.0010008498521182567, "NZD=_symbol": "NZDUSD.COMP", "NZD=_lastTS": "2023_12_14_23", "ZF0_HO0_Move_uniDR_68_smoothSeed": 0.00022701005671438943, "ZF0_HO0_Move_uniDR_68_zSeed": -2.83960269719885e-05, "ZF0_HO0_Move_uniDR_68_volSeed": 0.00027741497988361573, "ZF0_NZD=_Move_uniDR_6_smoothSeed": 0.00020530384532725546, "ZF0_NZD=_Move_uniDR_6_zSeed": 0.0001127954171909437, "ZF0_NZD=_Move_uniDR_6_volSeed": 6.485888920436377e-05, "ZF0_PL0_Move_uniDR_9_smoothSeed": 0.8505785797161132, "ZF0_PL0_Move_uniDR_9_zSeed": 0.31743897852088765, "ZF0_PL0_Move_uniDR_9_volSeed": 0.17852446043722278, "ZF0_CL0_Move_uniDR_6_smoothSeed": 0.06644939980405543, "ZF0_CL0_Move_uniDR_6_zSeed": 0.008020290150069226, "ZF0_CL0_Move_uniDR_6_volSeed": 0.022243506925280036}, "FBTP0": {"FBTP0_midPrice": 118.38, "Volatility_FBTP0": 0.2322025640712194, "FBTP0_lastTS": "2023_12_14_13", "FBTP0_symbol": "BTPH24", "CL0_midPrice": 72.27, "Volatility_CL0": 0.4409407729558185, "CL0_symbol": "QCLG24", "CL0_lastTS": "2023_12_14_23", "EUR=_midPrice": 1.09972, "Volatility_EUR=": 0.0016366711304525174, "EUR=_symbol": "EURUSD.COMP", "EUR=_lastTS": "2023_12_14_23", "FTI0_midPrice": 794.85, "Volatility_FTI0": 1.7844639822381771, "FTI0_symbol": "AEXF24", "FTI0_lastTS": "2023_12_14_16", "ICE-EU_BRN0_midPrice": 77.02, "Volatility_ICE-EU_BRN0": 0.4350350039662795, "ICE-EU_BRN0_symbol": "QBZG24", "ICE-EU_BRN0_lastTS": "2023_12_14_22", "ICE-LL_R0_midPrice": 100.4, "Volatility_ICE-LL_R0": 0.16501986979413033, "ICE-LL_R0_symbol": "LGH24", "ICE-LL_R0_lastTS": "2023_12_14_13", "ICE-EU_G0_midPrice": 757.5, "Volatility_ICE-EU_G0": 5.07262673056315, "ICE-EU_G0_symbol": "GASF24", "ICE-EU_G0_lastTS": "2023_12_14_23", "FBTP0_ICE-LL_R0_Move_uniDR_68_smoothSeed": 0.023206596453688492, "FBTP0_ICE-LL_R0_Move_uniDR_68_zSeed": 0.0006090344996219397, "FBTP0_ICE-LL_R0_Move_uniDR_68_volSeed": 0.003229561671924133, "FBTP0_FTI0_VSR_uniDR_68_smoothSeed": -0.016533765483933212, "FBTP0_FTI0_VSR_uniDR_68_zSeed": 0.0024909758775446683, "FBTP0_FTI0_VSR_uniDR_68_volSeed": 0.027179199726103893, "FBTP0_CL0_VSR_uniDR_68_smoothSeed": -0.05713938447291463, "FBTP0_CL0_VSR_uniDR_68_zSeed": -0.0014527440583158825, "FBTP0_CL0_VSR_uniDR_68_volSeed": 0.0460072667650341, "FBTP0_ICE-EU_G0_VSR_uniDR_35_smoothSeed": -0.13928929251623132, "FBTP0_ICE-EU_G0_VSR_uniDR_35_zSeed": -0.006328745449216822, "FBTP0_ICE-EU_G0_VSR_uniDR_35_volSeed": 0.06328945275679812, "FBTP0_ICE-EU_BRN0_VSR_uniDR_68_smoothSeed": -0.05781850254710015, "FBTP0_ICE-EU_BRN0_VSR_uniDR_68_zSeed": -0.0018157434591143326, "FBTP0_ICE-EU_BRN0_VSR_uniDR_68_volSeed": 0.04991796074677709}, "AP0": {"AP0_midPrice": 7461.0, "Volatility_AP0": 12.91131584136508, "AP0_lastTS": "2023_12_14_22", "AP0_symbol": "SPIZ23", "JPY=_midPrice": 142.06399954766823, "Volatility_JPY=": 0.192633214147824, "JPY=_symbol": "JPYUSD.COMP", "JPY=_lastTS": "2023_12_14_23", "FGBL0_midPrice": 135.9, "Volatility_FGBL0": 0.15526372525023438, "FGBL0_symbol": "BDH24", "FGBL0_lastTS": "2023_12_14_22", "AUD=_midPrice": 0.6716, "Volatility_AUD=": 0.0012832930616866005, "AUD=_symbol": "AUDUSD.COMP", "AUD=_lastTS": "2023_12_14_23", "ZS1_midPrice": 1334.25, "Volatility_ZS1": 3.8048212297247628, "ZS1_symbol": "@SH24", "ZS1_lastTS": "2023_12_14_23", "FBTS0_midPrice": 106.29, "Volatility_FBTS0": 0.053692864689355684, "FBTS0_symbol": "BTSH24", "FBTS0_lastTS": "2023_12_14_13", "ZS0_midPrice": 1317.0, "Volatility_ZS0": 3.9074206603177464, "ZS0_symbol": "@SF24", "ZS0_lastTS": "2023_12_14_23", "ICE-US_KC0_midPrice": 190.2, "Volatility_ICE-US_KC0": 0.7916949794479935, "ICE-US_KC0_symbol": "@KCH24", "ICE-US_KC0_lastTS": "2023_12_14_14", "ICE-LL_R0_midPrice": 100.4, "Volatility_ICE-LL_R0": 0.13084570305384566, "ICE-LL_R0_symbol": "LGH24", "ICE-LL_R0_lastTS": "2023_12_14_13", "NQ0_midPrice": 16767.0, "Volatility_NQ0": 28.527749021680954, "NQ0_symbol": "@NQH24", "NQ0_lastTS": "2023_12_14_23", "AP0_FGBL0_Basis_uniDR_6_smoothSeed": -7294.370256885286, "AP0_FGBL0_Basis_uniDR_6_zSeed": -5231.584292805993, "AP0_FGBL0_Basis_uniDR_6_volSeed": 1144.0303996728658, "AP0_ICE-LL_R0_Move_uniDR_6_smoothSeed": -0.005225429736602397, "AP0_ICE-LL_R0_Move_uniDR_6_zSeed": 0.02064919164207753, "AP0_ICE-LL_R0_Move_uniDR_6_volSeed": 0.009057980622492403, "AP0_JPY=_Move_uniDR_35_smoothSeed": -0.03533546727482033, "AP0_JPY=_Move_uniDR_35_zSeed": -0.0024960823398353323, "AP0_JPY=_Move_uniDR_35_volSeed": 0.005201809952463198, "AP0_ICE-US_KC0_Move_uniDR_17_smoothSeed": 0.060955387407536796, "AP0_ICE-US_KC0_Move_uniDR_17_zSeed": 0.029201667720415676, "AP0_ICE-US_KC0_Move_uniDR_17_volSeed": 0.032125543848603735, "AP0_ZS1_Basis_uniDR_35_smoothSeed": -5495.092753624753, "AP0_ZS1_Basis_uniDR_35_zSeed": -835.4614244018005, "AP0_ZS1_Basis_uniDR_35_volSeed": 145.33141359534463, "AP0_NQ0_VSR_uniDR_35_smoothSeed": -0.0970004733999126, "AP0_NQ0_VSR_uniDR_35_zSeed": 0.01072689325326309, "AP0_NQ0_VSR_uniDR_35_volSeed": 0.02835252395794822, "AP0_FBTS0_Move_uniDR_6_smoothSeed": 0.00454526050868901, "AP0_FBTS0_Move_uniDR_6_zSeed": 0.003543837164332417, "AP0_FBTS0_Move_uniDR_6_volSeed": 0.0030740757175322813}, "ES0": {"ES0_midPrice": 4774.5, "Volatility_ES0": 6.876424111917355, "ES0_lastTS": "2023_12_14_23", "ES0_symbol": "@ESH24", "FCE0_midPrice": 7575.3, "Volatility_FCE0": 12.987504804979267, "FCE0_symbol": "MTZ23", "FCE0_lastTS": "2023_12_14_16", "FDAX0_midPrice": 16759.0, "Volatility_FDAX0": 29.04569729618783, "FDAX0_symbol": "DXMZ23", "FDAX0_lastTS": "2023_12_14_22", "FESX0_midPrice": 4551.0, "Volatility_FESX0": 8.34312937936285, "FESX0_symbol": "EXZ23", "FESX0_lastTS": "2023_12_14_23", "FTI0_midPrice": 794.85, "Volatility_FTI0": 1.2921655373539462, "FTI0_symbol": "AEXF24", "FTI0_lastTS": "2023_12_14_16", "ICE-LL_R0_midPrice": 100.4, "Volatility_ICE-LL_R0": 0.1205973609698769, "ICE-LL_R0_symbol": "LGH24", "ICE-LL_R0_lastTS": "2023_12_14_13", "ES0_FTI0_VSR_uniDR_5_smoothSeed": -0.08215269984820475, "ES0_FTI0_VSR_uniDR_5_zSeed": -0.10190024481445858, "ES0_FTI0_VSR_uniDR_5_volSeed": 0.051863861391488776, "ES0_FCE0_VSR_uniDR_5_smoothSeed": -0.11600683517918622, "ES0_FCE0_VSR_uniDR_5_zSeed": -0.11800113075798013, "ES0_FCE0_VSR_uniDR_5_volSeed": 0.056068643801851635, "ES0_FDAX0_VSR_uniDR_5_smoothSeed": -0.19873256239796697, "ES0_FDAX0_VSR_uniDR_5_zSeed": -0.1647363773508874, "ES0_FDAX0_VSR_uniDR_5_volSeed": 0.058686241193977, "ES0_ICE-LL_R0_Move_uniDR_68_smoothSeed": 0.018071980071278033, "ES0_ICE-LL_R0_Move_uniDR_68_zSeed": 0.0010966765418766603, "ES0_ICE-LL_R0_Move_uniDR_68_volSeed": 0.0021914351804385654, "ES0_FESX0_VSR_uniDR_5_smoothSeed": -0.06509488697361743, "ES0_FESX0_VSR_uniDR_5_zSeed": -0.13976093240142248, "ES0_FESX0_VSR_uniDR_5_volSeed": 0.05425985296155973}, "FSMI0": {"FSMI0_midPrice": 11174.0, "Volatility_FSMI0": 24.721489430595415, "FSMI0_lastTS": "2023_12_14_16", "FSMI0_symbol": "SWH24", "FBTS0_midPrice": 106.29, "Volatility_FBTS0": 0.051751764056229776, "FBTS0_symbol": "BTSH24", "FBTS0_lastTS": "2023_12_14_13", "NG0_midPrice": 2.434, "Volatility_NG0": 0.03574963271727295, "NG0_symbol": "QNGF24", "NG0_lastTS": "2023_12_14_23", "CHF=_midPrice": 0.8666360530947455, "Volatility_CHF=": 0.001472082392712978, "CHF=_symbol": "CHFUSD.COMP", "CHF=_lastTS": "2023_12_14_23", "FSMI0_FBTS0_Move_uniDR_6_smoothSeed": 0.010036316065420714, "FSMI0_FBTS0_Move_uniDR_6_zSeed": 0.0026189981514141837, "FSMI0_FBTS0_Move_uniDR_6_volSeed": 0.003163102467863559, "FSMI0_NG0_Move_uniDR_6_smoothSeed": 0.003026429682949034, "FSMI0_NG0_Move_uniDR_6_zSeed": -0.0007265245480454263, "FSMI0_NG0_Move_uniDR_6_volSeed": 0.002625344702016013}, "FTI0": {"FTI0_midPrice": 794.85, "Volatility_FTI0": 1.7370550080288514, "FTI0_lastTS": "2023_12_14_16", "FTI0_symbol": "AEXF24", "FBTS0_midPrice": 106.29, "Volatility_FBTS0": 0.058883896324364485, "FBTS0_symbol": "BTSH24", "FBTS0_lastTS": "2023_12_14_13", "HE0_midPrice": 70.475, "Volatility_HE0": 0.34410956910162666, "HE0_symbol": "@HEG24", "HE0_lastTS": "2023_12_14_15", "EUR=_midPrice": 1.09972, "Volatility_EUR=": 0.001568050556462079, "EUR=_symbol": "EURUSD.COMP", "EUR=_lastTS": "2023_12_14_23", "HE1_midPrice": 77.125, "Volatility_HE1": 0.400429033404327, "HE1_symbol": "@HEJ24", "HE1_lastTS": "2023_12_14_15", "NG0_midPrice": 2.434, "Volatility_NG0": 0.037419061410518394, "NG0_symbol": "QNGF24", "NG0_lastTS": "2023_12_14_23", "ICE-US_KC0_midPrice": 190.2, "Volatility_ICE-US_KC0": 0.8762455047240485, "ICE-US_KC0_symbol": "@KCH24", "ICE-US_KC0_lastTS": "2023_12_14_14", "FTI0_FBTS0_Move_uniDR_5_smoothSeed": 0.006934239201436229, "FTI0_FBTS0_Move_uniDR_5_zSeed": 0.0038299771947216143, "FTI0_FBTS0_Move_uniDR_5_volSeed": 0.0036407746504497794, "FTI0_ICE-US_KC0_Move_uniDR_9_smoothSeed": 0.086852638853322, "FTI0_ICE-US_KC0_Move_uniDR_9_zSeed": 0.056241958785453974, "FTI0_ICE-US_KC0_Move_uniDR_9_volSeed": 0.05054535358857477, "FTI0_HE1_Basis_uniDR_69_smoothSeed": -380.13370579114917, "FTI0_HE1_Basis_uniDR_69_zSeed": -15.918741986570677, "FTI0_HE1_Basis_uniDR_69_volSeed": 2.0311485948593635, "FTI0_NG0_Move_uniDR_35_smoothSeed": 0.0010552575430737671, "FTI0_NG0_Move_uniDR_35_zSeed": 2.836104955933172e-05, "FTI0_NG0_Move_uniDR_35_volSeed": 0.0011869997551392575}, "ALSI0": {"ALSI0_midPrice": 68926.0, "Volatility_ALSI0": 179.7271496362817, "ALSI0_lastTS": "2023_12_14_11", "ALSI0_symbol": "ALJZ23", "GC1_midPrice": 2040.2, "Volatility_GC1": 3.8201682417123717, "GC1_symbol": "QGCF24", "GC1_lastTS": "2023_12_14_22", "AUD=_midPrice": 0.6716, "Volatility_AUD=": 0.001696337312967416, "AUD=_symbol": "AUDUSD.COMP", "AUD=_lastTS": "2023_12_14_23", "ZAR=_midPrice": 18.33939997627982, "Volatility_ZAR=": 0.04903666116977198, "ZAR=_symbol": "ZARUSD.COMP", "ZAR=_lastTS": "2023_12_14_23", "GC0_midPrice": 2049.7, "Volatility_GC0": 3.8047118301012106, "GC0_symbol": "QGCG24", "GC0_lastTS": "2023_12_14_23", "ES0_midPrice": 4774.5, "Volatility_ES0": 8.464740663380452, "ES0_symbol": "@ESH24", "ES0_lastTS": "2023_12_14_23", "ZF0_midPrice": 108.3359375, "Volatility_ZF0": 0.07476304080100486, "ZF0_symbol": "@FVH24", "ZF0_lastTS": "2023_12_14_23", "ZN0_midPrice": 112.34375, "Volatility_ZN0": 0.12158668989610925, "ZN0_symbol": "@TYH24", "ZN0_lastTS": "2023_12_14_23", "NQ0_midPrice": 16767.0, "Volatility_NQ0": 30.690350392260385, "NQ0_symbol": "@NQH24", "NQ0_lastTS": "2023_12_14_23", "ALSI0_ZF0_Move_uniDR_18_smoothSeed": 0.0008215293547266596, "ALSI0_ZF0_Move_uniDR_18_zSeed": -0.0010742039209423577, "ALSI0_ZF0_Move_uniDR_18_volSeed": 0.0029437419290552023, "ALSI0_GC1_Basis_uniDR_8_smoothSeed": -65299.83817373957, "ALSI0_GC1_Basis_uniDR_8_zSeed": -19481.10085939691, "ALSI0_GC1_Basis_uniDR_8_volSeed": 2409.6656998148437, "ALSI0_ES0_Move_uniDR_18_smoothSeed": 0.6511524148058685, "ALSI0_ES0_Move_uniDR_18_zSeed": 0.1517587266343111, "ALSI0_ES0_Move_uniDR_18_volSeed": 0.3111645500513292, "ALSI0_NQ0_Move_uniDR_18_smoothSeed": 2.0058348793865264, "ALSI0_NQ0_Move_uniDR_18_zSeed": 0.9515548966897203, "ALSI0_NQ0_Move_uniDR_18_volSeed": 1.061433798648693, "ALSI0_AUD=_VSR_uniDR_69_smoothSeed": -0.03448362493050176, "ALSI0_AUD=_VSR_uniDR_69_zSeed": 0.0022930335720530762, "ALSI0_AUD=_VSR_uniDR_69_volSeed": 0.018440881213063785, "ALSI0_ZN0_Move_uniDR_18_smoothSeed": 0.005014795437285887, "ALSI0_ZN0_Move_uniDR_18_zSeed": -0.0016262664761747376, "ALSI0_ZN0_Move_uniDR_18_volSeed": 0.004766283766220523}, "ZC0": {"ZC0_midPrice": 479.75, "Volatility_ZC0": 2.0718330308998323, "ZC0_lastTS": "2023_12_14_23", "ZC0_symbol": "@CH24", "ZC1_midPrice": 479.75, "Volatility_ZC1": 1.7985508302195439, "ZC1_symbol": "@CH24", "ZC1_lastTS": "2023_12_14_23", "RB0_midPrice": 2.1288, "Volatility_RB0": 0.010387795778322018, "RB0_symbol": "QRBF24", "RB0_lastTS": "2023_12_14_23", "CNH=_midPrice": 7.12331001695882, "Volatility_CNH=": 0.004440063660811152, "CNH=_symbol": "CNHUSD.COMP", "CNH=_lastTS": "2023_12_14_23", "ZC0_ZC1_Basis_uniDR_6_smoothSeed": 0.002897309173884323, "ZC0_ZC1_Basis_uniDR_6_zSeed": -0.00029662946707565406, "ZC0_ZC1_Basis_uniDR_6_volSeed": 0.04897189240245728, "ZC0_CNH=_Move_uniDR_68_smoothSeed": -0.00024666384173448045, "ZC0_CNH=_Move_uniDR_68_zSeed": 1.5807625575927359e-06, "ZC0_CNH=_Move_uniDR_68_volSeed": 0.00010890942847789487, "ZC0_RB0_Move_uniDR_38_smoothSeed": 0.0007285548259451598, "ZC0_RB0_Move_uniDR_38_zSeed": -2.7288477725051545e-05, "ZC0_RB0_Move_uniDR_38_volSeed": 0.0002890325577053453}, "ZS0": {"ZS0_midPrice": 1317.0, "Volatility_ZS0": 4.405760983498176, "ZS0_lastTS": "2023_12_14_23", "ZS0_symbol": "@SF24", "IND0_midPrice": 132900.0, "Volatility_IND0": 288.58556198074336, "IND0_symbol": "INDG24", "IND0_lastTS": "2023_12_14_17", "ZS1_midPrice": 1334.25, "Volatility_ZS1": 3.914312645511378, "ZS1_symbol": "@SH24", "ZS1_lastTS": "2023_12_14_23", "XT0_midPrice": 95.872, "Volatility_XT0": 0.012452794076894135, "XT0_symbol": "XTZ23", "XT0_lastTS": "2023_12_14_20", "PA0_midPrice": 1103.5, "Volatility_PA0": 9.23453608332284, "PA0_symbol": "QPAH24", "PA0_lastTS": "2023_12_14_22", "NQ0_midPrice": 16767.0, "Volatility_NQ0": 28.04285704641417, "NQ0_symbol": "@NQH24", "NQ0_lastTS": "2023_12_14_23", "ZS0_PA0_VSR_uniDR_68_smoothSeed": 0.07456671155396917, "ZS0_PA0_VSR_uniDR_68_zSeed": -0.0004367278614494719, "ZS0_PA0_VSR_uniDR_68_volSeed": 0.027422581460677237, "ZS0_IND0_Move_uniDR_9_smoothSeed": -26.745441638646366, "ZS0_IND0_Move_uniDR_9_zSeed": -4.871563507462191, "ZS0_IND0_Move_uniDR_9_volSeed": 16.5188065973946, "ZS0_NQ0_VSR_uniDR_68_smoothSeed": 0.03774397102361458, "ZS0_NQ0_VSR_uniDR_68_zSeed": 0.006073172412187971, "ZS0_NQ0_VSR_uniDR_68_volSeed": 0.028609469851637884, "ZS0_ZS1_Basis_uniDR_6_smoothSeed": 0.0666254064104449, "ZS0_ZS1_Basis_uniDR_6_zSeed": -0.01843253417972142, "ZS0_ZS1_Basis_uniDR_6_volSeed": 0.06471852565575645, "ZS0_XT0_VSR_uniDR_68_smoothSeed": 0.010438604654128951, "ZS0_XT0_VSR_uniDR_68_zSeed": -0.0005750898916867734, "ZS0_XT0_VSR_uniDR_68_volSeed": 0.0341080187951758}, "ZM0": {"ZM0_midPrice": 395.2, "Volatility_ZM0": 1.652687111082631, "ZM0_lastTS": "2023_12_14_23", "ZM0_symbol": "@SMH24", "YM0_midPrice": 37281.0, "Volatility_YM0": 66.3317905091831, "YM0_symbol": "@YMZ23", "YM0_lastTS": "2023_12_14_22", "FCE0_midPrice": 7575.3, "Volatility_FCE0": 14.038719265978461, "FCE0_symbol": "MTZ23", "FCE0_lastTS": "2023_12_14_16", "ICE-US_SB0_midPrice": 21.84, "Volatility_ICE-US_SB0": 0.06965275345772756, "ICE-US_SB0_symbol": "@SBH24", "ICE-US_SB0_lastTS": "2023_12_14_13", "FSMI0_midPrice": 11174.0, "Volatility_FSMI0": 20.999746551873887, "FSMI0_symbol": "SWH24", "FSMI0_lastTS": "2023_12_14_16", "FESX0_midPrice": 4551.0, "Volatility_FESX0": 9.109240512724021, "FESX0_symbol": "EXZ23", "FESX0_lastTS": "2023_12_14_23", "HG0_midPrice": 3.8905, "Volatility_HG0": 0.01019840999130512, "HG0_symbol": "QHGH24", "HG0_lastTS": "2023_12_14_23", "CNH=_midPrice": 7.12331001695882, "Volatility_CNH=": 0.004386338974392312, "CNH=_symbol": "CNHUSD.COMP", "CNH=_lastTS": "2023_12_14_23", "FTI0_midPrice": 794.85, "Volatility_FTI0": 1.402368879478022, "FTI0_symbol": "AEXF24", "FTI0_lastTS": "2023_12_14_16", "ZM0_HG0_VSR_uniDR_18_smoothSeed": 0.06567202651496204, "ZM0_HG0_VSR_uniDR_18_zSeed": 0.013266000295773506, "ZM0_HG0_VSR_uniDR_18_volSeed": 0.05376637275270564, "ZM0_FESX0_VSR_uniDR_68_smoothSeed": 0.02542882340208122, "ZM0_FESX0_VSR_uniDR_68_zSeed": 0.004806998832050915, "ZM0_FESX0_VSR_uniDR_68_volSeed": 0.027078611867034537, "ZM0_FSMI0_VSR_uniDR_68_smoothSeed": 0.025879851148972035, "ZM0_FSMI0_VSR_uniDR_68_zSeed": 0.0032189322189122853, "ZM0_FSMI0_VSR_uniDR_68_volSeed": 0.027192980456503407, "ZM0_FCE0_VSR_uniDR_68_smoothSeed": -0.003301623930382973, "ZM0_FCE0_VSR_uniDR_68_zSeed": 0.004998360066747684, "ZM0_FCE0_VSR_uniDR_68_volSeed": 0.026008526256439245, "ZM0_ICE-US_SB0_VSR_uniDR_68_smoothSeed": -0.11648463914309146, "ZM0_ICE-US_SB0_VSR_uniDR_68_zSeed": -0.010183287008843606, "ZM0_ICE-US_SB0_VSR_uniDR_68_volSeed": 0.03007890041334662, "ZM0_FTI0_VSR_uniDR_35_smoothSeed": -0.005150014866895864, "ZM0_FTI0_VSR_uniDR_35_zSeed": 0.013727414869003272, "ZM0_FTI0_VSR_uniDR_35_volSeed": 0.03931322859109912, "ZM0_YM0_VSR_uniDR_18_smoothSeed": 0.017540532356569286, "ZM0_YM0_VSR_uniDR_18_zSeed": 0.029626660961092864, "ZM0_YM0_VSR_uniDR_18_volSeed": 0.05456145546516257, "ZM0_CNH=_VSR_uniDR_68_smoothSeed": -0.04738909076693293, "ZM0_CNH=_VSR_uniDR_68_zSeed": 0.0014572950023087707, "ZM0_CNH=_VSR_uniDR_68_volSeed": 0.03614504505650737}, "ZW0": {"ZW0_midPrice": 620.5, "Volatility_ZW0": 3.645878049253468, "ZW0_lastTS": "2023_12_14_22", "ZW0_symbol": "@WH24", "HE0_midPrice": 70.475, "Volatility_HE0": 0.29298043887277125, "HE0_symbol": "@HEG24", "HE0_lastTS": "2023_12_14_15", "ICE-LL_Z0_midPrice": 7595.0, "Volatility_ICE-LL_Z0": 9.92767701910658, "ICE-LL_Z0_symbol": "TUKZ23", "ICE-LL_Z0_lastTS": "2023_12_12_05", "ICE-LX_C0_midPrice": 3561.0, "Volatility_ICE-LX_C0": 5.833314831378905, "ICE-LX_C0_symbol": "QCH24", "ICE-LX_C0_lastTS": "2023_12_14_12", "ZW0_ICE-LL_Z0_Move_uniDR_35_smoothSeed": 0.41921897114299567, "ZW0_ICE-LL_Z0_Move_uniDR_35_zSeed": 0.09355403209317822, "ZW0_ICE-LL_Z0_Move_uniDR_35_volSeed": 0.2959787617192872, "ZW0_ICE-LX_C0_Move_uniDR_5_smoothSeed": 0.5921079070783183, "ZW0_ICE-LX_C0_Move_uniDR_5_zSeed": 0.6549880716898473, "ZW0_ICE-LX_C0_Move_uniDR_5_volSeed": 0.4932526377947359, "ZW0_HE0_VSR_uniDR_68_smoothSeed": 0.0738045346403028, "ZW0_HE0_VSR_uniDR_68_zSeed": 0.000886190263461577, "ZW0_HE0_VSR_uniDR_68_volSeed": 0.030025984169357662}, "KE0": {"KE0_midPrice": 639.5, "Volatility_KE0": 3.7134816873486987, "KE0_lastTS": "2023_12_14_22", "KE0_symbol": "@KWH24", "W0_midPrice": 624.7, "Volatility_W0": 1.530137741103915, "W0_symbol": "QWH24", "W0_lastTS": "2023_12_14_13", "ICE-LX_C0_midPrice": 3561.0, "Volatility_ICE-LX_C0": 5.826637631512566, "ICE-LX_C0_symbol": "QCH24", "ICE-LX_C0_lastTS": "2023_12_14_12", "ZAR=_midPrice": 18.33939997627982, "Volatility_ZAR=": 0.03375385242776387, "ZAR=_symbol": "ZARUSD.COMP", "ZAR=_lastTS": "2023_12_14_23", "KE0_ZAR=_Move_uniDR_38_smoothSeed": -0.004777485964136375, "KE0_ZAR=_Move_uniDR_38_zSeed": 0.00012814692459497138, "KE0_ZAR=_Move_uniDR_38_volSeed": 0.0008615977556328309, "KE0_ICE-LX_C0_Move_uniDR_18_smoothSeed": 0.37938483330344325, "KE0_ICE-LX_C0_Move_uniDR_18_zSeed": 0.26947227084573305, "KE0_ICE-LX_C0_Move_uniDR_18_volSeed": 0.24901692962131985, "KE0_W0_Move_uniDR_5_smoothSeed": 0.053928623762511944, "KE0_W0_Move_uniDR_5_zSeed": -0.1925826324373512, "KE0_W0_Move_uniDR_5_volSeed": 0.11274340793056972}, "LE0": {"LE0_midPrice": 167.925, "Volatility_LE0": 0.44250743874012693, "LE0_lastTS": "2023_12_14_15", "LE0_symbol": "@LEG24", "VX0_midPrice": 12.4, "Volatility_VX0": 0.35325045395453697, "VX0_symbol": "@VXZ23", "VX0_lastTS": "2023_12_14_22", "FCE0_midPrice": 7575.3, "Volatility_FCE0": 19.174765321076194, "FCE0_symbol": "MTZ23", "FCE0_lastTS": "2023_12_14_16", "KE0_midPrice": 639.5, "Volatility_KE0": 4.592242122598504, "KE0_symbol": "@KWH24", "KE0_lastTS": "2023_12_14_22", "FESX0_midPrice": 4551.0, "Volatility_FESX0": 13.469632978760705, "FESX0_symbol": "EXZ23", "FESX0_lastTS": "2023_12_14_23", "EUR=_midPrice": 1.09972, "Volatility_EUR=": 0.0019854643651872404, "EUR=_symbol": "EURUSD.COMP", "EUR=_lastTS": "2023_12_14_23", "ICE-US_CC0_midPrice": 4278.0, "Volatility_ICE-US_CC0": 15.409546210229063, "ICE-US_CC0_symbol": "@CCH24", "ICE-US_CC0_lastTS": "2023_12_14_14", "LE0_FCE0_Move_uniDR_5_smoothSeed": -7.489682692478791, "LE0_FCE0_Move_uniDR_5_zSeed": 0.07148185215911525, "LE0_FCE0_Move_uniDR_5_volSeed": 1.3450070685831912, "LE0_VX0_VSR_uniDR_5_smoothSeed": -0.044080095849952414, "LE0_VX0_VSR_uniDR_5_zSeed": -0.1360490513821765, "LE0_VX0_VSR_uniDR_5_volSeed": 0.13177192113842692, "LE0_ICE-US_CC0_VSR_uniDR_5_smoothSeed": -0.0921606297568673, "LE0_ICE-US_CC0_VSR_uniDR_5_zSeed": 0.04829744404230674, "LE0_ICE-US_CC0_VSR_uniDR_5_volSeed": 0.11856027194097561, "LE0_EUR=_VSR_uniDR_79_smoothSeed": -0.0349716781429493, "LE0_EUR=_VSR_uniDR_79_zSeed": -0.0010371512627571778, "LE0_EUR=_VSR_uniDR_79_volSeed": 0.04598835239096121, "LE0_FESX0_Move_uniDR_5_smoothSeed": -2.9976301255241364, "LE0_FESX0_Move_uniDR_5_zSeed": 0.20379732426960495, "LE0_FESX0_Move_uniDR_5_volSeed": 0.9729157333619769, "LE0_KE0_VSR_uniDR_79_smoothSeed": -0.09867071154465376, "LE0_KE0_VSR_uniDR_79_zSeed": -0.0015548804887282241, "LE0_KE0_VSR_uniDR_79_volSeed": 0.035973745049026895}, "CL0": {"CL0_midPrice": 72.27, "Volatility_CL0": 0.3171029967596029, "CL0_lastTS": "2023_12_14_23", "CL0_symbol": "QCLG24", "ALSI0_midPrice": 68926.0, "Volatility_ALSI0": 111.51555522976969, "ALSI0_symbol": "ALJZ23", "ALSI0_lastTS": "2023_12_14_11", "THB=_midPrice": 34.85400059969793, "Volatility_THB=": 0.04468094109884401, "THB=_symbol": "THBUSD.COMP", "THB=_lastTS": "2023_12_14_23", "ZF0_midPrice": 108.3359375, "Volatility_ZF0": 0.05766749645789439, "ZF0_symbol": "@FVH24", "ZF0_lastTS": "2023_12_14_23", "SGD=_midPrice": 1.328420000153778, "Volatility_SGD=": 0.0009118300221891999, "SGD=_symbol": "SGDUSD.COMP", "SGD=_lastTS": "2023_12_14_23", "CL0_ZF0_VSR_uniDR_68_smoothSeed": 0.08831501383622863, "CL0_ZF0_VSR_uniDR_68_zSeed": 0.001767397262395668, "CL0_ZF0_VSR_uniDR_68_volSeed": 0.04164055682513209, "CL0_THB=_Move_uniDR_35_smoothSeed": -0.015729245225577546, "CL0_THB=_Move_uniDR_35_zSeed": -0.0004908678033963523, "CL0_THB=_Move_uniDR_35_volSeed": 0.0008474352872661225, "CL0_ALSI0_Move_uniDR_6_smoothSeed": 28.69644277050074, "CL0_ALSI0_Move_uniDR_6_zSeed": 8.115817331603164, "CL0_ALSI0_Move_uniDR_6_volSeed": 7.557484199049323, "CL0_SGD=_Move_uniDR_68_smoothSeed": -0.00012752308283811489, "CL0_SGD=_Move_uniDR_68_zSeed": -4.294146083601813e-06, "CL0_SGD=_Move_uniDR_68_volSeed": 1.7061010333805383e-05}, "HO0": {"HO0_midPrice": 2.6104, "Volatility_HO0": 0.01066749479327435, "HO0_lastTS": "2023_12_14_22", "HO0_symbol": "QHOF24", "ALSI0_midPrice": 68926.0, "Volatility_ALSI0": 108.91529433529819, "ALSI0_symbol": "ALJZ23", "ALSI0_lastTS": "2023_12_14_11", "ICE-US_CC0_midPrice": 4278.0, "Volatility_ICE-US_CC0": 9.598826189083486, "ICE-US_CC0_symbol": "@CCH24", "ICE-US_CC0_lastTS": "2023_12_14_14", "W0_midPrice": 624.7, "Volatility_W0": 1.4550504790614815, "W0_symbol": "QWH24", "W0_lastTS": "2023_12_14_13", "HO0_ICE-US_CC0_VSR_uniDR_68_smoothSeed": 0.09239815486134044, "HO0_ICE-US_CC0_VSR_uniDR_68_zSeed": 0.015910799363372394, "HO0_ICE-US_CC0_VSR_uniDR_68_volSeed": 0.029979359255615887, "HO0_W0_VSR_uniDR_68_smoothSeed": -0.12050929432805692, "HO0_W0_VSR_uniDR_68_zSeed": -0.003813024995991356, "HO0_W0_VSR_uniDR_68_volSeed": 0.02969401860885709, "HO0_ALSI0_Move_uniDR_8_smoothSeed": 41.43317727007645, "HO0_ALSI0_Move_uniDR_8_zSeed": 4.681859791391209, "HO0_ALSI0_Move_uniDR_8_volSeed": 6.061038820996225}, "RS0": {"RS0_midPrice": 666.9, "Volatility_RS0": 2.294892554437228, "RS0_lastTS": "2023_12_14_22", "RS0_symbol": "@RSH24", "CONF0_midPrice": 150.77, "Volatility_CONF0": 0.14875951073390634, "CONF0_symbol": "COH24", "CONF0_lastTS": "2023_12_14_10", "KE0_midPrice": 639.5, "Volatility_KE0": 3.22648282150805, "KE0_symbol": "@KWH24", "KE0_lastTS": "2023_12_14_22", "AUD=_midPrice": 0.6716, "Volatility_AUD=": 0.0013315633271177155, "AUD=_symbol": "AUDUSD.COMP", "AUD=_lastTS": "2023_12_14_23", "ZC0_midPrice": 479.75, "Volatility_ZC0": 1.733191472139017, "ZC0_symbol": "@CH24", "ZC0_lastTS": "2023_12_14_23", "HG0_midPrice": 3.8905, "Volatility_HG0": 0.011577369347801233, "HG0_symbol": "QHGH24", "HG0_lastTS": "2023_12_14_23", "CNH=_midPrice": 7.12331001695882, "Volatility_CNH=": 0.005316986078291858, "CNH=_symbol": "CNHUSD.COMP", "CNH=_lastTS": "2023_12_14_23", "CAD=_midPrice": 1.3392079923932987, "Volatility_CAD=": 0.001620272728857721, "CAD=_symbol": "CADUSD.COMP", "CAD=_lastTS": "2023_12_14_23", "ZW0_midPrice": 620.5, "Volatility_ZW0": 3.229852432963862, "ZW0_symbol": "@WH24", "ZW0_lastTS": "2023_12_14_22", "RS0_ZW0_Move_uniDR_5_smoothSeed": 0.17740191871290295, "RS0_ZW0_Move_uniDR_5_zSeed": -0.2246791066418915, "RS0_ZW0_Move_uniDR_5_volSeed": 0.2534942967086451, "RS0_AUD=_Move_uniDR_68_smoothSeed": 5.629146978402034e-05, "RS0_AUD=_Move_uniDR_68_zSeed": -2.1023742995037293e-07, "RS0_AUD=_Move_uniDR_68_volSeed": 2.3520979215181964e-05, "RS0_CNH=_VSR_uniDR_68_smoothSeed": -0.049547669910168776, "RS0_CNH=_VSR_uniDR_68_zSeed": 0.0004953834085088029, "RS0_CNH=_VSR_uniDR_68_volSeed": 0.04232517186270761, "RS0_KE0_Move_uniDR_5_smoothSeed": -0.13537452122505367, "RS0_KE0_Move_uniDR_5_zSeed": -0.22691220877264476, "RS0_KE0_Move_uniDR_5_volSeed": 0.2425137395397171, "RS0_HG0_Move_uniDR_68_smoothSeed": 0.0008113576422519961, "RS0_HG0_Move_uniDR_68_zSeed": 3.769784187881683e-05, "RS0_HG0_Move_uniDR_68_volSeed": 0.00021140042857509858, "RS0_CONF0_VSR_uniDR_17_smoothSeed": 0.11940094685615465, "RS0_CONF0_VSR_uniDR_17_zSeed": -0.004538179115598085, "RS0_CONF0_VSR_uniDR_17_volSeed": 0.06378412800462839, "RS0_ZC0_Move_uniDR_5_smoothSeed": -0.21803235978662738, "RS0_ZC0_Move_uniDR_5_zSeed": -0.08724747045202533, "RS0_ZC0_Move_uniDR_5_volSeed": 0.12819504195807802}, "W0": {"W0_midPrice": 624.7, "Volatility_W0": 2.102546761515223, "W0_lastTS": "2023_12_14_13", "W0_symbol": "QWH24", "ECO0_midPrice": 430.0, "Volatility_ECO0": 2.2550006853344944, "ECO0_symbol": "PGG24", "ECO0_lastTS": "2023_12_14_13", "RB0_midPrice": 2.1288, "Volatility_RB0": 0.014239432776968864, "RB0_symbol": "QRBF24", "RB0_lastTS": "2023_12_14_23", "KE0_midPrice": 639.5, "Volatility_KE0": 4.017100529504712, "KE0_symbol": "@KWH24", "KE0_lastTS": "2023_12_14_22", "W0_KE0_Move_uniDR_5_smoothSeed": -0.43019055099683134, "W0_KE0_Move_uniDR_5_zSeed": -0.10559871806111103, "W0_KE0_Move_uniDR_5_volSeed": 0.3140538758931877, "W0_RB0_Move_uniDR_8_smoothSeed": 0.004379679181595326, "W0_RB0_Move_uniDR_8_zSeed": -8.551160977470518e-05, "W0_RB0_Move_uniDR_8_volSeed": 0.0009075248552029717, "W0_ECO0_Move_uniDR_5_smoothSeed": -0.7371909329851579, "W0_ECO0_Move_uniDR_5_zSeed": -0.10284015695859099, "W0_ECO0_Move_uniDR_5_volSeed": 0.1962903671229377}, "ICE-US_CT0": {"ICE-US_CT0_midPrice": 80.98, "Volatility_ICE-US_CT0": 0.35664000418547614, "ICE-US_CT0_lastTS": "2023_12_14_22", "ICE-US_CT0_symbol": "@CTH24", "CL0_midPrice": 72.27, "Volatility_CL0": 0.3811259418214569, "CL0_symbol": "QCLG24", "CL0_lastTS": "2023_12_14_23", "ZT0_midPrice": 102.75390625, "Volatility_ZT0": 0.02350326966481593, "ZT0_symbol": "@TUH24", "ZT0_lastTS": "2023_12_14_23", "ZM0_midPrice": 395.2, "Volatility_ZM0": 1.5122718366870993, "ZM0_symbol": "@SMH24", "ZM0_lastTS": "2023_12_14_23", "FESB0_midPrice": 118.75, "Volatility_FESB0": 0.4635380815078633, "FESB0_symbol": "SXZ23", "FESB0_lastTS": "2023_12_14_16", "ZF0_midPrice": 108.3359375, "Volatility_ZF0": 0.06426017091941243, "ZF0_symbol": "@FVH24", "ZF0_lastTS": "2023_12_14_23", "ICE-US_MME0_midPrice": 999.7, "Volatility_ICE-US_MME0": 3.030331573258928, "ICE-US_MME0_symbol": "MEFZ23", "ICE-US_MME0_lastTS": "2023_12_14_12", "ICE-EU_BRN0_midPrice": 77.02, "Volatility_ICE-EU_BRN0": 0.3688030396098951, "ICE-EU_BRN0_symbol": "QBZG24", "ICE-EU_BRN0_lastTS": "2023_12_14_22", "ICE-EU_G0_midPrice": 757.5, "Volatility_ICE-EU_G0": 4.00968115377062, "ICE-EU_G0_symbol": "GASF24", "ICE-EU_G0_lastTS": "2023_12_14_23", "ICE-US_CT0_ZF0_Move_uniDR_68_smoothSeed": 0.0015450736986451995, "ICE-US_CT0_ZF0_Move_uniDR_68_zSeed": -3.1256192337855875e-05, "ICE-US_CT0_ZF0_Move_uniDR_68_volSeed": 0.0013593437141271021, "ICE-US_CT0_ZM0_Move_uniDR_68_smoothSeed": -0.06699537539897181, "ICE-US_CT0_ZM0_Move_uniDR_68_zSeed": -0.004195924410777787, "ICE-US_CT0_ZM0_Move_uniDR_68_volSeed": 0.03815869573928932, "ICE-US_CT0_CL0_VSR_uniDR_18_smoothSeed": 0.20001400837721797, "ICE-US_CT0_CL0_VSR_uniDR_18_zSeed": -0.014594436386402667, "ICE-US_CT0_CL0_VSR_uniDR_18_volSeed": 0.045530119753604284, "ICE-US_CT0_ICE-EU_BRN0_VSR_uniDR_18_smoothSeed": 0.2132225111738398, "ICE-US_CT0_ICE-EU_BRN0_VSR_uniDR_18_zSeed": -0.013742940146990708, "ICE-US_CT0_ICE-EU_BRN0_VSR_uniDR_18_volSeed": 0.046744013904659036, "ICE-US_CT0_ICE-EU_G0_VSR_uniDR_18_smoothSeed": 0.15403011961395358, "ICE-US_CT0_ICE-EU_G0_VSR_uniDR_18_zSeed": -0.02327634639006937, "ICE-US_CT0_ICE-EU_G0_VSR_uniDR_18_volSeed": 0.04768133281701256, "ICE-US_CT0_ICE-US_MME0_VSR_uniDR_5_smoothSeed": 0.4444932625547525, "ICE-US_CT0_ICE-US_MME0_VSR_uniDR_5_zSeed": 0.06144275849605588, "ICE-US_CT0_ICE-US_MME0_VSR_uniDR_5_volSeed": 0.0901890439588073, "ICE-US_CT0_FESB0_VSR_uniDR_5_smoothSeed": 0.07644650885622764, "ICE-US_CT0_FESB0_VSR_uniDR_5_zSeed": -0.03041082066297482, "ICE-US_CT0_FESB0_VSR_uniDR_5_volSeed": 0.09215468450486382, "ICE-US_CT0_ZT0_Move_uniDR_68_smoothSeed": 0.0010060153342477409, "ICE-US_CT0_ZT0_Move_uniDR_68_zSeed": -1.0560020091101872e-05, "ICE-US_CT0_ZT0_Move_uniDR_68_volSeed": 0.0005184153157813073}, "ICE-EU_G0": {"ICE-EU_G0_midPrice": 757.5, "Volatility_ICE-EU_G0": 3.5670976215770516, "ICE-EU_G0_lastTS": "2023_12_14_23", "ICE-EU_G0_symbol": "GASF24", "W0_midPrice": 624.7, "Volatility_W0": 1.527714009778841, "W0_symbol": "QWH24", "W0_lastTS": "2023_12_14_13", "ICE-LX_C0_midPrice": 3561.0, "Volatility_ICE-LX_C0": 5.6933460194636965, "ICE-LX_C0_symbol": "QCH24", "ICE-LX_C0_lastTS": "2023_12_14_12", "ALSI0_midPrice": 68926.0, "Volatility_ALSI0": 114.40543839187103, "ALSI0_symbol": "ALJZ23", "ALSI0_lastTS": "2023_12_14_11", "ZN0_midPrice": 112.34375, "Volatility_ZN0": 0.09169215007769244, "ZN0_symbol": "@TYH24", "ZN0_lastTS": "2023_12_14_23", "ZL0_midPrice": 49.9, "Volatility_ZL0": 0.18977384050220228, "ZL0_symbol": "@BOF24", "ZL0_lastTS": "2023_12_14_23", "ICE-EU_G0_ALSI0_Move_uniDR_6_smoothSeed": 45.286970863396384, "ICE-EU_G0_ALSI0_Move_uniDR_6_zSeed": 7.721921592099898, "ICE-EU_G0_ALSI0_Move_uniDR_6_volSeed": 7.720974192005882, "ICE-EU_G0_ICE-LX_C0_VSR_uniDR_68_smoothSeed": -0.021584138128299714, "ICE-EU_G0_ICE-LX_C0_VSR_uniDR_68_zSeed": 0.0007091931285006688, "ICE-EU_G0_ICE-LX_C0_VSR_uniDR_68_volSeed": 0.03706981184360556, "ICE-EU_G0_W0_VSR_uniDR_68_smoothSeed": -0.15562102335845523, "ICE-EU_G0_W0_VSR_uniDR_68_zSeed": -0.006675532586679785, "ICE-EU_G0_W0_VSR_uniDR_68_volSeed": 0.03137524891613583, "ICE-EU_G0_ZN0_VSR_uniDR_35_smoothSeed": 0.25395420196911245, "ICE-EU_G0_ZN0_VSR_uniDR_35_zSeed": 0.018478280263467897, "ICE-EU_G0_ZN0_VSR_uniDR_35_volSeed": 0.05772047756275923, "ICE-EU_G0_ZL0_Move_uniDR_68_smoothSeed": -0.010133658673514805, "ICE-EU_G0_ZL0_Move_uniDR_68_zSeed": 0.00019428696050729073, "ICE-EU_G0_ZL0_Move_uniDR_68_volSeed": 0.00400109360225102}, "ICE-US_KC0": {"ICE-US_KC0_midPrice": 190.2, "Volatility_ICE-US_KC0": 1.0174683744872728, "ICE-US_KC0_lastTS": "2023_12_14_14", "ICE-US_KC0_symbol": "@KCH24", "RS1_midPrice": 666.9, "Volatility_RS1": 2.62008285054329, "RS1_symbol": "@RSH24", "RS1_lastTS": "2023_12_14_22", "RB0_midPrice": 2.1288, "Volatility_RB0": 0.014436307580432557, "RB0_symbol": "QRBF24", "RB0_lastTS": "2023_12_14_23", "RS0_midPrice": 666.9, "Volatility_RS0": 2.691369489325683, "RS0_symbol": "@RSH24", "RS0_lastTS": "2023_12_14_22", "NG0_midPrice": 2.434, "Volatility_NG0": 0.0433214025983995, "NG0_symbol": "QNGF24", "NG0_lastTS": "2023_12_14_23", "ICE-US_KC0_RB0_Move_uniDR_35_smoothSeed": 0.0005133446303888169, "ICE-US_KC0_RB0_Move_uniDR_35_zSeed": -7.412377824619907e-05, "ICE-US_KC0_RB0_Move_uniDR_35_volSeed": 0.000407148881939198, "ICE-US_KC0_NG0_Move_uniDR_35_smoothSeed": -0.0005375811744436536, "ICE-US_KC0_NG0_Move_uniDR_35_zSeed": -2.4288738608178493e-05, "ICE-US_KC0_NG0_Move_uniDR_35_volSeed": 0.0013851489130100828, "ICE-US_KC0_RS1_Basis_uniDR_69_smoothSeed": 198.824993209544, "ICE-US_KC0_RS1_Basis_uniDR_69_zSeed": 5.6958825049651365, "ICE-US_KC0_RS1_Basis_uniDR_69_volSeed": 0.6041549436264063}}, "initPositions": {"ZN0": 0, "ZF0": 0, "FBTP0": 0, "AP0": 0, "ES0": 0, "FSMI0": 0, "FTI0": 0, "ALSI0": 0, "ZC0": 0, "ZS0": 0, "ZM0": 0, "ZW0": 0, "KE0": 0, "LE0": 0, "CL0": 0, "HO0": 0, "RS0": 0, "W0": 0, "ICE-US_CT0": -1, "ICE-EU_G0": 0, "ICE-US_KC0": 0}, "trades": {"ZN0": 0, "ZF0": 0, "FBTP0": 0, "AP0": 1, "ES0": -1, "FSMI0": 0, "FTI0": 0, "ALSI0": 0, "ZC0": 0, "ZS0": 0, "ZM0": 0, "ZW0": -1, "KE0": -2, "LE0": 0, "CL0": 0, "HO0": 0, "RS0": -3, "W0": 0, "ICE-US_CT0": 1, "ICE-EU_G0": 0, "ICE-US_KC0": 0}, "seedDump": {"ZN0": {"ZN0_midPrice": 112.359375, "Volatility_ZN0": 0.08915710091724607, "ZN0_lastTS": "2023_12_15_00", "ZN0_symbol": "@TYH24", "CL0_midPrice": 72.31, "Volatility_CL0": 0.31345191037238496, "CL0_symbol": "QCLG24", "CL0_lastTS": "2023_12_15_00", "AUD=_midPrice": 0.67169, "Volatility_AUD=": 0.0010602088336393596, "AUD=_symbol": "AUDUSD.COMP", "AUD=_lastTS": "2023_12_15_00", "PL0_midPrice": 966.2, "Volatility_PL0": 3.515813538048888, "PL0_symbol": "QPLF24", "PL0_lastTS": "2023_12_15_00", "ICE-US_CT0_midPrice": 81.29, "Volatility_ICE-US_CT0": 0.29347785927308795, "ICE-US_CT0_symbol": "@CTH24", "ICE-US_CT0_lastTS": "2023_12_14_23", "CAD=_midPrice": 1.3390107388661256, "Volatility_CAD=": 0.0012798789811360252, "CAD=_symbol": "CADUSD.COMP", "CAD=_lastTS": "2023_12_15_00", "ZN0_CL0_Move_uniDR_9_smoothSeed": 0.0666536409745476, "ZN0_CL0_Move_uniDR_9_zSeed": 0.0060922706527278825, "ZN0_CL0_Move_uniDR_9_volSeed": 0.017852335699833154, "ZN0_PL0_Move_uniDR_9_smoothSeed": 0.7466922108315854, "ZN0_PL0_Move_uniDR_9_zSeed": 0.31196518861858735, "ZN0_PL0_Move_uniDR_9_volSeed": 0.18059974925426991, "ZN0_AUD=_Move_uniDR_35_smoothSeed": 0.00019288116310110377, "ZN0_AUD=_Move_uniDR_35_zSeed": 1.3807439805829956e-05, "ZN0_AUD=_Move_uniDR_35_volSeed": 2.5903723965833554e-05, "ZN0_CAD=_Move_uniDR_18_smoothSeed": -0.00038036005980222345, "ZN0_CAD=_Move_uniDR_18_zSeed": -4.6973830842617835e-05, "ZN0_CAD=_Move_uniDR_18_volSeed": 4.871152251124002e-05, "ZN0_ICE-US_CT0_Move_uniDR_68_smoothSeed": 0.0007714108991142311, "ZN0_ICE-US_CT0_Move_uniDR_68_zSeed": 0.0007810509720054211, "ZN0_ICE-US_CT0_Move_uniDR_68_volSeed": 0.0053026609812719646}, "ZF0": {"ZF0_midPrice": 108.3359375, "Volatility_ZF0": 0.05748008379959312, "ZF0_lastTS": "2023_12_14_23", "ZF0_symbol": "@FVH24", "CL0_midPrice": 72.31, "Volatility_CL0": 0.3158119864827697, "CL0_symbol": "QCLG24", "CL0_lastTS": "2023_12_15_00", "HO0_midPrice": 2.6141, "Volatility_HO0": 0.010665383409782134, "HO0_symbol": "QHOF24", "HO0_lastTS": "2023_12_14_23", "PL0_midPrice": 966.2, "Volatility_PL0": 3.44590829929656, "PL0_symbol": "QPLF24", "PL0_lastTS": "2023_12_15_00", "NZD=_midPrice": 0.62161, "Volatility_NZD=": 0.0010008498521182567, "NZD=_symbol": "NZDUSD.COMP", "NZD=_lastTS": "2023_12_15_00", "ZF0_HO0_Move_uniDR_68_smoothSeed": 0.00022701005671438943, "ZF0_HO0_Move_uniDR_68_zSeed": -2.83960269719885e-05, "ZF0_HO0_Move_uniDR_68_volSeed": 0.00027741497988361573, "ZF0_NZD=_Move_uniDR_6_smoothSeed": 0.00020530384532725546, "ZF0_NZD=_Move_uniDR_6_zSeed": 0.0001127954171909437, "ZF0_NZD=_Move_uniDR_6_volSeed": 6.485888920436377e-05, "ZF0_PL0_Move_uniDR_9_smoothSeed": 0.8505785797161132, "ZF0_PL0_Move_uniDR_9_zSeed": 0.31743897852088765, "ZF0_PL0_Move_uniDR_9_volSeed": 0.17852446043722278, "ZF0_CL0_Move_uniDR_6_smoothSeed": 0.06644939980405543, "ZF0_CL0_Move_uniDR_6_zSeed": 0.008020290150069226, "ZF0_CL0_Move_uniDR_6_volSeed": 0.022243506925280036}, "FBTP0": {"FBTP0_midPrice": 118.38, "Volatility_FBTP0": 0.2322025640712194, "FBTP0_lastTS": "2023_12_14_13", "FBTP0_symbol": "BTPH24", "CL0_midPrice": 72.31, "Volatility_CL0": 0.4409407729558185, "CL0_symbol": "QCLG24", "CL0_lastTS": "2023_12_15_00", "EUR=_midPrice": 1.0998, "Volatility_EUR=": 0.0016366711304525174, "EUR=_symbol": "EURUSD.COMP", "EUR=_lastTS": "2023_12_15_00", "FTI0_midPrice": 794.85, "Volatility_FTI0": 1.7844639822381771, "FTI0_symbol": "AEXF24", "FTI0_lastTS": "2023_12_14_16", "ICE-EU_BRN0_midPrice": 77.07, "Volatility_ICE-EU_BRN0": 0.4350350039662795, "ICE-EU_BRN0_symbol": "QBZG24", "ICE-EU_BRN0_lastTS": "2023_12_14_23", "ICE-LL_R0_midPrice": 100.4, "Volatility_ICE-LL_R0": 0.16501986979413033, "ICE-LL_R0_symbol": "LGH24", "ICE-LL_R0_lastTS": "2023_12_14_13", "ICE-EU_G0_midPrice": 757.5, "Volatility_ICE-EU_G0": 5.07262673056315, "ICE-EU_G0_symbol": "GASF24", "ICE-EU_G0_lastTS": "2023_12_14_23", "FBTP0_ICE-LL_R0_Move_uniDR_68_smoothSeed": 0.023206596453688492, "FBTP0_ICE-LL_R0_Move_uniDR_68_zSeed": 0.0006090344996219397, "FBTP0_ICE-LL_R0_Move_uniDR_68_volSeed": 0.003229561671924133, "FBTP0_FTI0_VSR_uniDR_68_smoothSeed": -0.016533765483933212, "FBTP0_FTI0_VSR_uniDR_68_zSeed": 0.0024909758775446683, "FBTP0_FTI0_VSR_uniDR_68_volSeed": 0.027179199726103893, "FBTP0_CL0_VSR_uniDR_68_smoothSeed": -0.05713938447291463, "FBTP0_CL0_VSR_uniDR_68_zSeed": -0.0014527440583158825, "FBTP0_CL0_VSR_uniDR_68_volSeed": 0.0460072667650341, "FBTP0_ICE-EU_G0_VSR_uniDR_35_smoothSeed": -0.13928929251623132, "FBTP0_ICE-EU_G0_VSR_uniDR_35_zSeed": -0.006328745449216822, "FBTP0_ICE-EU_G0_VSR_uniDR_35_volSeed": 0.06328945275679812, "FBTP0_ICE-EU_BRN0_VSR_uniDR_68_smoothSeed": -0.05781850254710015, "FBTP0_ICE-EU_BRN0_VSR_uniDR_68_zSeed": -0.0018157434591143326, "FBTP0_ICE-EU_BRN0_VSR_uniDR_68_volSeed": 0.04991796074677709}, "AP0": {"AP0_midPrice": 7463.0, "Volatility_AP0": 12.905251571333347, "AP0_lastTS": "2023_12_14_23", "AP0_symbol": "SPIZ23", "JPY=_midPrice": 141.93456816407638, "Volatility_JPY=": 0.19258236862333056, "JPY=_symbol": "JPYUSD.COMP", "JPY=_lastTS": "2023_12_15_00", "FGBL0_midPrice": 135.9, "Volatility_FGBL0": 0.1551890066975636, "FGBL0_symbol": "BDH24", "FGBL0_lastTS": "2023_12_14_23", "AUD=_midPrice": 0.67169, "Volatility_AUD=": 0.001282678532619507, "AUD=_symbol": "AUDUSD.COMP", "AUD=_lastTS": "2023_12_15_00", "ZS1_midPrice": 1334.25, "Volatility_ZS1": 3.802990211339768, "ZS1_symbol": "@SH24", "ZS1_lastTS": "2023_12_14_23", "FBTS0_midPrice": 106.29, "Volatility_FBTS0": 0.05366702572966391, "FBTS0_symbol": "BTSH24", "FBTS0_lastTS": "2023_12_14_13", "ZS0_midPrice": 1317.0, "Volatility_ZS0": 3.905540267354456, "ZS0_symbol": "@SF24", "ZS0_lastTS": "2023_12_14_23", "ICE-US_KC0_midPrice": 190.2, "Volatility_ICE-US_KC0": 0.7913139870241306, "ICE-US_KC0_symbol": "@KCH24", "ICE-US_KC0_lastTS": "2023_12_14_14", "ICE-LL_R0_midPrice": 100.4, "Volatility_ICE-LL_R0": 0.13078273534171833, "ICE-LL_R0_symbol": "LGH24", "ICE-LL_R0_lastTS": "2023_12_14_13", "NQ0_midPrice": 16778.0, "Volatility_NQ0": 28.516062005922766, "NQ0_symbol": "@NQH24", "NQ0_lastTS": "2023_12_15_00", "AP0_FGBL0_Basis_uniDR_6_smoothSeed": -7297.722911250319, "AP0_FGBL0_Basis_uniDR_6_zSeed": -5255.31591892554, "AP0_FGBL0_Basis_uniDR_6_volSeed": 1155.0418510538009, "AP0_ICE-LL_R0_Move_uniDR_6_smoothSeed": -0.0046553286540714865, "AP0_ICE-LL_R0_Move_uniDR_6_zSeed": 0.020358544436976236, "AP0_ICE-LL_R0_Move_uniDR_6_volSeed": 0.00907562032917027, "AP0_JPY=_Move_uniDR_35_smoothSeed": -0.0371806308009554, "AP0_JPY=_Move_uniDR_35_zSeed": -0.0025647043585367885, "AP0_JPY=_Move_uniDR_35_volSeed": 0.005199915288382421, "AP0_ICE-US_KC0_Move_uniDR_17_smoothSeed": 0.05852001772655609, "AP0_ICE-US_KC0_Move_uniDR_17_zSeed": 0.029320965121711482, "AP0_ICE-US_KC0_Move_uniDR_17_volSeed": 0.0321229628620375, "AP0_ZS1_Basis_uniDR_35_smoothSeed": -5507.817428931832, "AP0_ZS1_Basis_uniDR_35_zSeed": -844.7054974933712, "AP0_ZS1_Basis_uniDR_35_volSeed": 147.60583147802504, "AP0_NQ0_VSR_uniDR_35_smoothSeed": -0.0905730581828777, "AP0_NQ0_VSR_uniDR_35_zSeed": 0.01052647527262541, "AP0_NQ0_VSR_uniDR_35_volSeed": 0.028340760839292312, "AP0_FBTS0_Move_uniDR_6_smoothSeed": 0.0040493667608049455, "AP0_FBTS0_Move_uniDR_6_zSeed": 0.0035496436669885086, "AP0_FBTS0_Move_uniDR_6_volSeed": 0.003074568685906861}, "ES0": {"ES0_midPrice": 4778.25, "Volatility_ES0": 6.874099236199754, "ES0_lastTS": "2023_12_15_00", "ES0_symbol": "@ESH24", "FCE0_midPrice": 7575.3, "Volatility_FCE0": 12.981254745216313, "FCE0_symbol": "MTZ23", "FCE0_lastTS": "2023_12_14_16", "FDAX0_midPrice": 16759.0, "Volatility_FDAX0": 29.03171945004388, "FDAX0_symbol": "DXMZ23", "FDAX0_lastTS": "2023_12_14_22", "FESX0_midPrice": 4551.0, "Volatility_FESX0": 8.339114362004699, "FESX0_symbol": "EXZ23", "FESX0_lastTS": "2023_12_14_23", "FTI0_midPrice": 794.85, "Volatility_FTI0": 1.2915437002918344, "FTI0_symbol": "AEXF24", "FTI0_lastTS": "2023_12_14_16", "ICE-LL_R0_midPrice": 100.4, "Volatility_ICE-LL_R0": 0.12053932513276776, "ICE-LL_R0_symbol": "LGH24", "ICE-LL_R0_lastTS": "2023_12_14_13", "ES0_FTI0_VSR_uniDR_5_smoothSeed": -0.14213611517425, "ES0_FTI0_VSR_uniDR_5_zSeed": -0.10245418393166873, "ES0_FTI0_VSR_uniDR_5_volSeed": 0.051936233353206435, "ES0_FCE0_VSR_uniDR_5_smoothSeed": -0.17160785175653914, "ES0_FCE0_VSR_uniDR_5_zSeed": -0.11873915032710934, "ES0_FCE0_VSR_uniDR_5_volSeed": 0.05616257162643112, "ES0_FDAX0_VSR_uniDR_5_smoothSeed": -0.24362478018593023, "ES0_FDAX0_VSR_uniDR_5_zSeed": -0.16582245730476436, "ES0_FDAX0_VSR_uniDR_5_volSeed": 0.05888310202613311, "ES0_ICE-LL_R0_Move_uniDR_68_smoothSeed": 0.017888701913160103, "ES0_ICE-LL_R0_Move_uniDR_68_zSeed": 0.0011137845049156642, "ES0_ICE-LL_R0_Move_uniDR_68_volSeed": 0.0021906530464632, "ES0_FESX0_VSR_uniDR_5_smoothSeed": -0.12728642656767813, "ES0_FESX0_VSR_uniDR_5_zSeed": -0.13958919219331, "ES0_FESX0_VSR_uniDR_5_volSeed": 0.05440632394365011}, "FSMI0": {"FSMI0_midPrice": 11174.0, "Volatility_FSMI0": 24.721489430595415, "FSMI0_lastTS": "2023_12_14_16", "FSMI0_symbol": "SWH24", "FBTS0_midPrice": 106.29, "Volatility_FBTS0": 0.051751764056229776, "FBTS0_symbol": "BTSH24", "FBTS0_lastTS": "2023_12_14_13", "NG0_midPrice": 2.434, "Volatility_NG0": 0.03574963271727295, "NG0_symbol": "QNGF24", "NG0_lastTS": "2023_12_14_23", "CHF=_midPrice": 0.8657441082167807, "Volatility_CHF=": 0.001472082392712978, "CHF=_symbol": "CHFUSD.COMP", "CHF=_lastTS": "2023_12_15_00", "FSMI0_FBTS0_Move_uniDR_6_smoothSeed": 0.010036316065420714, "FSMI0_FBTS0_Move_uniDR_6_zSeed": 0.0026189981514141837, "FSMI0_FBTS0_Move_uniDR_6_volSeed": 0.003163102467863559, "FSMI0_NG0_Move_uniDR_6_smoothSeed": 0.003026429682949034, "FSMI0_NG0_Move_uniDR_6_zSeed": -0.0007265245480454263, "FSMI0_NG0_Move_uniDR_6_volSeed": 0.002625344702016013}, "FTI0": {"FTI0_midPrice": 794.85, "Volatility_FTI0": 1.7370550080288514, "FTI0_lastTS": "2023_12_14_16", "FTI0_symbol": "AEXF24", "FBTS0_midPrice": 106.29, "Volatility_FBTS0": 0.058883896324364485, "FBTS0_symbol": "BTSH24", "FBTS0_lastTS": "2023_12_14_13", "HE0_midPrice": 70.475, "Volatility_HE0": 0.34410956910162666, "HE0_symbol": "@HEG24", "HE0_lastTS": "2023_12_14_15", "EUR=_midPrice": 1.0998, "Volatility_EUR=": 0.001568050556462079, "EUR=_symbol": "EURUSD.COMP", "EUR=_lastTS": "2023_12_15_00", "HE1_midPrice": 77.125, "Volatility_HE1": 0.400429033404327, "HE1_symbol": "@HEJ24", "HE1_lastTS": "2023_12_14_15", "NG0_midPrice": 2.434, "Volatility_NG0": 0.037419061410518394, "NG0_symbol": "QNGF24", "NG0_lastTS": "2023_12_14_23", "ICE-US_KC0_midPrice": 190.2, "Volatility_ICE-US_KC0": 0.8762455047240485, "ICE-US_KC0_symbol": "@KCH24", "ICE-US_KC0_lastTS": "2023_12_14_14", "FTI0_FBTS0_Move_uniDR_5_smoothSeed": 0.006934239201436229, "FTI0_FBTS0_Move_uniDR_5_zSeed": 0.0038299771947216143, "FTI0_FBTS0_Move_uniDR_5_volSeed": 0.0036407746504497794, "FTI0_ICE-US_KC0_Move_uniDR_9_smoothSeed": 0.086852638853322, "FTI0_ICE-US_KC0_Move_uniDR_9_zSeed": 0.056241958785453974, "FTI0_ICE-US_KC0_Move_uniDR_9_volSeed": 0.05054535358857477, "FTI0_HE1_Basis_uniDR_69_smoothSeed": -380.13370579114917, "FTI0_HE1_Basis_uniDR_69_zSeed": -15.918741986570677, "FTI0_HE1_Basis_uniDR_69_volSeed": 2.0311485948593635, "FTI0_NG0_Move_uniDR_35_smoothSeed": 0.0010552575430737671, "FTI0_NG0_Move_uniDR_35_zSeed": 2.836104955933172e-05, "FTI0_NG0_Move_uniDR_35_volSeed": 0.0011869997551392575}, "ALSI0": {"ALSI0_midPrice": 68926.0, "Volatility_ALSI0": 179.7271496362817, "ALSI0_lastTS": "2023_12_14_11", "ALSI0_symbol": "ALJZ23", "GC1_midPrice": 2038.7, "Volatility_GC1": 3.8201682417123717, "GC1_symbol": "QGCF24", "GC1_lastTS": "2023_12_14_23", "AUD=_midPrice": 0.67169, "Volatility_AUD=": 0.001696337312967416, "AUD=_symbol": "AUDUSD.COMP", "AUD=_lastTS": "2023_12_15_00", "ZAR=_midPrice": 18.333600056658156, "Volatility_ZAR=": 0.04903666116977198, "ZAR=_symbol": "ZARUSD.COMP", "ZAR=_lastTS": "2023_12_15_00", "GC0_midPrice": 2050.2, "Volatility_GC0": 3.8047118301012106, "GC0_symbol": "QGCG24", "GC0_lastTS": "2023_12_15_00", "ES0_midPrice": 4778.25, "Volatility_ES0": 8.464740663380452, "ES0_symbol": "@ESH24", "ES0_lastTS": "2023_12_15_00", "ZF0_midPrice": 108.3359375, "Volatility_ZF0": 0.07476304080100486, "ZF0_symbol": "@FVH24", "ZF0_lastTS": "2023_12_14_23", "ZN0_midPrice": 112.359375, "Volatility_ZN0": 0.12158668989610925, "ZN0_symbol": "@TYH24", "ZN0_lastTS": "2023_12_15_00", "NQ0_midPrice": 16778.0, "Volatility_NQ0": 30.690350392260385, "NQ0_symbol": "@NQH24", "NQ0_lastTS": "2023_12_15_00", "ALSI0_ZF0_Move_uniDR_18_smoothSeed": 0.0008215293547266596, "ALSI0_ZF0_Move_uniDR_18_zSeed": -0.0010742039209423577, "ALSI0_ZF0_Move_uniDR_18_volSeed": 0.0029437419290552023, "ALSI0_GC1_Basis_uniDR_8_smoothSeed": -65299.83817373957, "ALSI0_GC1_Basis_uniDR_8_zSeed": -19481.10085939691, "ALSI0_GC1_Basis_uniDR_8_volSeed": 2409.6656998148437, "ALSI0_ES0_Move_uniDR_18_smoothSeed": 0.6511524148058685, "ALSI0_ES0_Move_uniDR_18_zSeed": 0.1517587266343111, "ALSI0_ES0_Move_uniDR_18_volSeed": 0.3111645500513292, "ALSI0_NQ0_Move_uniDR_18_smoothSeed": 2.0058348793865264, "ALSI0_NQ0_Move_uniDR_18_zSeed": 0.9515548966897203, "ALSI0_NQ0_Move_uniDR_18_volSeed": 1.061433798648693, "ALSI0_AUD=_VSR_uniDR_69_smoothSeed": -0.03448362493050176, "ALSI0_AUD=_VSR_uniDR_69_zSeed": 0.0022930335720530762, "ALSI0_AUD=_VSR_uniDR_69_volSeed": 0.018440881213063785, "ALSI0_ZN0_Move_uniDR_18_smoothSeed": 0.005014795437285887, "ALSI0_ZN0_Move_uniDR_18_zSeed": -0.0016262664761747376, "ALSI0_ZN0_Move_uniDR_18_volSeed": 0.004766283766220523}, "ZC0": {"ZC0_midPrice": 479.75, "Volatility_ZC0": 2.0718330308998323, "ZC0_lastTS": "2023_12_14_23", "ZC0_symbol": "@CH24", "ZC1_midPrice": 479.75, "Volatility_ZC1": 1.7985508302195439, "ZC1_symbol": "@CH24", "ZC1_lastTS": "2023_12_14_23", "RB0_midPrice": 2.1288, "Volatility_RB0": 0.010387795778322018, "RB0_symbol": "QRBF24", "RB0_lastTS": "2023_12_14_23", "CNH=_midPrice": 7.112760006942054, "Volatility_CNH=": 0.004440063660811152, "CNH=_symbol": "CNHUSD.COMP", "CNH=_lastTS": "2023_12_15_00", "ZC0_ZC1_Basis_uniDR_6_smoothSeed": 0.002897309173884323, "ZC0_ZC1_Basis_uniDR_6_zSeed": -0.00029662946707565406, "ZC0_ZC1_Basis_uniDR_6_volSeed": 0.04897189240245728, "ZC0_CNH=_Move_uniDR_68_smoothSeed": -0.00024666384173448045, "ZC0_CNH=_Move_uniDR_68_zSeed": 1.5807625575927359e-06, "ZC0_CNH=_Move_uniDR_68_volSeed": 0.00010890942847789487, "ZC0_RB0_Move_uniDR_38_smoothSeed": 0.0007285548259451598, "ZC0_RB0_Move_uniDR_38_zSeed": -2.7288477725051545e-05, "ZC0_RB0_Move_uniDR_38_volSeed": 0.0002890325577053453}, "ZS0": {"ZS0_midPrice": 1317.0, "Volatility_ZS0": 4.405760983498176, "ZS0_lastTS": "2023_12_14_23", "ZS0_symbol": "@SF24", "IND0_midPrice": 132900.0, "Volatility_IND0": 288.58556198074336, "IND0_symbol": "INDG24", "IND0_lastTS": "2023_12_14_17", "ZS1_midPrice": 1334.25, "Volatility_ZS1": 3.914312645511378, "ZS1_symbol": "@SH24", "ZS1_lastTS": "2023_12_14_23", "XT0_midPrice": 95.872, "Volatility_XT0": 0.012452794076894135, "XT0_symbol": "XTZ23", "XT0_lastTS": "2023_12_14_20", "PA0_midPrice": 1100.5, "Volatility_PA0": 9.23453608332284, "PA0_symbol": "QPAH24", "PA0_lastTS": "2023_12_15_00", "NQ0_midPrice": 16778.0, "Volatility_NQ0": 28.04285704641417, "NQ0_symbol": "@NQH24", "NQ0_lastTS": "2023_12_15_00", "ZS0_PA0_VSR_uniDR_68_smoothSeed": 0.07456671155396917, "ZS0_PA0_VSR_uniDR_68_zSeed": -0.0004367278614494719, "ZS0_PA0_VSR_uniDR_68_volSeed": 0.027422581460677237, "ZS0_IND0_Move_uniDR_9_smoothSeed": -26.745441638646366, "ZS0_IND0_Move_uniDR_9_zSeed": -4.871563507462191, "ZS0_IND0_Move_uniDR_9_volSeed": 16.5188065973946, "ZS0_NQ0_VSR_uniDR_68_smoothSeed": 0.03774397102361458, "ZS0_NQ0_VSR_uniDR_68_zSeed": 0.006073172412187971, "ZS0_NQ0_VSR_uniDR_68_volSeed": 0.028609469851637884, "ZS0_ZS1_Basis_uniDR_6_smoothSeed": 0.0666254064104449, "ZS0_ZS1_Basis_uniDR_6_zSeed": -0.01843253417972142, "ZS0_ZS1_Basis_uniDR_6_volSeed": 0.06471852565575645, "ZS0_XT0_VSR_uniDR_68_smoothSeed": 0.010438604654128951, "ZS0_XT0_VSR_uniDR_68_zSeed": -0.0005750898916867734, "ZS0_XT0_VSR_uniDR_68_volSeed": 0.0341080187951758}, "ZM0": {"ZM0_midPrice": 395.2, "Volatility_ZM0": 1.652687111082631, "ZM0_lastTS": "2023_12_14_23", "ZM0_symbol": "@SMH24", "YM0_midPrice": 37305.0, "Volatility_YM0": 66.3317905091831, "YM0_symbol": "@YMZ23", "YM0_lastTS": "2023_12_14_23", "FCE0_midPrice": 7575.3, "Volatility_FCE0": 14.038719265978461, "FCE0_symbol": "MTZ23", "FCE0_lastTS": "2023_12_14_16", "ICE-US_SB0_midPrice": 21.84, "Volatility_ICE-US_SB0": 0.06965275345772756, "ICE-US_SB0_symbol": "@SBH24", "ICE-US_SB0_lastTS": "2023_12_14_13", "FSMI0_midPrice": 11174.0, "Volatility_FSMI0": 20.999746551873887, "FSMI0_symbol": "SWH24", "FSMI0_lastTS": "2023_12_14_16", "FESX0_midPrice": 4551.0, "Volatility_FESX0": 9.109240512724021, "FESX0_symbol": "EXZ23", "FESX0_lastTS": "2023_12_14_23", "HG0_midPrice": 3.8935, "Volatility_HG0": 0.01019840999130512, "HG0_symbol": "QHGH24", "HG0_lastTS": "2023_12_15_00", "CNH=_midPrice": 7.112760006942054, "Volatility_CNH=": 0.004386338974392312, "CNH=_symbol": "CNHUSD.COMP", "CNH=_lastTS": "2023_12_15_00", "FTI0_midPrice": 794.85, "Volatility_FTI0": 1.402368879478022, "FTI0_symbol": "AEXF24", "FTI0_lastTS": "2023_12_14_16", "ZM0_HG0_VSR_uniDR_18_smoothSeed": 0.06567202651496204, "ZM0_HG0_VSR_uniDR_18_zSeed": 0.013266000295773506, "ZM0_HG0_VSR_uniDR_18_volSeed": 0.05376637275270564, "ZM0_FESX0_VSR_uniDR_68_smoothSeed": 0.02542882340208122, "ZM0_FESX0_VSR_uniDR_68_zSeed": 0.004806998832050915, "ZM0_FESX0_VSR_uniDR_68_volSeed": 0.027078611867034537, "ZM0_FSMI0_VSR_uniDR_68_smoothSeed": 0.025879851148972035, "ZM0_FSMI0_VSR_uniDR_68_zSeed": 0.0032189322189122853, "ZM0_FSMI0_VSR_uniDR_68_volSeed": 0.027192980456503407, "ZM0_FCE0_VSR_uniDR_68_smoothSeed": -0.003301623930382973, "ZM0_FCE0_VSR_uniDR_68_zSeed": 0.004998360066747684, "ZM0_FCE0_VSR_uniDR_68_volSeed": 0.026008526256439245, "ZM0_ICE-US_SB0_VSR_uniDR_68_smoothSeed": -0.11648463914309146, "ZM0_ICE-US_SB0_VSR_uniDR_68_zSeed": -0.010183287008843606, "ZM0_ICE-US_SB0_VSR_uniDR_68_volSeed": 0.03007890041334662, "ZM0_FTI0_VSR_uniDR_35_smoothSeed": -0.005150014866895864, "ZM0_FTI0_VSR_uniDR_35_zSeed": 0.013727414869003272, "ZM0_FTI0_VSR_uniDR_35_volSeed": 0.03931322859109912, "ZM0_YM0_VSR_uniDR_18_smoothSeed": 0.017540532356569286, "ZM0_YM0_VSR_uniDR_18_zSeed": 0.029626660961092864, "ZM0_YM0_VSR_uniDR_18_volSeed": 0.05456145546516257, "ZM0_CNH=_VSR_uniDR_68_smoothSeed": -0.04738909076693293, "ZM0_CNH=_VSR_uniDR_68_zSeed": 0.0014572950023087707, "ZM0_CNH=_VSR_uniDR_68_volSeed": 0.03614504505650737}, "ZW0": {"ZW0_midPrice": 616.75, "Volatility_ZW0": 3.6459796689244444, "ZW0_lastTS": "2023_12_15_00", "ZW0_symbol": "@WH24", "HE0_midPrice": 70.475, "Volatility_HE0": 0.2928394460277385, "HE0_symbol": "@HEG24", "HE0_lastTS": "2023_12_14_15", "ICE-LL_Z0_midPrice": 7595.0, "Volatility_ICE-LL_Z0": 9.922899459782567, "ICE-LL_Z0_symbol": "TUKZ23", "ICE-LL_Z0_lastTS": "2023_12_12_05", "ICE-LX_C0_midPrice": 3561.0, "Volatility_ICE-LX_C0": 5.830507628081605, "ICE-LX_C0_symbol": "QCH24", "ICE-LX_C0_lastTS": "2023_12_14_12", "ZW0_ICE-LL_Z0_Move_uniDR_35_smoothSeed": 0.4109983428172058, "ZW0_ICE-LL_Z0_Move_uniDR_35_zSeed": 0.09418208321085657, "ZW0_ICE-LL_Z0_Move_uniDR_35_volSeed": 0.2958507513911215, "ZW0_ICE-LX_C0_Move_uniDR_5_smoothSeed": 0.5154598720391191, "ZW0_ICE-LX_C0_Move_uniDR_5_zSeed": 0.6530671457337461, "ZW0_ICE-LX_C0_Move_uniDR_5_volSeed": 0.49343129801491675, "ZW0_HE0_VSR_uniDR_68_smoothSeed": 0.08348694635213308, "ZW0_HE0_VSR_uniDR_68_zSeed": 0.0009703451316751169, "ZW0_HE0_VSR_uniDR_68_volSeed": 0.03001154966798774}, "KE0": {"KE0_midPrice": 638.5, "Volatility_KE0": 3.7118242455006034, "KE0_lastTS": "2023_12_14_23", "KE0_symbol": "@KWH24", "W0_midPrice": 624.7, "Volatility_W0": 1.5294013831605644, "W0_symbol": "QWH24", "W0_lastTS": "2023_12_14_13", "ICE-LX_C0_midPrice": 3561.0, "Volatility_ICE-LX_C0": 5.82383364152674, "ICE-LX_C0_symbol": "QCH24", "ICE-LX_C0_lastTS": "2023_12_14_12", "ZAR=_midPrice": 18.333600056658156, "Volatility_ZAR=": 0.033738088558010096, "ZAR=_symbol": "ZARUSD.COMP", "ZAR=_lastTS": "2023_12_15_00", "KE0_ZAR=_Move_uniDR_38_smoothSeed": -0.004795966820935019, "KE0_ZAR=_Move_uniDR_38_zSeed": 0.00011917317578015834, "KE0_ZAR=_Move_uniDR_38_volSeed": 0.000861191057838511, "KE0_ICE-LX_C0_Move_uniDR_18_smoothSeed": 0.36505312996068484, "KE0_ICE-LX_C0_Move_uniDR_18_zSeed": 0.26983962754112384, "KE0_ICE-LX_C0_Move_uniDR_18_volSeed": 0.249037802923961, "KE0_W0_Move_uniDR_5_smoothSeed": 0.04694759379423952, "KE0_W0_Move_uniDR_5_zSeed": -0.18928494903004836, "KE0_W0_Move_uniDR_5_volSeed": 0.11284201721745465}, "LE0": {"LE0_midPrice": 167.925, "Volatility_LE0": 0.44250743874012693, "LE0_lastTS": "2023_12_14_15", "LE0_symbol": "@LEG24", "VX0_midPrice": 12.35, "Volatility_VX0": 0.35325045395453697, "VX0_symbol": "@VXZ23", "VX0_lastTS": "2023_12_14_23", "FCE0_midPrice": 7575.3, "Volatility_FCE0": 19.174765321076194, "FCE0_symbol": "MTZ23", "FCE0_lastTS": "2023_12_14_16", "KE0_midPrice": 638.5, "Volatility_KE0": 4.592242122598504, "KE0_symbol": "@KWH24", "KE0_lastTS": "2023_12_14_23", "FESX0_midPrice": 4551.0, "Volatility_FESX0": 13.469632978760705, "FESX0_symbol": "EXZ23", "FESX0_lastTS": "2023_12_14_23", "EUR=_midPrice": 1.0998, "Volatility_EUR=": 0.0019854643651872404, "EUR=_symbol": "EURUSD.COMP", "EUR=_lastTS": "2023_12_15_00", "ICE-US_CC0_midPrice": 4278.0, "Volatility_ICE-US_CC0": 15.409546210229063, "ICE-US_CC0_symbol": "@CCH24", "ICE-US_CC0_lastTS": "2023_12_14_14", "LE0_FCE0_Move_uniDR_5_smoothSeed": -7.489682692478791, "LE0_FCE0_Move_uniDR_5_zSeed": 0.07148185215911525, "LE0_FCE0_Move_uniDR_5_volSeed": 1.3450070685831912, "LE0_VX0_VSR_uniDR_5_smoothSeed": -0.044080095849952414, "LE0_VX0_VSR_uniDR_5_zSeed": -0.1360490513821765, "LE0_VX0_VSR_uniDR_5_volSeed": 0.13177192113842692, "LE0_ICE-US_CC0_VSR_uniDR_5_smoothSeed": -0.0921606297568673, "LE0_ICE-US_CC0_VSR_uniDR_5_zSeed": 0.04829744404230674, "LE0_ICE-US_CC0_VSR_uniDR_5_volSeed": 0.11856027194097561, "LE0_EUR=_VSR_uniDR_79_smoothSeed": -0.0349716781429493, "LE0_EUR=_VSR_uniDR_79_zSeed": -0.0010371512627571778, "LE0_EUR=_VSR_uniDR_79_volSeed": 0.04598835239096121, "LE0_FESX0_Move_uniDR_5_smoothSeed": -2.9976301255241364, "LE0_FESX0_Move_uniDR_5_zSeed": 0.20379732426960495, "LE0_FESX0_Move_uniDR_5_volSeed": 0.9729157333619769, "LE0_KE0_VSR_uniDR_79_smoothSeed": -0.09867071154465376, "LE0_KE0_VSR_uniDR_79_zSeed": -0.0015548804887282241, "LE0_KE0_VSR_uniDR_79_volSeed": 0.035973745049026895}, "CL0": {"CL0_midPrice": 72.31, "Volatility_CL0": 0.31695282400182395, "CL0_lastTS": "2023_12_15_00", "CL0_symbol": "QCLG24", "ALSI0_midPrice": 68926.0, "Volatility_ALSI0": 111.46188988795456, "ALSI0_symbol": "ALJZ23", "ALSI0_lastTS": "2023_12_14_11", "THB=_midPrice": 34.87400041088547, "Volatility_THB=": 0.044663747955204246, "THB=_symbol": "THBUSD.COMP", "THB=_lastTS": "2023_12_15_00", "ZF0_midPrice": 108.3359375, "Volatility_ZF0": 0.05763974476080909, "ZF0_symbol": "@FVH24", "ZF0_lastTS": "2023_12_14_23", "SGD=_midPrice": 1.327729999391621, "Volatility_SGD=": 0.0009116425140290994, "SGD=_symbol": "SGDUSD.COMP", "SGD=_lastTS": "2023_12_15_00", "CL0_ZF0_VSR_uniDR_68_smoothSeed": 0.08613947819512272, "CL0_ZF0_VSR_uniDR_68_zSeed": 0.0018533567824777072, "CL0_ZF0_VSR_uniDR_68_volSeed": 0.041620557581162856, "CL0_THB=_Move_uniDR_35_smoothSeed": -0.015028620221888908, "CL0_THB=_Move_uniDR_35_zSeed": -0.0005196301763434072, "CL0_THB=_Move_uniDR_35_volSeed": 0.0008471808283734678, "CL0_ALSI0_Move_uniDR_6_smoothSeed": 25.565624079426716, "CL0_ALSI0_Move_uniDR_6_zSeed": 8.316245456754562, "CL0_ALSI0_Move_uniDR_6_volSeed": 7.558250922571487, "CL0_SGD=_Move_uniDR_68_smoothSeed": -0.00013322748670760952, "CL0_SGD=_Move_uniDR_68_zSeed": -4.42550527209274e-06, "CL0_SGD=_Move_uniDR_68_volSeed": 1.7053352511799482e-05}, "HO0": {"HO0_midPrice": 2.6141, "Volatility_HO0": 0.010662978926371169, "HO0_lastTS": "2023_12_14_23", "HO0_symbol": "QHOF24", "ALSI0_midPrice": 68926.0, "Volatility_ALSI0": 108.86288033361603, "ALSI0_symbol": "ALJZ23", "ALSI0_lastTS": "2023_12_14_11", "ICE-US_CC0_midPrice": 4278.0, "Volatility_ICE-US_CC0": 9.594206884741595, "ICE-US_CC0_symbol": "@CCH24", "ICE-US_CC0_lastTS": "2023_12_14_14", "W0_midPrice": 624.7, "Volatility_W0": 1.4543502558401002, "W0_symbol": "QWH24", "W0_lastTS": "2023_12_14_13", "HO0_ICE-US_CC0_VSR_uniDR_68_smoothSeed": 0.0879420210347538, "HO0_ICE-US_CC0_VSR_uniDR_68_zSeed": 0.015984185834078644, "HO0_ICE-US_CC0_VSR_uniDR_68_volSeed": 0.029969034062412487, "HO0_W0_VSR_uniDR_68_smoothSeed": -0.12280621344861162, "HO0_W0_VSR_uniDR_68_zSeed": -0.003934257010887072, "HO0_W0_VSR_uniDR_68_volSeed": 0.029679979676715696, "HO0_ALSI0_Move_uniDR_8_smoothSeed": 37.99439107947599, "HO0_ALSI0_Move_uniDR_8_zSeed": 4.96924408521085, "HO0_ALSI0_Move_uniDR_8_volSeed": 6.060082797048011}, "RS0": {"RS0_midPrice": 667.2, "Volatility_RS0": 2.293807046022006, "RS0_lastTS": "2023_12_14_23", "RS0_symbol": "@RSH24", "CONF0_midPrice": 150.77, "Volatility_CONF0": 0.1486879222458668, "CONF0_symbol": "COH24", "CONF0_lastTS": "2023_12_14_10", "KE0_midPrice": 638.5, "Volatility_KE0": 3.225079305062421, "KE0_symbol": "@KWH24", "KE0_lastTS": "2023_12_14_23", "AUD=_midPrice": 0.67169, "Volatility_AUD=": 0.0013309254585046118, "AUD=_symbol": "AUDUSD.COMP", "AUD=_lastTS": "2023_12_15_00", "ZC0_midPrice": 479.75, "Volatility_ZC0": 1.7323573973537392, "ZC0_symbol": "@CH24", "ZC0_lastTS": "2023_12_14_23", "HG0_midPrice": 3.8935, "Volatility_HG0": 0.011572172083422231, "HG0_symbol": "QHGH24", "HG0_lastTS": "2023_12_15_00", "CNH=_midPrice": 7.112760006942054, "Volatility_CNH=": 0.005324494165803367, "CNH=_symbol": "CNHUSD.COMP", "CNH=_lastTS": "2023_12_15_00", "CAD=_midPrice": 1.3390107388661256, "Volatility_CAD=": 0.0016195045537487336, "CAD=_symbol": "CADUSD.COMP", "CAD=_lastTS": "2023_12_15_00", "ZW0_midPrice": 616.75, "Volatility_ZW0": 3.2303931968920936, "ZW0_symbol": "@WH24", "ZW0_lastTS": "2023_12_15_00", "RS0_ZW0_Move_uniDR_5_smoothSeed": -0.3309980473742037, "RS0_ZW0_Move_uniDR_5_zSeed": -0.22614283091690626, "RS0_ZW0_Move_uniDR_5_volSeed": 0.2534693966440491, "RS0_AUD=_Move_uniDR_68_smoothSeed": 5.663332702968389e-05, "RS0_AUD=_Move_uniDR_68_zSeed": -1.5232436834651612e-07, "RS0_AUD=_Move_uniDR_68_volSeed": 2.350966053919208e-05, "RS0_CNH=_VSR_uniDR_68_smoothSeed": -0.07046616893422988, "RS0_CNH=_VSR_uniDR_68_zSeed": 0.0004230867326863597, "RS0_CNH=_VSR_uniDR_68_volSeed": 0.04230480548607388, "RS0_KE0_Move_uniDR_5_smoothSeed": -0.24729980241228944, "RS0_KE0_Move_uniDR_5_zSeed": -0.22719289079895105, "RS0_KE0_Move_uniDR_5_volSeed": 0.24249946244343984, "RS0_HG0_Move_uniDR_68_smoothSeed": 0.0008335539006876989, "RS0_HG0_Move_uniDR_68_zSeed": 3.850867176606522e-05, "RS0_HG0_Move_uniDR_68_volSeed": 0.00021130207152960295, "RS0_CONF0_VSR_uniDR_17_smoothSeed": 0.10940511194582656, "RS0_CONF0_VSR_uniDR_17_zSeed": -0.004074539841359508, "RS0_CONF0_VSR_uniDR_17_volSeed": 0.0637535580492429, "RS0_ZC0_Move_uniDR_5_smoothSeed": -0.18980819362903167, "RS0_ZC0_Move_uniDR_5_zSeed": -0.08865945423537797, "RS0_ZC0_Move_uniDR_5_volSeed": 0.12816286137919647}, "W0": {"W0_midPrice": 624.7, "Volatility_W0": 2.102546761515223, "W0_lastTS": "2023_12_14_13", "W0_symbol": "QWH24", "ECO0_midPrice": 430.0, "Volatility_ECO0": 2.2550006853344944, "ECO0_symbol": "PGG24", "ECO0_lastTS": "2023_12_14_13", "RB0_midPrice": 2.1288, "Volatility_RB0": 0.014239432776968864, "RB0_symbol": "QRBF24", "RB0_lastTS": "2023_12_14_23", "KE0_midPrice": 638.5, "Volatility_KE0": 4.017100529504712, "KE0_symbol": "@KWH24", "KE0_lastTS": "2023_12_14_23", "W0_KE0_Move_uniDR_5_smoothSeed": -0.43019055099683134, "W0_KE0_Move_uniDR_5_zSeed": -0.10559871806111103, "W0_KE0_Move_uniDR_5_volSeed": 0.3140538758931877, "W0_RB0_Move_uniDR_8_smoothSeed": 0.004379679181595326, "W0_RB0_Move_uniDR_8_zSeed": -8.551160977470518e-05, "W0_RB0_Move_uniDR_8_volSeed": 0.0009075248552029717, "W0_ECO0_Move_uniDR_5_smoothSeed": -0.7371909329851579, "W0_ECO0_Move_uniDR_5_zSeed": -0.10284015695859099, "W0_ECO0_Move_uniDR_5_volSeed": 0.1962903671229377}, "ICE-US_CT0": {"ICE-US_CT0_midPrice": 81.29, "Volatility_ICE-US_CT0": 0.356598057333445, "ICE-US_CT0_lastTS": "2023_12_14_23", "ICE-US_CT0_symbol": "@CTH24", "CL0_midPrice": 72.31, "Volatility_CL0": 0.3809445509072497, "CL0_symbol": "QCLG24", "CL0_lastTS": "2023_12_15_00", "ZT0_midPrice": 102.75, "Volatility_ZT0": 0.02349227153780628, "ZT0_symbol": "@TUH24", "ZT0_lastTS": "2023_12_15_00", "ZM0_midPrice": 395.2, "Volatility_ZM0": 1.5115440764668682, "ZM0_symbol": "@SMH24", "ZM0_lastTS": "2023_12_14_23", "FESB0_midPrice": 118.8, "Volatility_FESB0": 0.46331760619052403, "FESB0_symbol": "SXZ23", "FESB0_lastTS": "2023_12_14_23", "ZF0_midPrice": 108.3359375, "Volatility_ZF0": 0.06422924658755233, "ZF0_symbol": "@FVH24", "ZF0_lastTS": "2023_12_14_23", "ICE-US_MME0_midPrice": 999.7, "Volatility_ICE-US_MME0": 3.0288732674704932, "ICE-US_MME0_symbol": "MEFZ23", "ICE-US_MME0_lastTS": "2023_12_14_12", "ICE-EU_BRN0_midPrice": 77.07, "Volatility_ICE-EU_BRN0": 0.3686288210923251, "ICE-EU_BRN0_symbol": "QBZG24", "ICE-EU_BRN0_lastTS": "2023_12_14_23", "ICE-EU_G0_midPrice": 757.5, "Volatility_ICE-EU_G0": 4.007751549337916, "ICE-EU_G0_symbol": "GASF24", "ICE-EU_G0_lastTS": "2023_12_14_23", "ICE-US_CT0_ZF0_Move_uniDR_68_smoothSeed": 0.001529404233510374, "ICE-US_CT0_ZF0_Move_uniDR_68_zSeed": -2.9666168484776915e-05, "ICE-US_CT0_ZF0_Move_uniDR_68_volSeed": 0.001358689860124986, "ICE-US_CT0_ZM0_Move_uniDR_68_smoothSeed": -0.06631593745375973, "ICE-US_CT0_ZM0_Move_uniDR_68_zSeed": -0.004259213195997182, "ICE-US_CT0_ZM0_Move_uniDR_68_volSeed": 0.038140561224142985, "ICE-US_CT0_CL0_VSR_uniDR_18_smoothSeed": 0.16358502051790136, "ICE-US_CT0_CL0_VSR_uniDR_18_zSeed": -0.013909619184705695, "ICE-US_CT0_CL0_VSR_uniDR_18_volSeed": 0.04551025443509012, "ICE-US_CT0_ICE-EU_BRN0_VSR_uniDR_18_smoothSeed": 0.177451853523284, "ICE-US_CT0_ICE-EU_BRN0_VSR_uniDR_18_zSeed": -0.013008099633638887, "ICE-US_CT0_ICE-EU_BRN0_VSR_uniDR_18_volSeed": 0.04672326141977867, "ICE-US_CT0_ICE-EU_G0_VSR_uniDR_18_smoothSeed": 0.11537164798214822, "ICE-US_CT0_ICE-EU_G0_VSR_uniDR_18_zSeed": -0.02274346491665757, "ICE-US_CT0_ICE-EU_G0_VSR_uniDR_18_volSeed": 0.04766360843075815, "ICE-US_CT0_ICE-US_MME0_VSR_uniDR_5_smoothSeed": 0.27442008557845626, "ICE-US_CT0_ICE-US_MME0_VSR_uniDR_5_zSeed": 0.06437488029421377, "ICE-US_CT0_ICE-US_MME0_VSR_uniDR_5_volSeed": 0.09016775680468393, "ICE-US_CT0_FESB0_VSR_uniDR_5_smoothSeed": -0.0320133853152013, "ICE-US_CT0_FESB0_VSR_uniDR_5_zSeed": -0.03043288364411052, "ICE-US_CT0_FESB0_VSR_uniDR_5_volSeed": 0.09211517381163345, "ICE-US_CT0_ZT0_Move_uniDR_68_smoothSeed": 0.0009561972767301611, "ICE-US_CT0_ZT0_Move_uniDR_68_zSeed": -9.57507350270582e-06, "ICE-US_CT0_ZT0_Move_uniDR_68_volSeed": 0.0005181659206001844}, "ICE-EU_G0": {"ICE-EU_G0_midPrice": 757.5, "Volatility_ICE-EU_G0": 3.5670976215770516, "ICE-EU_G0_lastTS": "2023_12_14_23", "ICE-EU_G0_symbol": "GASF24", "W0_midPrice": 624.7, "Volatility_W0": 1.527714009778841, "W0_symbol": "QWH24", "W0_lastTS": "2023_12_14_13", "ICE-LX_C0_midPrice": 3561.0, "Volatility_ICE-LX_C0": 5.6933460194636965, "ICE-LX_C0_symbol": "QCH24", "ICE-LX_C0_lastTS": "2023_12_14_12", "ALSI0_midPrice": 68926.0, "Volatility_ALSI0": 114.40543839187103, "ALSI0_symbol": "ALJZ23", "ALSI0_lastTS": "2023_12_14_11", "ZN0_midPrice": 112.359375, "Volatility_ZN0": 0.09169215007769244, "ZN0_symbol": "@TYH24", "ZN0_lastTS": "2023_12_15_00", "ZL0_midPrice": 49.9, "Volatility_ZL0": 0.18977384050220228, "ZL0_symbol": "@BOF24", "ZL0_lastTS": "2023_12_14_23", "ICE-EU_G0_ALSI0_Move_uniDR_6_smoothSeed": 45.286970863396384, "ICE-EU_G0_ALSI0_Move_uniDR_6_zSeed": 7.721921592099898, "ICE-EU_G0_ALSI0_Move_uniDR_6_volSeed": 7.720974192005882, "ICE-EU_G0_ICE-LX_C0_VSR_uniDR_68_smoothSeed": -0.021584138128299714, "ICE-EU_G0_ICE-LX_C0_VSR_uniDR_68_zSeed": 0.0007091931285006688, "ICE-EU_G0_ICE-LX_C0_VSR_uniDR_68_volSeed": 0.03706981184360556, "ICE-EU_G0_W0_VSR_uniDR_68_smoothSeed": -0.15562102335845523, "ICE-EU_G0_W0_VSR_uniDR_68_zSeed": -0.006675532586679785, "ICE-EU_G0_W0_VSR_uniDR_68_volSeed": 0.03137524891613583, "ICE-EU_G0_ZN0_VSR_uniDR_35_smoothSeed": 0.25395420196911245, "ICE-EU_G0_ZN0_VSR_uniDR_35_zSeed": 0.018478280263467897, "ICE-EU_G0_ZN0_VSR_uniDR_35_volSeed": 0.05772047756275923, "ICE-EU_G0_ZL0_Move_uniDR_68_smoothSeed": -0.010133658673514805, "ICE-EU_G0_ZL0_Move_uniDR_68_zSeed": 0.00019428696050729073, "ICE-EU_G0_ZL0_Move_uniDR_68_volSeed": 0.00400109360225102}, "ICE-US_KC0": {"ICE-US_KC0_midPrice": 190.2, "Volatility_ICE-US_KC0": 1.0174683744872728, "ICE-US_KC0_lastTS": "2023_12_14_14", "ICE-US_KC0_symbol": "@KCH24", "RS1_midPrice": 667.2, "Volatility_RS1": 2.62008285054329, "RS1_symbol": "@RSH24", "RS1_lastTS": "2023_12_14_23", "RB0_midPrice": 2.1288, "Volatility_RB0": 0.014436307580432557, "RB0_symbol": "QRBF24", "RB0_lastTS": "2023_12_14_23", "RS0_midPrice": 667.2, "Volatility_RS0": 2.691369489325683, "RS0_symbol": "@RSH24", "RS0_lastTS": "2023_12_14_23", "NG0_midPrice": 2.434, "Volatility_NG0": 0.0433214025983995, "NG0_symbol": "QNGF24", "NG0_lastTS": "2023_12_14_23", "ICE-US_KC0_RB0_Move_uniDR_35_smoothSeed": 0.0005133446303888169, "ICE-US_KC0_RB0_Move_uniDR_35_zSeed": -7.412377824619907e-05, "ICE-US_KC0_RB0_Move_uniDR_35_volSeed": 0.000407148881939198, "ICE-US_KC0_NG0_Move_uniDR_35_smoothSeed": -0.0005375811744436536, "ICE-US_KC0_NG0_Move_uniDR_35_zSeed": -2.4288738608178493e-05, "ICE-US_KC0_NG0_Move_uniDR_35_volSeed": 0.0013851489130100828, "ICE-US_KC0_RS1_Basis_uniDR_69_smoothSeed": 198.824993209544, "ICE-US_KC0_RS1_Basis_uniDR_69_zSeed": 5.6958825049651365, "ICE-US_KC0_RS1_Basis_uniDR_69_volSeed": 0.6041549436264063}}, "logs": {"ZN0": ["2023_12_15_00", false, 112.359375, 1, 0.08915710091724607, 0.015625, -0.0051866613983959095, -0.6497177351379166, 0, 0, 1, -0.3559956731229873, 2, 112359.38, 1], "ZF0": [], "FBTP0": [], "AP0": ["2023_12_14_23", false, 7463.0, 1, 12.905251571333347, 2.0, 1.257220985426342, 0.007413985073684775, 0, 1, 1, 0.6309774530795553, 2, 333278.74, 0.6716], "ES0": ["2023_12_15_00", false, 4778.25, 1, 6.874099236199754, 3.75, -0.5185642479277143, -0.010906289062005905, 0, -1, 1, -0.3944693671153756, 3, 238912.5, 1], "FSMI0": [], "FTI0": [], "ALSI0": [], "ZC0": [], "ZS0": [], "ZM0": [], "ZW0": ["2023_12_15_00", false, 616.75, 1, 3.6459796689244444, -3.75, -0.021568510833391383, -0.0013017409517249534, 0, -1, 3, -0.0775307297036899, 14, 30837.5, 1], "KE0": ["2023_12_14_23", false, 638.5, 1, 3.7118242455006034, -1.0, -0.10557715950807317, -0.005814360368547772, 0, -2, 2, -0.30082576410118855, 8, 31975.0, 1], "LE0": [], "CL0": ["2023_12_15_00", false, 72.31, 1, 0.31695282400182395, 0.04000000000000625, 0.008022384979727543, 0.07960349600376533, 0, 0, 1, 0.23284250184646915, 2, 72310.0, 1], "HO0": ["2023_12_14_23", false, 2.6141, 1, 0.010662978926371169, 0.0037000000000002586, 7.467776846986018e-05, 0.3419355278389558, 0, 0, 1, 0.06341902410858713, 2, 109636.8, 1], "RS0": ["2023_12_14_23", false, 667.2, 1, 2.293807046022006, 0.3000000000000682, -0.0895439233383974, -0.016255725197487986, 0, -3, 6, -0.11002331806513785, 29, 9959.62, 1.3392079923932987], "W0": [], "ICE-US_CT0": ["2023_12_14_23", false, 81.29, 1, 0.356598057333445, 0.3100000000000023, 0.0003645948401757255, -0.018037165288744987, -1, 1, 3, -0.04031975931478047, 15, 40490.0, 1], "ICE-EU_G0": [], "ICE-US_KC0": []}}